{"text": "RECORD #197702\n091761834 | CMLMC | 07592927 | | 3017067 | 9/27/2006 12:00:00 AM | b | | DIS | Admission Date: 4/8/2006 Report Status:\nDischarge Date: 5/3/2006\n****** FINAL DISCHARGE ORDERS ******\nSCHEFFER , FELTON 128-55-71-1\nPend\nService: CAR\nDISCHARGE PATIENT ON: 2/22/06 AT 06:00 PM\nCONTINGENT UPON Not Applicable\nWILL D/C ORDER BE USED AS THE D/C SUMMARY: YES\nAttending: TARKA , FELTON CHAD , M.D.\nCODE STATUS:\nFull code\nDISPOSITION: Home\nDISCHARGE MEDICATIONS:\nACETYLSALICYLIC ACID 81 MG PO DAILY\nStarting Today ( 6/17 )\nATENOLOL 100 MG PO BID Starting Today ( 6/17 )\nLIPITOR ( ATORVASTATIN ) 40 MG PO DAILY\nStarting Today ( 6/17 )\nInstructions: Please cut your lipitor 80mg tablet in half\nusing your pill cutter.\nZETIA ( EZETIMIBE ) 10 MG PO DAILY\nHYDROCHLOROTHIAZIDE 50 MG PO DAILY\nIMDUR ER ( ISOSORBIDE MONONITRATE ( SR ) ) 120 MG PO DAILY\nFood/Drug Interaction Instruction\nGive on an empty stomach ( give 1hr before or 2hr after\nfood )\nLISINOPRIL 40 MG PO DAILY Starting Today ( 6/17 )\nInstructions: Please take one 40mg tablet daily.\nAlert overridden: Override added on 2/22/06 by :\nPOTENTIALLY SERIOUS INTERACTION: POTASSIUM CHLORIDE &amp;\nLISINOPRIL\nPOTENTIALLY SERIOUS INTERACTION: POTASSIUM CHLORIDE &amp;\nLISINOPRIL\nPOTENTIALLY SERIOUS INTERACTION: POTASSIUM CHLORIDE &amp;\nLISINOPRIL\nPOTENTIALLY SERIOUS INTERACTION: POTASSIUM CHLORIDE &amp;\nLISINOPRIL Reason for override:\nNIFEDIPINE ( SUSTAINED RELEASE ) ( NIFEDIPINE ( S... )\n90 MG PO DAILY Food/Drug Interaction Instruction\nAvoid grapefruit unless MD instructs otherwise.\nNITROGLYCERIN 1/150 ( 0.4 MG ) 1 TAB SL Q5MIN X 3 doses\nPRN Chest Pain\nDIET: House / Low chol/low sat. fat\nDIET: House / ADA 2100 cals/dy\nRETURN TO WORK: After Appt with local physician\nFOLLOW UP APPOINTMENT( S ):\nPCP Dr. Deangelo Shoobridge Yshealt Hill Healthcare Center 2/10 at 3pm scheduled ,\nCardiologist Dr. Kendrick Lowin 230-881-8027 Meaert Mo Rynei Hospital 5/12 at 8: scheduled ,\nCardiac catheterization at AV , please go to Admitting in the lobby to register at 7:30am , do not eat breakfast 7/21 at 7:30am scheduled ,\nALLERGY: GEMFIBROZIL\nADMIT DIAGNOSIS:\nchest pain\nPRINCIPAL DISCHARGE DIAGNOSIS ;Responsible After Study for Causing Admission )\nb\nOTHER DIAGNOSIS;Conditions , Infections , Complications , affecting Treatment/Stay\nHTN HYPERLIPIDEMIA\nATYPICAL C.PAIN STEMI 5/23 Echo 5/23 EF 60% , mild LVH , RV with\nHK mi 3/6 s/p RCA stent\n3/6 DM ( diet-controlled ) chronic renal insufficiency ( chronic renal\ndysfunction )\nOPERATIONS AND PROCEDURES:\nNone.\nOTHER TREATMENTS/PROCEDURES ( NOT IN O.R. )\nstress test\nBRIEF RESUME OF HOSPITAL COURSE:\n***CC: Chest pain\n***HPI: 52M pastor h/o NIDDM , HTN , hypercholesterolemia , and known\n3-vessel CAD s/p NSTEMI ( 2002 ) w/ failed angioplasty to Marg1 occlusion ,\nCYPHER stent to RCA ( 2003 ) , recurrent unstable angina w/ last cath ( 0/0 )\nw/ diffuse CAD precluding CABG/PTCA but w/ patent RCA stent , last\nperfusion stress ( 0/0 ) w/ moderate rev ischemia in Diag/PDA territories ,\nETT ( 6/10 ) w/ CP and ST depression in inferolateral leads , last Echo\n( 0/0 ) w/ EF 55-60% no WMA , physically active at baseline p/w CP. At\n8:45am pt first noticed left-sided substernal pain/pressure after\nbreakfast and coffee while walking to living room , well-circumscribed ,\n4/10 intensity , constant , w/o radiation to jaw/arm/back , worse on deep\ninspiration , w/ associated nausea and dizziness. Pt sat down w/ pain\n2/10 , administered nitro spray x2 w/o relief , wife measured BP 158/90s\n( usu 140/85 ). No other sx , but pt describes pain as similar but less\nintense than that experienced in 2002 MI. Denies h/o CP since then\ndespite recently active baseline ( yesterday washing windows/ climbing\nladders , over last months doing cement work in church ) , but notes DOE\nwith walking 2 blocks uphill. Pt reports frequent prophylactic use of\nnifedipine sprays immediately prior to exertion/activity.On 6/1/06 , pt\nwas evaluated for CABG by surgeon Dr. Ashley Starcher , who noted possible\ncandidacy for combined CABG/TMLR since diagonal likely too small to\nbypass. Since pt was asymptomatic w/ nlm LVEF , he has remained on medical\ntherapy. Last visit to PCP Dr. Rob Holzinger at Thbull Carmonte Medical Center\non 11/29/06 was routine , and he is followed by cardiologist Dr. Heath Koerner\n****ED Course: CP spontaneously resolved ( total duration 1hr ) prior to\narrival by car at BMC ED where VS Afebrile HR118 BP 150/68 RR18\n98%RA. Received lopressor 5mg IV x1` HR 80s , ASA. ECG showed NSR@95bpm w/\nST depression and T wave flattening in 2 , 3 , V5 , V6 different from prior ECG\n10/0/06 , high voltage and LVH also present. Received heparin 5000U bolus\nx1 and 1500U/hr infusion. Labs: CK 647 ( h/o chronically elev CKs\n400-1300s ) , CK-MB 3.8 , TnI &lt;0.10 , WBC 6.41 , Hct 44.2 , Plt 228 , Cre 1.3 ,\nPTT 33.6.\n****ROS: Pt notes ( intentional ) 20lb weight loss ( 215`195lb ) over last\nmonth since starting metformin. Pertinent negatives include no systemic\ncomplaints/ LOC/ change in vision/ diaphoresis/ cough/ orthopnea/ edema/\nleg pain or claudication/ change in GU/GI habits.\n****PMH/PSH:\n*CAD ( 3-vessel as below )\n-s/p NSTEMI ( 2002 ) w/ recurrent UA\n-L Cath 5/23 \"Diffuse CAD precludes CABG/PTCA;\" RCA stents patent;\nDiag1 ostial 80% , Diag2 prox 80% , LCx prox 40% , LCx mid 50% , Marg1 ostial\n100% ( collat LCx ) , Marg2 ostial 50% , RCA dist 100% ( collat to PDA from\nRCA intracoronary ) , no sig LM/LAD lesions\nL cath 1/11 Failed angioplasty Marg1 ostial 100% ( inability to\ncross occlusion ) , no sig LM/LCx/LAD/RCA lesions\nL cath 4/8 Cypher stent to RCA; RCA distal 100% , RCA prox 60% ,\nRCA mid 85% , RCA mid 95% , LCx mid 35% , Marg1 ostial 100% 2/12\nFailed angioplasty to Marg1 100%; RCA 90% , PDA 100%\n- Stress: 8/5 ETT , std Bruce , 6.0 METS: 4/10 CP 3min , 1mm ST dep\nin 2 , 3 , F , V5-6 , Duke -7 ( mod ) , HRR 13 5/23 Exercise MIBI SPECT , 7.0\nMETS: CP , 1mm ST dep in 2 , 3 , F , V5-6 , 65% APHR , rev ischemia in\nDiag , PDA territories ( sum stress/diff 7/7 mild/mod )\n3/18 Ex MIBI SPECT , 7.6 METS , CP , no perf defect\n10/21 Ex MIBI SPECT , 6.4 METS , CP , rev isch LCx territory , sum\nstress/diff 7/5 )\n8/11 Ex MIBI SPECT , 7.6 METS , CP , rev isch LCx , PDA territory\nscar , sum stress/diff 15/11 ) 0/21 Adeno MIBI SPECT , no perf defect ,\nsum stress 2\n11/17 ETT , std Bruce 56%APHR , CP 4min , 1mm ST dep 2 , 3 , F\n-Echo: 5/23 LV nlm size , EF 55-60% , no WMA , thick MV , mild\nRVE/RAE , trace MR/PR 10/7 ( Stress ): EF 55-60% , nlm ventricular\ncontractility 2/12 EF 55-60% , mild concentric LV hypertrophy , no\nWMA , thick MV , trace MR/PR\n-CT/A Ch/Abd/Pel ( 6/10 ): nlm Ao w/o dissection/aneurysm\n*NIDDM ( 2005 ) , HgbA1c 7.1 ` Metformin 1mo ago\n*Hypercholesterolemia ( &lt;2000 ) -h/o elev CKs ( 400-1300s on gemfibrozil ,\nstatins )\n*HTN ( 1996 )\n*chronic renal insufficiency , bl Cre 1.2\nrefused renal MRA 11/11\n*Carotid stenoses ( 2006 ) , R ICA 55-60% , L ICA &gt;50% asx\n*Erectile dysfunction s/p penile prosthesis placement\n****MEDS ( pre- admission ): ASA 81mg PO qdayAtenolol 100mg PO\nBIDLisinopril 80mg PO qdayImdur ER ( isosorbide ) 120mg PO qdayLipitor 80mg\nPO qdayZetia ( ezetimibe ) 10mg PO qdayHCTZ 50mg PO qdayMetformin 500mg PO\nqdayNifedipine ER 90mg PO qdayNitroglycerin 0.4MG/SPRAY PO x1 PRN chest\npain\n****ALLERGIES: Gemfibrozil ` elev CK ( 400-1300s )\n****SH: Denies h/o tob/EtOH/drugs. Pt lives in Orlwoodank w/ wife of 30yrs ,\n3 grown children , 5 grandchildren all healthy. Pastor at Leighfay Che O Broke Lo x30yrs.\n****FH: Significant h/o DM , HTN. Father 91yo h/o MI ( 62yo ) , CVA ( 76yo ) ,\nHTN , DM. Mother 80yo h/o HTN , DM , identical twin h/o HTN , DM. Denies h/o\ncancer.\n****PHYSICAL EXAM:VS: T 98 HR 63 reg BP 126/67 RR 18 O2Sat 98%\nRAGen: black male in NAD , lying in bed , pleasantHEENT: PEERLA , MMM ,\noropharynx clearCV: nlm S1 , S2 , no murmur JVP ~8cm , No obvious\ncarotid bruits bilat , symmetric No bruit at fem groove bilat , DP 2+\nbilatResp: mild bibasilar crackles , no wheeze , no accessory muscle\nuseAbd: Soft , NT , obeseSkin &amp; Ext: WWP , no edema , nails unremarkable\n( remnant red paint )Neuro: A&amp;Ox3 , CN II-XII grossly intact\n****ADMISSION LABS: WBC 6.4 , hct 44 , Cr 1.3 , enz neg , ddimer 530s\n****ADMISSION EKG ( 8/10 ): NSR@95bpm w/ ST depression and T wave\nflattening in 2 , 3 , V5 , V6 different from prior ECG 10/0/06 , high voltage\nand LVH also present.Radiology:\n****ADMISSION CXR ( 8/10 ): nlm heart , clear lungs , no\nPTX/edemaMicrobiology:UA , USed ( 8/10 ): WNL\n****STUDIES:\n-ETT MIBI: abnormal imaging - preliminary results showed that he stopped\nafter 5 minutes due to chest pain , 1mm ST depressions in inferior and\nlateral leads , and mild ischemia in Diag1 territory which raises concern\nfor balanced ischemia.\n****ASSESSMENT and PLAN:\n52M pastor w/ unstable angina in setting of known 3-vessel CAD s/p stent\nto RCA '03 last cath 3 of May w/ diffuse CAD precluding CABG/PTCA , medically\nmanaged and asymptomatic until present. Vitals stable , enzymes negative ,\nstress test with abnormal perfusion.\nCV *ischemia* Known 3vd s/p stent. Rest chest pain. NSSTT\ninferolaterally , Negative enzymes. Stress test prelim read shows\nabnormal perfusion: stopped after 5 minutes due to chest pain , 1mm ST\ndepressions in inferior and lateral leads , mild ischemic in Diag1\nterritory which is concerning for \"balanced ischemia\" rather than an\nimprovement compared to previous nuclear imaging in 0/12 Inpatient cardiac\ncathterization advised by medical\nteam but refused by pt. Pt. opts to be discharged and follow up for\nelective cardiac catheterization on Tue 4/10 The risks of this plan were\ndiscussed with him by his outpatient cardiologist , Dr. Marion Brzostowski\nWhile an inpatient , patient was medically managed w/ ASA , hep gtt , statin ,\nbb , acei. Lipid panel checked with TC 101 , tri 89 , HDL 41 , LDL 31. Statin\ndose lowered for persistently high CK. Acei dose lowered as marginal BP\neffect above ULN dose. Heparin gtt was discontinued prior to discharge.\nOn discharge , pt. instructed to take ASA , bb , acei , imdur , lipitor , zetia.\nHe was advised to discontinue metformin for 2 days before and 2 days\nafter cardiac catheterization. He was advised to be minimally active\nand to call his physician or 911 if he experienced any further chest pain ,\nshortness of breath , palpitations , lightheadedness or any other symptoms c\nconcerning to him.\n*pump* Appears euvolemic. Nl EF. HTN controlled as above with bb , acei.\n*rhythm* Sinus rhythm. Pt continued on home atenolol.\nRENAL: *CRI* Possibly related to HTN/DM. Pt. w/ Cr 1.3 , within baseline.\nENDO: *DM* Metformin held. Pt. rx'ed w/ SSI. HgA1c checked and pending.\nTSH also checked and pending.\nPROPH: nexium/heparin gtt\nCODE: FULL\nDISPOSITION: Pt discharged to home with plans for elective outpatient\ncardiac cathterization , cardiology , PCP f/u\nDISCHARGE STATUS: afebrile P 50s-90s SBP 120s/70s sat RA\nExam w/o significant change from admission. Labs w/ Hct 40.2 , Cr 1.2\nADDITIONAL COMMENTS: You were admitted with chest pain. Your blood tests show that you did not\nhave a heart attack. You had a stress test which is concerning for regions\nof your heart not receiving enough blood flow. The medical team\nadvised cardiac catheterization during this admission , but your plan is to\ngo home today and return for an elective outpatient cardiac catherization\non Tuesday 7/21 at 7:30am. Please go to the Admitting Office on the Ins to register. Do not eat anything after midnight Monday\nnight. Do not eat breakfast or drink liquids after midnight. Your\nmedications have been changed as follows: a ) stop\ntaking metformin for 2 days before and 2 days after your cardiac\ncatheterization b ) take lisinopril 40 mg daily instead of 80 mg daily\nc ) take lipitor 40 mg daily instead of 80 mg daily. Do not do any\nsignificant exertion until your cardiac catheterization. Call your doctor\nor go to the ED if you experience any further chest pain , dizziness ,\npalpitations , shortness of breath , or other symptoms concerning to you.\nDISCHARGE CONDITION: Fair\nTO DO/PLAN:\nPCP/cards:\n-f/u official results of stress test\n-f/u results of outpatient cardiac catheterization\n( prehydration/mucomyst peri-cath )\n-f/u results of HgA1c and TSH\nNo dictated summary\nENTERED BY: WEYKER , MARCUS A , M.D. ( LI54 ) 2/22/06 @ 05\n****** END OF DISCHARGE ORDERS ******\n[report_end]\n", "annotations": [{"medication_name": "acetylsalicylic acid", "medication_dosage": "81 mg", "mode": "po", "frequency": "daily", "line": "16"}, {"medication_name": "atenolol", "medication_dosage": "100 mg", "mode": "po", "frequency": "bid", "line": "18"}, {"medication_name": "lipitor ( atorvastatin )", "medication_dosage": "40 mg", "mode": "po", "frequency": "daily", "line": "19"}, {"medication_name": "lipitor", "medication_dosage": "80mg tablet in half", "mode": "", "frequency": "", "line": "21"}, {"medication_name": "zetia ( ezetimibe )", "medication_dosage": "10 mg", "mode": "po", "frequency": "daily", "line": "23"}, {"medication_name": "hydrochlorothiazide", "medication_dosage": "50 mg", "mode": "po", "frequency": "daily", "line": "24"}, {"medication_name": "imdur er ( isosorbide mononitrate ( sr ) )", "medication_dosage": "120 mg", "mode": "po", "frequency": "daily", "line": "25"}, {"medication_name": "lisinopril", "medication_dosage": "one 40mg tablet", "mode": "po", "frequency": "daily.", "line": "29"}, {"medication_name": "lisinopril", "medication_dosage": "40 mg", "mode": "po", "frequency": "daily", "line": "29"}, {"medication_name": "potassium chloride", "medication_dosage": "", "mode": "", "frequency": "", "line": "32"}, {"medication_name": "lisinopril", "medication_dosage": "", "mode": "", "frequency": "", "line": "33"}, {"medication_name": "potassium chloride", "medication_dosage": "", "mode": "", "frequency": "", "line": "34"}, {"medication_name": "lisinopril", "medication_dosage": "", "mode": "", "frequency": "", "line": "35"}, {"medication_name": "potassium chloride", "medication_dosage": "", "mode": "", "frequency": "", "line": "36"}, {"medication_name": "lisinopril", "medication_dosage": "", "mode": "", "frequency": "", "line": "37"}, {"medication_name": "potassium chloride", "medication_dosage": "", "mode": "", "frequency": "", "line": "38"}, {"medication_name": "lisinopril", "medication_dosage": "", "mode": "", "frequency": "", "line": "39"}, {"medication_name": "nifedipine ( sustained release ) ( nifedipine ( s... )", "medication_dosage": "90 mg", "mode": "po", "frequency": "daily", "line": "40"}, {"medication_name": "nitroglycerin 1/150 ( 0.4 mg )", "medication_dosage": "1 tab", "mode": "sl", "frequency": "q5min x 3 doses prn", "line": "43"}, {"medication_name": "nitro spray", "medication_dosage": "", "mode": "", "frequency": "x2", "line": "80"}, {"medication_name": "nifedipine sprays", "medication_dosage": "", "mode": "", "frequency": "", "line": "86"}, {"medication_name": "lopressor", "medication_dosage": "5mg", "mode": "iv", "frequency": "", "line": "94"}, {"medication_name": "asa", "medication_dosage": "", "mode": "", "frequency": "", "line": "94"}, {"medication_name": "heparin", "medication_dosage": "5000u", "mode": "bolus", "frequency": "x1", "line": "96"}, {"medication_name": "heparin", "medication_dosage": "1500u/hr", "mode": "infusion", "frequency": "", "line": "96"}, {"medication_name": "metformin", "medication_dosage": "", "mode": "", "frequency": "", "line": "101"}, {"medication_name": "metformin", "medication_dosage": "", "mode": "", "frequency": "", "line": "132"}, {"medication_name": "gemfibrozil", "medication_dosage": "", "mode": "", "frequency": "", "line": "133"}, {"medication_name": "statins", "medication_dosage": "", "mode": "", "frequency": "", "line": "134"}, {"medication_name": "asa", "medication_dosage": "81mg", "mode": "po", "frequency": "qdayatenolol", "line": "140"}, {"medication_name": "er ( isosorbide )", "medication_dosage": "120mg", "mode": "po", "frequency": "qdayLipitor", "line": "141"}, {"medication_name": "( ezetimibe )", "medication_dosage": "10mg", "mode": "po", "frequency": "qdayhctz", "line": "142"}, {"medication_name": "er", "medication_dosage": "90mg", "mode": "po", "frequency": "qdayNitroglycerin", "line": "143"}, {"medication_name": "statin", "medication_dosage": "", "mode": "", "frequency": "", "line": "184"}, {"medication_name": "hep gtt", "medication_dosage": "", "mode": "", "frequency": "", "line": "184"}, {"medication_name": "asa", "medication_dosage": "", "mode": "", "frequency": "", "line": "184"}, {"medication_name": "acei", "medication_dosage": "", "mode": "", "frequency": "", "line": "185"}, {"medication_name": "bb", "medication_dosage": "", "mode": "", "frequency": "", "line": "185"}, {"medication_name": "statin", "medication_dosage": "", "mode": "", "frequency": "", "line": "185"}, {"medication_name": "acei", "medication_dosage": "", "mode": "", "frequency": "", "line": "186"}, {"medication_name": "heparin gtt", "medication_dosage": "", "mode": "", "frequency": "", "line": "187"}, {"medication_name": "zetia", "medication_dosage": "", "mode": "", "frequency": "", "line": "188"}, {"medication_name": "imdur", "medication_dosage": "", "mode": "", "frequency": "", "line": "188"}, {"medication_name": "lipitor", "medication_dosage": "", "mode": "", "frequency": "", "line": "188"}, {"medication_name": "acei", "medication_dosage": "", "mode": "", "frequency": "", "line": "188"}, {"medication_name": "bb", "medication_dosage": "", "mode": "", "frequency": "", "line": "188"}, {"medication_name": "asa", "medication_dosage": "", "mode": "", "frequency": "", "line": "188"}, {"medication_name": "metformin", "medication_dosage": "", "mode": "", "frequency": "", "line": "189"}, {"medication_name": "bb", "medication_dosage": "", "mode": "", "frequency": "", "line": "194"}, {"medication_name": "acei", "medication_dosage": "", "mode": "", "frequency": "", "line": "194"}, {"medication_name": "atenolol", "medication_dosage": "", "mode": "", "frequency": "", "line": "195"}, {"medication_name": "metformin", "medication_dosage": "", "mode": "", "frequency": "", "line": "197"}, {"medication_name": "ssi", "medication_dosage": "", "mode": "", "frequency": "", "line": "197"}, {"medication_name": "nexium/heparin", "medication_dosage": "", "mode": "gtt", "frequency": "", "line": "199"}, {"medication_name": "your medications", "medication_dosage": "", "mode": "", "frequency": "", "line": "211"}, {"medication_name": "metformin", "medication_dosage": "", "mode": "", "frequency": "", "line": "213"}, {"medication_name": "lisinopril", "medication_dosage": "40 mg", "mode": "", "frequency": "daily", "line": "214"}, {"medication_name": "lisinopril", "medication_dosage": "80 mg", "mode": "", "frequency": "daily", "line": "214"}, {"medication_name": "lipitor", "medication_dosage": "40 mg", "mode": "", "frequency": "daily ", "line": "215"}, {"medication_name": "lipitor", "medication_dosage": "80 mg", "mode": "", "frequency": "daily.", "line": "215"}]}