{"text": "RECORD #66947\n\n\n165924793 | ARCCH | 42505562 | | 4965709 | 1/30/2007 12:00:00 AM | s/p angioplasty and stenting | | DIS | Admission Date: 11/8/2007 Report Status:\n\nDischarge Date: 4/14/2007\n****** FINAL DISCHARGE ORDERS ******\nCOOLBAUGH , OMAR J. 598-85-46-5\nSouth Dakota\nService: CAR\nDISCHARGE PATIENT ON: 6/21/07 AT 10:00 AM\nCONTINGENT UPON labs/ekg\nWILL D/C ORDER BE USED AS THE D/C SUMMARY: YES\nAttending: KEASER , JR , OMER R. , M.D.\nCODE STATUS:\nFull code\nDISPOSITION: Home\nMEDICATIONS ON ADMISSION:\n1. MYCOPHENOLATE MOFETIL 1000 MG PO BID\n2. OXYBUTYNIN CHLORIDE XL 10 MG PO QD\n3. INSULIN GLARGINE 20 UNITS SC QAM\n4. FUROSEMIDE PO QD\n5. CLOPIDOGREL 75 MG PO QD\n6. PRAVASTATIN 40 MG PO QHS\n7. PREDNISONE 5 MG PO QD\n8. CYCLOSPORINE ( SANDIMMUNE ) 75 MG PO BID\n9. METOPROLOL SUCCINATE EXTENDED RELEASE 50 MG PO QD\n10. FENOFIBRATE ( TRICOR ) 48 MG PO QD\nMEDICATIONS ON DISCHARGE:\nENTERIC COATED ASA 325 MG PO DAILY\nPLAVIX ( CLOPIDOGREL ) 75 MG PO DAILY\nStarting Tomorrow ( 5/25 )\nCYCLOSPORINE ( SANDIMMUNE ) 75 MG PO BID\nFood/Drug Interaction Instruction\nAvoid grapefruit unless MD instructs otherwise.\nGive with meals\nOverride Notice: Override added on 1/17/07 by REGES , FAUSTO T BUCK JERRY , M.D. on order for TRICOR PO ( ref # 438676570 )\nPOTENTIALLY SERIOUS INTERACTION: CYCLOSPORINE &amp;\nFENOFIBRATE , MICRONIZED Reason for override:\npatient home meds Previous override information:\nOverride added on 1/17/07 by KELLETT , WILTON GAYLORD MILO , M.D.\nPOTENTIALLY SERIOUS INTERACTION: PRAVASTATIN SODIUM &amp;\nCYCLOSPORINE Reason for override: patient home meds\nTRICOR ( FENOFIBRATE ( TRICOR ) ) 48 MG PO DAILY\nAlert overridden: Override added on 1/17/07 by RAGONE , JAMAL F BERNARD HOUSTON , M.D.\nPOTENTIALLY SERIOUS INTERACTION: PRAVASTATIN SODIUM &amp;\nFENOFIBRATE , MICRONIZED\nPOTENTIALLY SERIOUS INTERACTION: CYCLOSPORINE &amp;\nFENOFIBRATE , MICRONIZED Reason for override:\npatient home meds Number of Doses Required ( approximate ): 4\nLASIX ( FUROSEMIDE ) 40 MG PO DAILY\nINSULIN GLARGINE 20 UNITS SC DAILY\nTOPROL XL ( METOPROLOL SUCCINATE EXTENDED RELEASE )\n50 MG PO DAILY Food/Drug Interaction Instruction\nTake consistently with meals or on empty stomach.\nNumber of Doses Required ( approximate ): 3\nCELLCEPT ( MYCOPHENOLATE MOFETIL ) 1 , 000 MG PO BID\nFood/Drug Interaction Instruction\nGive on an empty stomach ( give 1hr before or 2hr after\nfood ) Food decreases peak by up to 40%\nTNG 0.4 MG ( NITROGLYCERIN 1/150 ( 0.4 MG ) )\n1 TAB SL Q5MIN X 3 doses PRN Chest Pain\nDITROPAN XL ( OXYBUTYNIN CHLORIDE XL ) 10 MG PO DAILY\nNumber of Doses Required ( approximate ): 3\nPRAVACHOL ( PRAVASTATIN ) 40 MG PO BEDTIME\nFood/Drug Interaction Instruction\nAvoid grapefruit unless MD instructs otherwise.\nOverride Notice: Override added on 1/17/07 by KWAN , JOHNSON A EDMUNDO TAD , M.D. on order for TRICOR PO ( ref # 438676570 )\nPOTENTIALLY SERIOUS INTERACTION: PRAVASTATIN SODIUM &amp;\nFENOFIBRATE , MICRONIZED Reason for override:\npatient home meds Previous override information:\nOverride added on 1/17/07 by LAMOREE , MARCELLUS VICENTE RONALD , M.D.\non order for CYCLOSPORINE ( SANDIMMUNE ) PO ( ref #\n472656194 )\nPOTENTIALLY SERIOUS INTERACTION: PRAVASTATIN SODIUM &amp;\nCYCLOSPORINE Reason for override: patient home meds\nPrevious override information:\nOverride added on 1/17/07 by SLEIMAN , CARTER ERNESTO BRUNO , M.D.\non order for PRAVACHOL PO ( ref # 214437202 )\nPt. has a PROBABLE allergy to SIMVASTATIN; reaction is\nmuscle aches. Reason for override: patient home meds\nPREDNISOLONE SODIUM PHOSPHATE 5MG/5ML 5 MG PO DAILY\nDIET: House / Low chol/low sat. fat\nACTIVITY: light activity , no heavy lifting or driving x 2 days. ok to shower , no swimming or bathing x 5 days\nLift restrictions: Do not lift greater then 10-15 pounds\nFOLLOW UP APPOINTMENT( S ):\nHeart failure Clinic 2-4 weeks ,\nALLERGY: SIMVASTATIN\nADMIT DIAGNOSIS:\ns/p cardiac transplant\nPRINCIPAL DISCHARGE DIAGNOSIS ;Responsible After Study for Causing Admission )\ns/p angioplasty and stenting\nOTHER DIAGNOSIS;Conditions , Infections , Complications , affecting Treatment/Stay\ns/p cardiac transplant 1992 ( S/P cardiac transplant ) Diabetes mellitus\ntype II ( diabetes mellitus type 2 ) Trochanteric bursitis ( trochanteric\nbursitis ) Dyslipidemia ( dyslipidemia ) DJD spine ( OA of cervical\nspine ) Hx vocal cord injury postop Hx gastritis with UGIB ( H/O upper\nGI bleeding ) Hx postop seizure\nOPERATIONS AND PROCEDURES:\nOTHER TREATMENTS/PROCEDURES ( NOT IN O.R. )\ns/p LAD angioplasty and stenting\nBRIEF RESUME OF HOSPITAL COURSE:\n71 year old female that is now 15 years following\ncardiac transplantation , with a multiplicity of medical issues ,\nincluding allograft coronary artery disease , bilateral carotid\ndisease ( underwent carotid stenting in March 2006 ) , History of TIA ,\ndiabetes and significant obesity.Her baseline renal cr was\n1.7. The LCX was stented in June\n2006. Current meds\nincludes CellCept 1000 mg p.o. b.i.d. , prednisone 5 mg\ndaily , cyclosporine 75 mg p.o. b.i.d. , Toprol-XL 50 mg daily , TriCor ,\nonce daily , Pravachol 40 mg daily , Plavix 75 mg daily , Lasix , 40 mg\ndaily , insulin , aspirin , Ditropan 10 mg daily and\nvitamins. Elective cardiac catheterization Was performed\ntoday for her annual post cardiac transplant evaluation revealed\ndouble vessel disease proximal LAD 95% lesion , LeftnCX\n( Proximal ) , 75% lesion CX ( Mid ) , 95% lesion , MARG1 ( Ostial ) , 95%\nlesion . Successful PTCA/Stenting - LAD using XB3.5guide ,\nBMW , which was predilated with a 2mm balloon , 2 DES was used ( 3 by\n18 ) and( 3 by 18 ) cypher stents which was subsequently postdilated to\n3.2 , no residual\nstenosis Right groin access was closed with\nStarclose. PCI of the LAD today and possible planned PCI of\nLCX in 1-3 weeks. Check renal function over the next 2\ndays Plan:\nPCI of the LAD today and possible planned PCI of LCX in 1-3\nweeks. Check renal function over the next 2\ndays\n0/7/07\nUp , eating and voiding well. Ambulating on POD - \"tired\" but no change\nfrom baseline.\nNo Chest pain , shortness of breath , groin or flank pain. No palpitations.\nMultiple questions regarding activity , medications reviewed with patient.\nPHYSICAL EXAM: 96.4 80-90s 110/60 97%ra voiding to BR\nNAD. JVP not elevated.\nCOR RRR , S1S2 , no murmur appreciated\nLungs - CTA bilat , no RRW\nEXT - warm , no edema\nRight Groin-soft , no ecchymosis , no hematoma or bruit. Palpable femoral\npulse.\nEKG: SR at 95 wtih inc RBBB , flat T 1 , L , no change from prior.\nTELE: no tele events\nA/P:\n**CV:12 years post transplant , resume meds per transplant team.\n*CAD: 1 day post Cypher DES to LAD with significant residual disease ,\nplease see cath report for full details. Will need ASA 325 daily x life ,\nPlavix 75 daily for minimum of 12 months and should continue out indef.\nImportance of both stressed and patient understands! SL TNG prn chest\npain. AM enzymes pending.\n*PUMP: no evidence of volume overload , CHF.\n*RHYTHM: no palps , no tachy/brady tele events.\n*HTN: BP well controlled HR up some on Toprol XL 50 , lasix 40.\n*LIPIDS: will cont pravachol 40 , tricor 48.\n**PULM: no issues.\n**RENAL: baseline 1.5 - 1.7 , AM pending. encouraged increased PO intake\nover next several days , if urine output falls she will call , she should\nhave renal fx rechecked on monday with local MD.\n**ENDO: check hgb a1c as outpt. cont insulin\n**DISPO: stable and ready for DC this am pending labs , attending eval.\nFU with Transplant team , they will be in contact regarding date of staged\nPCI to LCx. To call with any concerns. All Questions answered.\nAddendum: renal fx fine but asxatic MB bump to 25 , rechecking and dc if\nstable , keep until tomorrow if up.\nADDITIONAL COMMENTS: -you must take aspirin for life\n-you must take plavix for a minimum of 1 year- DO NOT STOP ASPIRIN OR\nPLAVIX FOR ANY REASON UNLESS SPEAK WITH YOUR CARDIOLOGIST FIRST!!!\n-resume other medications at usual doses\n-you will need your kidney function test on monday 10/23 after receiving\ncontrast- this should be followed by heart transplant clinic\n-drink plenty of fluids over the next several days , if your urine output\nfalls please call.\n-you will need to return for another intervention in the next several\nweeks- this should be set up through transplant clinic\n-call with questions or concerns\nDISCHARGE CONDITION: Stable\nTO DO/PLAN:\nNo dictated summary\nENTERED BY: DANES , CRUZ , M.D. ( XO06 ) 6/21/07 @ 09:39 AM\n****** END OF DISCHARGE ORDERS ******\n[report_end]\n", "annotations": [{"medication_name": "mycophenolate mofetil", "medication_dosage": "1000 mg", "mode": "po", "frequency": "bid", "line": "19"}, {"medication_name": "oxybutynin chloride xl", "medication_dosage": "10 mg", "mode": "po", "frequency": "qd", "line": "20"}, {"medication_name": "insulin glargine", "medication_dosage": "20 units", "mode": "sc", "frequency": "qam", "line": "21"}, {"medication_name": "furosemide", "medication_dosage": "", "mode": "po", "frequency": "qd", "line": "22"}, {"medication_name": "clopidogrel", "medication_dosage": "75 mg", "mode": "po", "frequency": "qd", "line": "23"}, {"medication_name": "pravastatin", "medication_dosage": "40 mg", "mode": "po", "frequency": "qhs", "line": "24"}, {"medication_name": "prednisone", "medication_dosage": "5 mg", "mode": "po", "frequency": "qd", "line": "25"}, {"medication_name": "cyclosporine ( sandimmune )", "medication_dosage": "75 mg", "mode": "po", "frequency": "bid", "line": "26"}, {"medication_name": "metoprolol succinate extended release", "medication_dosage": "50 mg", "mode": "po", "frequency": "qd", "line": "27"}, {"medication_name": "fenofibrate ( tricor )", "medication_dosage": "48 mg", "mode": "po", "frequency": "qd", "line": "28"}, {"medication_name": "enteric coated asa", "medication_dosage": "325 mg", "mode": "po", "frequency": "daily", "line": "30"}, {"medication_name": "plavix ( clopidogrel )", "medication_dosage": "75 mg", "mode": "po", "frequency": "daily", "line": "31"}, {"medication_name": "cyclosporine ( sandimmune )", "medication_dosage": "75 mg", "mode": "po", "frequency": "bid", "line": "33"}, {"medication_name": "tricor", "medication_dosage": "", "mode": "po", "frequency": "", "line": "37"}, {"medication_name": "cyclosporine", "medication_dosage": "", "mode": "", "frequency": "", "line": "38"}, {"medication_name": "fenofibrate , micronized", "medication_dosage": "", "mode": "", "frequency": "", "line": "39"}, {"medication_name": "micronized", "medication_dosage": "", "mode": "", "frequency": "", "line": "39"}, {"medication_name": "home meds", "medication_dosage": "", "mode": "", "frequency": "", "line": "40"}, {"medication_name": "pravastatin sodium", "medication_dosage": "", "mode": "", "frequency": "", "line": "42"}, {"medication_name": "home meds", "medication_dosage": "", "mode": "", "frequency": "", "line": "43"}, {"medication_name": "cyclosporine", "medication_dosage": "", "mode": "", "frequency": "", "line": "43"}, {"medication_name": "tricor ( fenofibrate ( tricor ) )", "medication_dosage": "48 mg", "mode": "po", "frequency": "daily", "line": "44"}, {"medication_name": "pravastatin sodium", "medication_dosage": "", "mode": "", "frequency": "", "line": "46"}, {"medication_name": "fenofibrate , micronized", "medication_dosage": "", "mode": "", "frequency": "", "line": "47"}, {"medication_name": "cyclosporine", "medication_dosage": "", "mode": "", "frequency": "", "line": "48"}, {"medication_name": "fenofibrate , micronized", "medication_dosage": "", "mode": "", "frequency": "", "line": "49"}, {"medication_name": "lasix ( furosemide )", "medication_dosage": "40 mg", "mode": "po", "frequency": "daily", "line": "51"}, {"medication_name": "insulin glargine", "medication_dosage": "20 units", "mode": "sc", "frequency": "daily", "line": "52"}, {"medication_name": "toprol xl ( metoprolol succinate extended release )", "medication_dosage": "50 mg", "mode": "po", "frequency": "daily", "line": "53"}, {"medication_name": "cellcept ( mycophenolate mofetil )", "medication_dosage": "1 , 000 mg", "mode": "po", "frequency": "bid", "line": "57"}, {"medication_name": "tng 0.4 mg ( nitroglycerin 1/150 ( 0.4 mg ) )", "medication_dosage": "1 tab", "mode": "sl", "frequency": "q5min x 3 doses prn", "line": "61"}, {"medication_name": "ditropan xl ( oxybutynin chloride xl )", "medication_dosage": "3 doses", "mode": "", "frequency": "prn", "line": "63"}, {"medication_name": "pravachol ( pravastatin )", "medication_dosage": "40 mg", "mode": "po", "frequency": "bedtime", "line": "65"}, {"medication_name": "tricor", "medication_dosage": "", "mode": "po", "frequency": "", "line": "68"}, {"medication_name": "pravastatin sodium", "medication_dosage": "", "mode": "", "frequency": "", "line": "69"}, {"medication_name": "fenofibrate , micronized", "medication_dosage": "", "mode": "", "frequency": "", "line": "70"}, {"medication_name": "home meds", "medication_dosage": "", "mode": "", "frequency": "", "line": "71"}, {"medication_name": "cyclosporine ( sandimmune )", "medication_dosage": "", "mode": "po", "frequency": "", "line": "73"}, {"medication_name": "pravastatin sodium", "medication_dosage": "", "mode": "", "frequency": "", "line": "75"}, {"medication_name": "cyclosporine", "medication_dosage": "", "mode": "", "frequency": "", "line": "76"}, {"medication_name": "home meds", "medication_dosage": "", "mode": "", "frequency": "", "line": "76"}, {"medication_name": "pravachol", "medication_dosage": "", "mode": "po", "frequency": "", "line": "79"}, {"medication_name": "prednisolone sodium phosphate 5mg/5ml", "medication_dosage": "5 mg", "mode": "po", "frequency": "daily", "line": "82"}, {"medication_name": "prednisone", "medication_dosage": "5 mg", "mode": "", "frequency": "daily", "line": "110"}, {"medication_name": "cellcept", "medication_dosage": "1000 mg", "mode": "p.o.", "frequency": "b.i.d.", "line": "110"}, {"medication_name": "toprol-xl", "medication_dosage": "50 mg", "mode": "", "frequency": "daily", "line": "111"}, {"medication_name": "cyclosporine", "medication_dosage": "75mg", "mode": "p.o.", "frequency": "b.i.d.", "line": "111"}, {"medication_name": "tricor", "medication_dosage": "", "mode": "", "frequency": "once daily", "line": "111"}, {"medication_name": "lasix", "medication_dosage": "40 mg", "mode": "", "frequency": "daily", "line": "112"}, {"medication_name": "plavix", "medication_dosage": "75 mg", "mode": "", "frequency": "daily", "line": "112"}, {"medication_name": "pravachol", "medication_dosage": "40 mg", "mode": "", "frequency": "daily", "line": "112"}, {"medication_name": "aspirin", "medication_dosage": "", "mode": "", "frequency": "", "line": "113"}, {"medication_name": "ditropan", "medication_dosage": "10 mg", "mode": "", "frequency": "daily", "line": "113"}, {"medication_name": "insulin", "medication_dosage": "", "mode": "", "frequency": "", "line": "113"}, {"medication_name": "vitamins.", "medication_dosage": "", "mode": "", "frequency": "", "line": "114"}, {"medication_name": "asa", "medication_dosage": "325", "mode": "", "frequency": "daily", "line": "146"}, {"medication_name": "plavix", "medication_dosage": "75", "mode": "", "frequency": "daily", "line": "147"}, {"medication_name": "tng", "medication_dosage": "", "mode": "sl", "frequency": "prn", "line": "148"}, {"medication_name": "lasix", "medication_dosage": "40.", "mode": "", "frequency": "", "line": "152"}, {"medication_name": "toprol xl", "medication_dosage": "50", "mode": "", "frequency": "", "line": "152"}, {"medication_name": "pravachol", "medication_dosage": "40", "mode": "", "frequency": "", "line": "153"}, {"medication_name": "tricor", "medication_dosage": "48.", "mode": "", "frequency": "", "line": "153"}, {"medication_name": "insulin", "medication_dosage": "", "mode": "", "frequency": "", "line": "158"}, {"medication_name": "aspirin", "medication_dosage": "", "mode": "", "frequency": "", "line": "164"}, {"medication_name": "plavix", "medication_dosage": "", "mode": "", "frequency": "", "line": "165"}, {"medication_name": "aspirin", "medication_dosage": "", "mode": "", "frequency": "", "line": "165"}, {"medication_name": "plavix", "medication_dosage": "", "mode": "", "frequency": "", "line": "166"}, {"medication_name": "other medications", "medication_dosage": "", "mode": "", "frequency": "", "line": "167"}]}