{"text": "RECORD #940794\n\n\n750216362 | TMH | 21370582 | | 6716015 | 2/27/2006 12:00:00 AM | Non cardiac chest pain | | DIS | Admission Date: 9/21/2006 Report Status:\n\nDischarge Date: 2/11/2006\n****** FINAL DISCHARGE ORDERS ******\nLANTON , ORVAL 313-51-70-4\nBufft\nService: MED\nDISCHARGE PATIENT ON: 9/11/06 AT 05:00 PM\nCONTINGENT UPON Not Applicable\nWILL D/C ORDER BE USED AS THE D/C SUMMARY: YES\nAttending: BECKETT , COLIN WALLY , M.D.\nCODE STATUS:\nFull code\nDISPOSITION: Rehabilitation\nDISCHARGE MEDICATIONS:\nACEBUTOLOL HCL 400 MG PO DAILY Starting IN AM ( 8/10 )\nFood/Drug Interaction Instruction\nTake consistently with meals or on empty stomach.\nALLOPURINOL 100 MG PO DAILY\nVITAMIN C ( ASCORBIC ACID ) 500 MG PO BID\nCALCIUM CARBONATE ( 500 MG ELEMENTAL CA++ ) 500 MG PO BID\nCIPROFLOXACIN 250 MG PO Q12H X 4 doses\nStarting Today ( 5/28 ) Food/Drug Interaction Instruction\nAdminister iron products a minimum of 2 hours before or\nafter a levofloxacin or ciprofloxacin dose dose\nIf on tube feeds , please cycle ( hold 1 hr before to 2 hr\nafter ) Take 2 hours before or 2 hours after dairy products.\nDIGOXIN 0.125 MG PO DAILY\nCOLACE ( DOCUSATE SODIUM ) 100 MG PO BID\nLOVENOX ( ENOXAPARIN ) 120 MG SC BEDTIME\nTARCEVA ( ERLOTINIB ) 100 mg PO DAILY\n( HT: 61.0in. 154.9cm. WT: 129.5kg. BSA: 2.20 )\nPrimary DX: chest pain Day 1: 0/11/06\nPrevious- Weight:136kg BSA:2.24\nAdmit- Weight:129.5kg BSA:2.20\nFOLIC ACID 1 MG PO DAILY\nFUROSEMIDE 40 MG PO DAILY Starting IN AM ( 4/9 )\nDILAUDID ( HYDROMORPHONE HCL ) 0.5 MG PO Q4H PRN Pain\nAlert overridden: Override added on 9/11/06 by\nBORSH , WADE M. , M.D.\non order for DILAUDID PO ( ref # 925975305 )\nPt. has a PROBABLE allergy to PERCOCET; reaction is\nUnknown. Reason for override: aware\nPrevious Alert overridden\nOverride added on 9/11/06 by WILBANKS , JASPER C. , M.D.\nPOTENTIALLY SERIOUS INTERACTION: TRAMADOL HCL &amp;\nHYDROMORPHONE HCL Reason for override: aware\nLIDODERM 5% PATCH ( LIDOCAINE 5% PATCH ) 1 EA TP DAILY\nInstructions: 12h on/12h off , apply to L breast\nPRAVACHOL ( PRAVASTATIN ) 20 MG PO BEDTIME\nFood/Drug Interaction Instruction\nAvoid grapefruit unless MD instructs otherwise.\nVITAMIN B6 ( PYRIDOXINE HCL ) 50 MG PO DAILY\nULTRAM ( TRAMADOL ) 50 MG PO Q6H PRN Pain\nOverride Notice: Override added on 9/11/06 by\nINTERIANO , FLOYD E. , M.D.\non order for DILAUDID PO ( ref # 925975305 )\nPOTENTIALLY SERIOUS INTERACTION: TRAMADOL HCL &amp;\nHYDROMORPHONE HCL Reason for override: aware\nPrevious override information:\nOverride added on 2/29/06 by NOGALES , ARNOLD C. , M.D. , PH.D.\non order for ULTRAM PO ( ref # 417339527 )\nPt. has a PROBABLE allergy to PERCOCET; reaction is\nUnknown. Reason for override: MD aware\nPrevious Alert overridden\nOverride added on 2/29/06 by BECKLIN , JOAN N. , M.D. , PH.D.\nPOTENTIALLY SERIOUS INTERACTION: MORPHINE &amp; TRAMADOL HCL\nReason for override: will dc morphine\nNumber of Doses Required ( approximate ): 15\nDIET: Patient should measure weight daily\nDIET: House / Low chol/low sat. fat\nDIET: 2 gram Sodium\nACTIVITY: Resume regular exercise\nFOLLOW UP APPOINTMENT( S ):\nDr. Lagnese , call to schedule ,\nDr. Olufson call to schedule 246-729-9224 ,\nDr. Izzard cardiology 1/19/07 11:30 scheduled ,\nALLERGY: PERCOCET , DICLOXACILLIN , LISINOPRIL , WARFARIN SODIUM\nADMIT DIAGNOSIS:\nChest pain\nPRINCIPAL DISCHARGE DIAGNOSIS ;Responsible After Study for Causing Admission )\nNon cardiac chest pain\nOTHER DIAGNOSIS;Conditions , Infections , Complications , affecting Treatment/Stay\ns/p MVA 10/3 s/p B TKA htn\n( hypertension ) svt ( supraventricular tachycardia ) thrombophlebitis\n( superficial thrombophlebitis ) recurrent bilat LE cellulitis\n( cellulitis ) pernicious anemia ( pernicious anemia ) afib ( atrial\nfibrillation ) dvt ( deep venous thrombosis ) multiple episodes of\ncellulitis ( cellulitis )\nOPERATIONS AND PROCEDURES:\nNone\nOTHER TREATMENTS/PROCEDURES ( NOT IN O.R. )\nNone\nBRIEF RESUME OF HOSPITAL COURSE:\nCC: chest pain\n*****\n81 year old woman with Afib ( on fondaparinux no coumadin secondary to\nprior epistaxis ) , NSC lung ca , presents with 3 days of constant chest\npain. pleuritic , not exertional , related mostly to arm movement. Concern\nfor bone met vs.subsegmental PE on admission. She had been on\nfondapurinox as oupt ( hx of lung ca and afib with intolerance of\ncoumadin ). Continued work up with question of breast\nnodule , pt identifies one particular area which she feels is the primary\nsite of her pain.\n*****\nIn ED: PE CT neg. No ekg changes. ASA and no change with\nNGL.\n*****\nPatient status: AF , BP 125/51 P60 O2 98% RA\nRR18 AAO x 3 , obese , resting and breathing\ncomfortably irr irr 1-2/6 SEM\ncrackles at left base +palpable L breast\nmass at approx 12 oclock a few inches above nipple , diffusely nodular\nbreasts\nabd soft nt\nExt 1+ edema , no calf tenderness\n*****\nSignificant studies:\nCT-PE: IMPRESSION:\n1. No evidence of pulmonary embolism or deep venous thrombosis.\n2. Post right lower lobe resection changes.\n3. Interval resolution of the left upper lobe nodule without new\nnodules.\nper discussion with radiology possible chronic subsegmental PE\nCXR-no acute process\n+lupus anticoag\n*****\nProblem List/Hospital Course:\n* Chest pain-No met seen on CXR or CT. No large\nPE , but evidence for pulm HTN. Given question of chronic PE and outpt\ntreatment with fondapurinox will transition to lovenox while inpatient\nfor maintenance ( intolerance of coumadin with epistaxis ). No evidence of\ncardiac process on this admission no hypoxia , unclear etiology\nof chest pain may be related to painful breast lump , pt will have\nmammogram next week for evaluation , continue pain control with Lidoderm\npatch , ultram and low dose dilaudid as needed for severe pain.\n* Lung CA- Continuing tarceva as per outpatient oncologist Dr Goetzke , no new\nfindings on imaging but would consider bone scan as an oupatient if\ncontinues to have severe pain.\n* A fib- Lowered acebutolol dose from 400mg BID to 400mg daily due to\nintermittent bradycardia ( asymptomatic ). Pt to d/c fondaparinux and\ncontinue on lovenox as outpt.\n* CHF-gently diuresing , restarting home dose of\nlasix on 4/8 at 40 mg daily with improvement in crackles at left base.\nWill need to follow daily weights and titrate lasix as needed.\n* ID - Klebsiella UTI , treating with Cipro starting 4/8 with 250mg BID\n* Pain - tx with lidoderm patch , ultram on day of discharge adding low\ndose dilaudid for treatment of breakthrough pain.\n* Dispo to rehabilitation for continued reconditioning and improvement in\nfunctional status.\n* CODE: FULL\nADDITIONAL COMMENTS: Ms Cheramie , it was a pleasure to be involved in your care. Please\nfollow up with your regular primary care provider , Dr. Sauro and with\nyour oncologist Dr. Willard Camps . Please also keep your appointment to\nhave mammogram as scheduled on November at PNH .  You should also follow up\nwith yoru cardiologist Dr. Bennie Tomaselli for continued management of\nyour heart conditions. Please continue to work with the rehabilitation\nspecialists to try to regain strength and function.\nDISCHARGE CONDITION: Stable\nTO DO/PLAN:\n1. Check Factor Xa level to insure Lovenox dosing is therapeutic.\n2. Follow up on mammogram scheduled for November\n3. Continue to monitor heart rate intermittently to insure adequate rate\ncontrol with decreased dose of Acebutolol.\n4. Continue Lasix at 40mg daily ( admit dose had been 40mg alternating\nwith 60mg ) and monitor daily weights.\n5. Complete course of Cipro 250mg BID x 3 days ( 4 doses to complete on\ndischarge ) for Klebsiella UTI\n6. Follow up with oncologist , PCP and with cardiologist as above.\nNo dictated summary\nENTERED BY: WALLINGER , COLIN D. , M.D. , PH.D. ( NG11 ) 9/11/06 @ 04:29 PM\n****** END OF DISCHARGE ORDERS ******\n[report_end]\n", "annotations": [{"medication_name": "acebutolol hcl", "medication_dosage": "400 mg", "mode": "po", "frequency": "daily", "line": "19"}, {"medication_name": "allopurinol", "medication_dosage": "100 mg", "mode": "po", "frequency": "daily", "line": "22"}, {"medication_name": "vitamin c ( ascorbic acid )", "medication_dosage": "500 mg", "mode": "po", "frequency": "bid", "line": "23"}, {"medication_name": "calcium carbonate ( 500 mg elemental ca++ )", "medication_dosage": "500 mg", "mode": "po", "frequency": "bid", "line": "24"}, {"medication_name": "ciprofloxacin", "medication_dosage": "250 mg", "mode": "po", "frequency": "q12h", "line": "25"}, {"medication_name": "iron products", "medication_dosage": "", "mode": "", "frequency": "", "line": "27"}, {"medication_name": "ciprofloxacin", "medication_dosage": "", "mode": "", "frequency": "", "line": "28"}, {"medication_name": "levofloxacin", "medication_dosage": "", "mode": "", "frequency": "", "line": "28"}, {"medication_name": "digoxin", "medication_dosage": "0.125 mg", "mode": "po", "frequency": "daily", "line": "31"}, {"medication_name": "colace ( docusate sodium )", "medication_dosage": "100 mg", "mode": "po", "frequency": "bid", "line": "32"}, {"medication_name": "lovenox ( enoxaparin )", "medication_dosage": "120 mg", "mode": "sc", "frequency": "bedtime", "line": "33"}, {"medication_name": "tarceva ( erlotinib )", "medication_dosage": "100 mg", "mode": "po", "frequency": "daily", "line": "34"}, {"medication_name": "folic acid", "medication_dosage": "1 mg", "mode": "po", "frequency": "daily", "line": "39"}, {"medication_name": "furosemide", "medication_dosage": "40 mg", "mode": "po", "frequency": "daily", "line": "40"}, {"medication_name": "dilaudid ( hydromorphone hcl )", "medication_dosage": "0.5 mg", "mode": "po", "frequency": "q4h prn", "line": "41"}, {"medication_name": "dilaudid", "medication_dosage": "", "mode": "po", "frequency": "", "line": "44"}, {"medication_name": "tramadol hcl", "medication_dosage": "", "mode": "", "frequency": "", "line": "49"}, {"medication_name": "hydromorphone hcl", "medication_dosage": "", "mode": "", "frequency": "", "line": "50"}, {"medication_name": "lidoderm 5% patch ( lidocaine 5% patch )", "medication_dosage": "1 ea", "mode": "tp", "frequency": "daily", "line": "51"}, {"medication_name": "pravachol ( pravastatin )", "medication_dosage": "20 mg", "mode": "po", "frequency": "bedtime", "line": "53"}, {"medication_name": "vitamin b6 ( pyridoxine hcl )", "medication_dosage": "50 mg", "mode": "po", "frequency": "daily", "line": "56"}, {"medication_name": "ultram ( tramadol )", "medication_dosage": "50 mg", "mode": "po", "frequency": "q6h prn", "line": "57"}, {"medication_name": "dilaudid", "medication_dosage": "", "mode": "po", "frequency": "", "line": "60"}, {"medication_name": "tramadol hcl", "medication_dosage": "", "mode": "", "frequency": "", "line": "61"}, {"medication_name": "hydromorphone hcl", "medication_dosage": "", "mode": "", "frequency": "", "line": "62"}, {"medication_name": "ultram", "medication_dosage": "", "mode": "po", "frequency": "", "line": "65"}, {"medication_name": "morphine", "medication_dosage": "", "mode": "", "frequency": "", "line": "70"}, {"medication_name": "tramadol hcl", "medication_dosage": "", "mode": "", "frequency": "", "line": "70"}, {"medication_name": "morphine", "medication_dosage": "", "mode": "", "frequency": "", "line": "71"}, {"medication_name": "fondaparinux", "medication_dosage": "", "mode": "", "frequency": "", "line": "100"}, {"medication_name": "fondapurinox", "medication_dosage": "", "mode": "", "frequency": "", "line": "104"}, {"medication_name": "asa", "medication_dosage": "", "mode": "", "frequency": "", "line": "109"}, {"medication_name": "ngl", "medication_dosage": "", "mode": "", "frequency": "", "line": "110"}, {"medication_name": "lovenox", "medication_dosage": "", "mode": "", "frequency": "", "line": "134"}, {"medication_name": "fondapurinox", "medication_dosage": "", "mode": "", "frequency": "", "line": "134"}, {"medication_name": "lidoderm", "medication_dosage": "", "mode": "patch", "frequency": "", "line": "138"}, {"medication_name": "ultram", "medication_dosage": "", "mode": "", "frequency": "", "line": "139"}, {"medication_name": "dilaudid", "medication_dosage": "low dose", "mode": "", "frequency": "as needed", "line": "139"}, {"medication_name": "tarceva", "medication_dosage": "", "mode": "", "frequency": "", "line": "140"}, {"medication_name": "acebutolol", "medication_dosage": "400mg", "mode": "", "frequency": "daily", "line": "143"}, {"medication_name": "acebutolol", "medication_dosage": "400mg", "mode": "", "frequency": "bid", "line": "143"}, {"medication_name": "fondaparinux", "medication_dosage": "", "mode": "", "frequency": "", "line": "144"}, {"medication_name": "lovenox", "medication_dosage": "", "mode": "", "frequency": "", "line": "145"}, {"medication_name": "lasix", "medication_dosage": "40 mg", "mode": "", "frequency": "daily", "line": "147"}, {"medication_name": "lasix", "medication_dosage": "titrate", "mode": "", "frequency": "as needed", "line": "148"}, {"medication_name": "cipro", "medication_dosage": "250mg", "mode": "", "frequency": "bid", "line": "149"}, {"medication_name": "lidoderm", "medication_dosage": "", "mode": "patch", "frequency": "", "line": "150"}, {"medication_name": "ultram", "medication_dosage": "", "mode": "", "frequency": "", "line": "150"}, {"medication_name": "dilaudid", "medication_dosage": "low dose", "mode": "", "frequency": "", "line": "151"}, {"medication_name": "lovenox", "medication_dosage": "", "mode": "", "frequency": "", "line": "164"}, {"medication_name": "acebutolol", "medication_dosage": "decreased dose", "mode": "", "frequency": "", "line": "167"}, {"medication_name": "lasix", "medication_dosage": "40mg", "mode": "", "frequency": "", "line": "168"}, {"medication_name": "lasix", "medication_dosage": "40mg", "mode": "", "frequency": "daily", "line": "168"}, {"medication_name": "cipro", "medication_dosage": "250mg", "mode": "", "frequency": "bid", "line": "170"}]}