{
  "text": "RECORD #133198\n\n\n974726289 | SH | 63436693 | | 9978052 | 3/13/2005 12:00:00 AM | CHEST PAIN | Signed | DIS | Admission Date: 1/20/2005 Report Status: Signed\n\nDischarge Date: 1/18/2005\nATTENDING: LANGLAIS , EZEQUIEL MD\nPRINCIPAL DIAGNOSIS:\nCoronary artery disease.\nHISTORY OF PRESENT ILLNESS:\nA 66-year-old gentleman with a medical history significant for\ncoronary artery disease and two prior MIs. He is also status\npost angioplasty and an LAD stent , he has hypertension ,\nhyperlipidemia , and diabetes mellitus , and presents now with\nchest pain. The patient had been in his usual state of health\nwhen on the day prior to admission , he developed substernal chest\npain while walking and lasted 2-3 hours and was relieved by rest\nand sublingual nitroglycerin. He denies shortness of breath ,\nnausea , or diaphoresis. He presented to Renba Memorial Urgent Care where he was evaluated and sent to the\nCrossdick Hospital Of emergency department , where he was\nfound to have a troponin of 5.6 , which peaked at 6.7. He was\nadmitted , and cardiac catheterization revealed diffuse disease.\nHe is being evaluated for possible surgical intervention.\nPAST MEDICAL HISTORY:\nHypertension , insulin-dependent diabetes mellitus ,\nhypothyroidism , hypercholesterolemia , B12 deficiency sleep apnea ,\non home CPAP , nephrolithiasis , restless legs syndrome , and\ndiabetic retinopathy.\nPAST SURGICAL HISTORY:\nCongenital Schatzki's ring , status post dilation via EGD.\nSOCIAL HISTORY:\nPositive for a rare alcohol use. The patient has three children ,\nand is semi-retired as an architect.\nALLERGIES:\nSulfa causing rash and joint swelling , and enalaprilat causing\ncough.\nMEDICATIONS ON ADMISSION:\nLopressor 50 mg p.o. q.i.d. , valsartan 160 mg p.o. daily , aspirin\n325 mg p.o. daily , atorvastatin 80 mg p.o. daily , B12 100 mcg\np.o. daily , Colace 100 mg p.o. b.i.d. , folate , Levoxyl , Nexium ,\nLantus , and NovoLog insulin.\nPHYSICAL EXAMINATION:\nHeight 5 feet 7 inches tall , weight 67 kg. Vital signs: Not\nlisted. HEENT: PERRL. Oropharynx is benign. Neck: Without\ncarotid bruits. Chest: Without incisions. Cardiovascular:\nRegular rate and rhythm , no murmurs. Respiratory: Breath sounds\nare clear bilaterally. Abdomen: No incisions , soft , no masses.\nRectal: Normal tone , no masses , guaiac negative. Extremities:\nWithout scarring , varicosities or edema. Pedal pulses are 1+\nbilaterally. Radial pulses are 2+ bilaterally. Allen's test in\nthe left upper extremity is normal by pulse oximeter. Neuro:\nAlert and oriented , grossly nonfocal exam , although there is\nslightly decreased light touch sensation in the lower extremities\naround the great toe bilaterally.\nLABORATORY VALUES ON ADMISSION:\nInclude sodium of 139 , potassium of 4.3. BUN of 12 , creatinine\nof 1.2 , and glucose of 106. Hematology includes white blood cell\ncount of 7.4 , hematocrit of 33 , INR of 1 , PTT of 104. Cardiac\ncatheterization data: EKG , normal sinus rhythm at 67 with a\nnonspecific T-wave abnormality in 1 , aVL , V5 , and V6. Chest\nx-ray is without acute disease.\nHOSPITAL COURSE:\nThe patient was admitted on 3/10/05 and underwent cardiac\ncatheterization the following day , which revealed 90% proximal\nLAD stenosis , 90% mid LAD and 100% distal LAD stenosis , 100% mid\nLVB1 , 80% mid circumflex , 70% proximal D1 , 70% proximal PDA , and\na right dominant circulation. There is diffuse coronary\ncalcification and extensive diffuse disease with small distal\nvessels. LAD in stent restenosis. There is collateral flow\ndiffusely small left main. The patient was taken to the\noperating room on 4/15/05 and underwent CABG x4 with SVG1 to\nRCA , and sequential graft of SVG2 to D1 and then OM1. The\npatient also had LIMA to LAD and an LAD endarterectomy. The\npatient was taken to the Intensive Care Unit following surgery in\nstable condition. He was given 150 mg of Plavix on arrival to\nthe ICU , and a second dose 6 hours later. He was also started on\nheparin 500 units for 48 hours and given aspirin that same night.\nThe patient was extubated the following day and was noted to\nrequire the transfusion of a unit of packed red blood cells. He\nrequired neosynephrine transiently , which was weaned off on\npostoperative day #2. That same day , he transferred to the\nStep-Down Unit , neurologically intact , with pain well controlled ,\nhemodynamically stable , started on aspirin , Lopressor , and\nPlavix. The patient was also on 2 liters of oxygen at the time\nof transfer , and had chest tube in that still had output. The\npatient's diet was being advanced , and he was being diuresed with\nLasix with good effect. Perioperatively , he was also followed by\nthe Diabetes Management Service for blood sugar control and was\ntransitioned from IV insulin to subcutaneous insulin\npostoperatively. The patient was noted to have a preoperative\nurinary tract infection of E. coli for which he was started on\nlevofloxacin on 0/5/05 and treated for five days. On\npostoperative day #3 , his wires , chest tubes and Foley were\nremoved. He was noted to have loose lower front teeth following\nhis difficult intubation , and the Dental Service was called to\nsee the patient. The recommendation was simply to avoid putting\npressure on those teeth and they advised that this would allow\nthe teeth to retighten in the jaw over the next couple of weeks.\nThe patient continued to do well , remained in sinus rhythm , and\nwas weaned off oxygen , saturating well on room air. He\nprogressed daily and walked first with assistance and then\nsteadily on his own. He is discharged to home in good condition\non postoperative day #7 on the following medications:\nEnteric-coated aspirin 325 mg p.o. daily , atenolol 75 mg p.o.\ndaily , Colace 100 mg p.o. t.i.d. , oxycodone 5 mg to 10 mg p.o.\nq.6h. p.r.n. pain , Plavix 75 mg p.o. daily , Lantus 38 units\nsubcutaneously at bedtime , NovoLog 18 units subcutaneous q.a.m. ,\nNovoLog 12 units subcutaneously with lunch and supper , and\natorvastatin 80 mg p.o. daily. He is to have a follow-up\nappointment with his cardiologist , Dr. Abusufait , in one to two weeks ,\nand with his cardiac surgeon , Dr. Cederberg , in four to six weeks.\neScription document: 7-8654026 EMSFocus transcriptionists\nDictated By: GOTTDENGER , NEWTON\nAttending: ROTHERHAM , KENT\nDictation ID 1407522\nD: 5/18/05\nT: 5/18/05\n[report_end]\n",
  "annotations": [
    {
      "medication_name": "nitroglycerin.",
      "medication_dosage": "",
      "mode": "sublingual",
      "frequency": "",
      "line": "18"
    },
    {
      "medication_name": "valsartan",
      "medication_dosage": "160 mg",
      "mode": "p.o.",
      "frequency": "daily",
      "line": "38"
    },
    {
      "medication_name": "lopressor",
      "medication_dosage": "50 mg",
      "mode": "p.o.",
      "frequency": "q.i.d.",
      "line": "38"
    },
    {
      "medication_name": "aspirin",
      "medication_dosage": "325 mg",
      "mode": "p.o.",
      "frequency": "daily",
      "line": "38"
    },
    {
      "medication_name": "atorvastatin",
      "medication_dosage": "80 mg",
      "mode": "p.o.",
      "frequency": "daily",
      "line": "39"
    },
    {
      "medication_name": "b12",
      "medication_dosage": "100 mcg",
      "mode": "p.o.",
      "frequency": "daily ",
      "line": "39"
    },
    {
      "medication_name": "folate",
      "medication_dosage": "",
      "mode": "",
      "frequency": "",
      "line": "40"
    },
    {
      "medication_name": "levoxyl",
      "medication_dosage": "",
      "mode": "",
      "frequency": "",
      "line": "40"
    },
    {
      "medication_name": "nexium",
      "medication_dosage": "",
      "mode": "",
      "frequency": "",
      "line": "40"
    },
    {
      "medication_name": "colace",
      "medication_dosage": "100 mg",
      "mode": "p.o.",
      "frequency": "b.i.d.",
      "line": "40"
    },
    {
      "medication_name": "lantus",
      "medication_dosage": "",
      "mode": "",
      "frequency": "",
      "line": "41"
    },
    {
      "medication_name": "novolog insulin",
      "medication_dosage": "",
      "mode": "",
      "frequency": "",
      "line": "41"
    },
    {
      "medication_name": "plavix",
      "medication_dosage": "150 mg",
      "mode": "",
      "frequency": "",
      "line": "75"
    },
    {
      "medication_name": "plavix",
      "medication_dosage": "a second dose",
      "mode": "",
      "frequency": "",
      "line": "75"
    },
    {
      "medication_name": "heparin",
      "medication_dosage": "500 units",
      "mode": "",
      "frequency": "",
      "line": "77"
    },
    {
      "medication_name": "aspirin",
      "medication_dosage": "",
      "mode": "",
      "frequency": "",
      "line": "77"
    },
    {
      "medication_name": "packed red blood cells.",
      "medication_dosage": "a unit",
      "mode": "transfusion",
      "frequency": "",
      "line": "79"
    },
    {
      "medication_name": "neosynephrine",
      "medication_dosage": "",
      "mode": "",
      "frequency": "",
      "line": "80"
    },
    {
      "medication_name": "lopressor",
      "medication_dosage": "",
      "mode": "",
      "frequency": "",
      "line": "83"
    },
    {
      "medication_name": "aspirin",
      "medication_dosage": "",
      "mode": "",
      "frequency": "",
      "line": "83"
    },
    {
      "medication_name": "plavix.",
      "medication_dosage": "",
      "mode": "",
      "frequency": "",
      "line": "84"
    },
    {
      "medication_name": "oxygen",
      "medication_dosage": "2 liters",
      "mode": "",
      "frequency": "",
      "line": "84"
    },
    {
      "medication_name": "lasix",
      "medication_dosage": "",
      "mode": "",
      "frequency": "",
      "line": "87"
    },
    {
      "medication_name": "insulin",
      "medication_dosage": "",
      "mode": "subcutaneous",
      "frequency": "",
      "line": "89"
    },
    {
      "medication_name": "insulin",
      "medication_dosage": "",
      "mode": "IV",
      "frequency": "",
      "line": "89"
    },
    {
      "medication_name": "levofloxacin",
      "medication_dosage": "",
      "mode": "",
      "frequency": "",
      "line": "92"
    },
    {
      "medication_name": "oxygen",
      "medication_dosage": "",
      "mode": "",
      "frequency": "",
      "line": "100"
    },
    {
      "medication_name": "enteric-coated aspirin",
      "medication_dosage": "325 mg",
      "mode": "p.o.",
      "frequency": "daily",
      "line": "104"
    },
    {
      "medication_name": "atenolol",
      "medication_dosage": "75 mg",
      "mode": "p.o.",
      "frequency": "daily",
      "line": "104"
    },
    {
      "medication_name": "oxycodone",
      "medication_dosage": "5 mg to 10 mg",
      "mode": "p.o.",
      "frequency": "q.6h. p.r.n.",
      "line": "105"
    },
    {
      "medication_name": "colace",
      "medication_dosage": "100 mg",
      "mode": "p.o.",
      "frequency": "t.i.d.",
      "line": "105"
    },
    {
      "medication_name": "plavix",
      "medication_dosage": "75 mg",
      "mode": "p.o.",
      "frequency": "daily",
      "line": "106"
    },
    {
      "medication_name": "lantus",
      "medication_dosage": "38 units",
      "mode": "subcutaneously",
      "frequency": "at bedtime",
      "line": "106"
    },
    {
      "medication_name": "novolog",
      "medication_dosage": "18 units",
      "mode": "subcutaneous",
      "frequency": "q.a.m.",
      "line": "107"
    },
    {
      "medication_name": "novolog",
      "medication_dosage": "12 units",
      "mode": "subcutaneously",
      "frequency": "with lunch and supper",
      "line": "108"
    },
    {
      "medication_name": "atorvastatin",
      "medication_dosage": "80 mg",
      "mode": "p.o.",
      "frequency": "daily.",
      "line": "109"
    }
  ]
}