{"text": "RECORD #734280\n746472700 | PAMC | 03453039 | | 0162843 | 8/28/2005 12:00:00 AM | viral URI , pulmonary HTN | | DIS | Admission Date: 4/21/2005 Report Status:\nDischarge Date: 9/22/2005\n****** FINAL DISCHARGE ORDERS ******\nLIBRIZZI , MARIANO 915-22-38-9\nNew Hi A\nService: CAR\nDISCHARGE PATIENT ON: 2/17/05 AT 08:00 PM\nCONTINGENT UPON Not Applicable\nWILL D/C ORDER BE USED AS THE D/C SUMMARY: YES\nAttending: CADENAS , HONG BROOKS , M.D.\nDISPOSITION: Home\nDISCHARGE MEDICATIONS:\nECASA ( ASPIRIN ENTERIC COATED ) 81 MG PO QD\nAlert overridden: Override added on 9/4/05 by\nLEVER , DARYL , M.D.\nPOTENTIALLY SERIOUS INTERACTION: WARFARIN &amp; ASPIRIN\nReason for override: aware\nCOLACE ( DOCUSATE SODIUM ) 100 MG PO BID\nLASIX ( FUROSEMIDE ) 160 MG PO BID\nGLIPIZIDE 10 MG PO BID\nOCEAN SPRAY ( SODIUM CHLORIDE 0.65% ) 2 SPRAY NA QID\nPRN Other:dried nasal mucosa\nCOUMADIN ( WARFARIN SODIUM ) 5 MG PO QPM\nStarting NOW , Within Hour of Pharmacy Approval\nFood/Drug Interaction Instruction\nNo high Vitamin-K containing foods\nOverride Notice: Override added on 9/4/05 by\nJERICH , JOSPEH , M.D. on order for ECASA PO ( ref # 91585860 )\nPOTENTIALLY SERIOUS INTERACTION: WARFARIN &amp; ASPIRIN\nReason for override: aware\nZOLOFT ( SERTRALINE ) 150 MG PO QD\nAMBIEN ( ZOLPIDEM TARTRATE ) 10 MG PO QHS\nFood/Drug Interaction Instruction\nGive on an empty stomach ( give 1hr before or 2hr after\nfood )\nKCL SLOW RELEASE 20 MEQ PO BID\nAs per L Potassium Chloride Policy:\neach 20 mEq dose to be given with 4 oz of fluid\nATROVENT NASAL 0.06% ( IPRATROPIUM NASAL 0.06% )\n2 SPRAY NA TID\nNumber of Doses Required ( approximate ): 10\nNEXIUM ( ESOMEPRAZOLE ) 20 MG PO QD\nTRACLEER ( BOSENTAN ) 125 MG PO BID\nNumber of Doses Required ( approximate ): 10\nVENTAVIS 1 neb NEB Q3H Instructions: during wake hours\nALBUTEROL INHALER 2 PUFF INH Q4H\nPRN Shortness of Breath , Wheezing\nDIET: House / Low chol/low sat. fat\nDIET: 4 gram Sodium\nACTIVITY: Walking as tolerated\nFOLLOW UP APPOINTMENT( S ):\nTFHC per TLHO team ,\nArrange INR to be drawn on 0/1/05 with f/u INR's to be drawn every\nperclinic days. INR's will be followed by prior clinic\nALLERGY: Cephalosporins , ACE Inhibitor\nADMIT DIAGNOSIS:\nViral infection , severe pulmonary hypertension\nPRINCIPAL DISCHARGE DIAGNOSIS ;Responsible After Study for Causing Admission )\nviral URI , pulmonary HTN\nOTHER DIAGNOSIS;Conditions , Infections , Complications , affecting Treatment/Stay\nHTN H/O PUD dm ( diabetes\nmellitus ) pulmonary hypertension ( pulmonary hypertension ) osa ( sleep\napnea ) gerd ( gastroesophageal reflux disease )\nOPERATIONS AND PROCEDURES:\nNone\nOTHER TREATMENTS/PROCEDURES ( NOT IN O.R. )\nNone\nBRIEF RESUME OF HOSPITAL COURSE:\nCC: SOB\nHPI: 51 F w/ h/o severe pulmonary HTN , DM , OSA , obesity , on chronic\nhome O2 ( 8L NC ). She is followed by the AH service , at\nher baseline until about one week ago , having returned\nfrom Pe Ale two weeks ago , she began to experience dyspnea on\nexertion and chest tightness. She also reports productive cough\n( greenish ) , rhinorrhea , sinus tenderness , N/V , malaise. She denies\npalpitations or radiating chest pain. The day PTA , VNA found the\npatient to desat to 82% with exertion. She went to Gas Healthcare ,\nwhere she was found to have an SpO2 of 99% on 8L , no EKG\nchanges , NAD on CXR.\nShe was hospitalized in July 2005 at CRT with simlar SOB. At this\ntime , she underwent a RHC which showed PA pressures 70-80% ( 110/40/60-65 )\nof sytemic pressures. She also had a negative MIBI , negative\nswallowing study. Since discharge , she reports being med compliant , and\ndiet compliant. Her weight has been stable at 238 lbs. She feels that\nher depression has been worse of late. ALL: ACEi ,\ncephalopsporins\nMEDS: K-Dur 20 BID , Nexium 20 , lasix 160 BID ,\ntracleer 125 BID , Glipizide 80 BID , Coumadin 5/7.5 , ECASA 81 , Zoloft\n100 , MVI , Oceanspray , Ambien 10 QHS , Ventavis nebs\nQ3H\nPE:96.8 , 83 , 114/76 , 97-98% on 8L\nNC. JVP 14 , RRR , loud P2 , no M. CTA. Obese.\nLabs: K 3.5 , Cr 1.4 , WBC 8.2 , CK/TNI neg , BNP 443.\n****************Hospital Course******************\nA/P 51F with sever pHTN , OSA , DM , obesity , p/w SOB and URI-type Sx.\nNear pulmonary baseline.\n1. Pulm: Severe pHTN with very elevated PA pressures. Likely subjective\nSOB in the context of viral URI. Cont Ilprost , home O2 , tracleer ,\nalbuterol. Pulmonary status stable , but patient is uneasy with going\nhome , and so will stay - stable enought to go home.\n2. CV: Recent ECHO , Cath , probably no need to do further w/u. ROMI by\nserial enzymes/EKG. Continue Lasix , KCl , ASA 81.\n3. Psych: h/o depression. Inpatient psych consult. Cont. zoloft , ambien.\n4. DM: Will follow FSBS.\n5. Heme: Coumadin for pulmonary microclots on Bx in\npast. WIll increase Coumadin since INR 1.9 , recheck QD.\n6. FEN: low salt , low fat diet.\n7. ID: Likely viral URI. BCx taken.\nWIll recheck CXR if clinically\nwarranted.\n8. GI: GERD , nexium prophylaxis.\nADDITIONAL COMMENTS: Call you doctor if you become more short of breath.\nDISCHARGE CONDITION: Satisfactory\nTO DO/PLAN:\nNo dictated summary\nENTERED BY: EVERLY , ARRON J. , M.D. ( TC12 ) 2/17/05 @ 07\n****** END OF DISCHARGE ORDERS ******\n[report_end]\n", "annotations": [{"medication_name": "ecasa ( aspirin enteric coated )", "medication_dosage": "81 mg", "mode": "po ", "frequency": "qd ", "line": "14"}, {"medication_name": "aspirin", "medication_dosage": "", "mode": "", "frequency": "", "line": "17"}, {"medication_name": "warfarin", "medication_dosage": "", "mode": "", "frequency": "", "line": "17"}, {"medication_name": "colace ( docusate sodium )", "medication_dosage": "100 mg", "mode": "po", "frequency": "bid", "line": "19"}, {"medication_name": "lasix ( furosemide )", "medication_dosage": "160 mg", "mode": "po", "frequency": "bid", "line": "20"}, {"medication_name": "glipizide", "medication_dosage": "10 mg", "mode": "po", "frequency": "bid", "line": "21"}, {"medication_name": "ocean spray ( sodium chloride 0.65% )", "medication_dosage": "2 spray", "mode": "na", "frequency": "qid prn", "line": "22"}, {"medication_name": "coumadin ( warfarin sodium )", "medication_dosage": "5 mg", "mode": "po", "frequency": "qpm", "line": "24"}, {"medication_name": "ecasa", "medication_dosage": "", "mode": "po ", "frequency": "", "line": "29"}, {"medication_name": "aspirin", "medication_dosage": "", "mode": "", "frequency": "", "line": "30"}, {"medication_name": "warfarin", "medication_dosage": "", "mode": "", "frequency": "", "line": "30"}, {"medication_name": "zoloft ( sertraline )", "medication_dosage": "150 mg", "mode": "po", "frequency": "qd", "line": "32"}, {"medication_name": "ambien ( zolpidem tartrate )", "medication_dosage": "10 mg", "mode": "po", "frequency": "qhs", "line": "33"}, {"medication_name": "kcl slow release", "medication_dosage": "20 meq", "mode": "po", "frequency": "bid", "line": "37"}, {"medication_name": "atrovent nasal 0.06% ( ipratropium nasal 0.06% )", "medication_dosage": "2 spray", "mode": "na", "frequency": "tid", "line": "40"}, {"medication_name": "nexium ( esomeprazole )", "medication_dosage": "20 mg", "mode": "po", "frequency": "qd", "line": "43"}, {"medication_name": "tracleer ( bosentan )", "medication_dosage": "125 mg", "mode": "po", "frequency": "bid", "line": "44"}, {"medication_name": "ventavis", "medication_dosage": "1 neb", "mode": "neb", "frequency": "q3h", "line": "46"}, {"medication_name": "albuterol inhaler", "medication_dosage": "2 puff", "mode": "inh", "frequency": "q4h prn", "line": "47"}, {"medication_name": "o2", "medication_dosage": "8l", "mode": "", "frequency": "", "line": "72"}, {"medication_name": "acei", "medication_dosage": "", "mode": "", "frequency": "", "line": "86"}, {"medication_name": "cephalopsporins", "medication_dosage": "", "mode": "", "frequency": "", "line": "87"}, {"medication_name": "k-dur", "medication_dosage": "20", "mode": "", "frequency": "bid ", "line": "88"}, {"medication_name": "lasix", "medication_dosage": "160", "mode": "", "frequency": "bid", "line": "88"}, {"medication_name": "nexium", "medication_dosage": "20", "mode": "", "frequency": "", "line": "88"}, {"medication_name": "coumadin", "medication_dosage": "5/7.5", "mode": "", "frequency": "", "line": "89"}, {"medication_name": "zoloft", "medication_dosage": "100", "mode": "", "frequency": "", "line": "89"}, {"medication_name": "glipizide", "medication_dosage": "80", "mode": "", "frequency": "bid", "line": "89"}, {"medication_name": "ecasa", "medication_dosage": "81", "mode": "", "frequency": "", "line": "89"}, {"medication_name": "tracleer", "medication_dosage": "125", "mode": "", "frequency": "bid", "line": "89"}, {"medication_name": "ambien", "medication_dosage": "10", "mode": "", "frequency": "qhs", "line": "90"}, {"medication_name": "ventavis", "medication_dosage": "", "mode": "nebs", "frequency": "q3h", "line": "90"}, {"medication_name": "mvi", "medication_dosage": "", "mode": "", "frequency": "", "line": "90"}, {"medication_name": "oceanspray", "medication_dosage": "", "mode": "", "frequency": "", "line": "90"}, {"medication_name": "tracleer", "medication_dosage": "", "mode": "", "frequency": "", "line": "99"}, {"medication_name": "o2", "medication_dosage": "", "mode": "", "frequency": "", "line": "99"}, {"medication_name": "albuterol.", "medication_dosage": "", "mode": "", "frequency": "", "line": "100"}, {"medication_name": "lasix", "medication_dosage": "", "mode": "", "frequency": "", "line": "103"}, {"medication_name": "asa", "medication_dosage": "81", "mode": "", "frequency": "", "line": "103"}, {"medication_name": "kcl", "medication_dosage": "", "mode": "", "frequency": "", "line": "103"}, {"medication_name": "zoloft", "medication_dosage": "", "mode": "", "frequency": "", "line": "104"}, {"medication_name": "ambien.", "medication_dosage": "", "mode": "", "frequency": "", "line": "104"}, {"medication_name": "coumadin", "medication_dosage": "", "mode": "", "frequency": "", "line": "106"}, {"medication_name": "coumadin", "medication_dosage": "", "mode": "", "frequency": "", "line": "107"}, {"medication_name": "nexium", "medication_dosage": "", "mode": "", "frequency": "", "line": "112"}]}