{
  "text": "RECORD #5091\n\n\n798348513 | CMC | 42176106 | | 6273542 | 0/12/2006 12:00:00 AM | LEFT IST TOE INFECTION | Signed | DIS | Admission Date: 0/12/2006 Report Status: Signed\n\nDischarge Date: 6/7/2006\nATTENDING: KIRTLAND , AHMAD F. D. C.\nADMITTING DIAGNOSIS:\nPeripheral vascular disease.\nLIST OF PROBLEMS AND DIAGNOSES:\nChronic kidney disease , diabetes , peripheral vascular disease ,\ncongestive heart failure , aortic stenosis , coronary artery\ndisease status post CABG , anemia , hypertension.\nHISTORY OF PRESENT ILLNESS:\nA 79-year-old male with history of non-insulin dependent\ndiabetes , coronary artery disease , congestive heart failure ,\nhypertension , chronic renal failure , recently 1.5 months status\npost left toe amputation on 7/1/06 complicated by acute on\nchronic renal failure and delirium requiring postoperative\ndialysis from 9/8/06 through 9/27/06 . The patient presented\non 3/26/05 for a nonhealing ulcer for three weeks' duration ,\nexposed bone on the left great toe and was admitted for\ndebridement and antibiotics. An MRA on 10/3/06 demonstrated on\nthe right a multifocal high-grade stenosis of the proximal ,\nanterior tibial , the tibioperoneal trunk and the proximal ,\nposterior tibial arteries and included peroneal artery at the\nmidcalf , two-vessel runoff and on the left diffuse high-grade\nstenoses of the anterior tibial , posterior tibial arteries and\nocclusion of the peroneal artery in the dorsalis pedis. The\npatient now presents with bleeding from the site of the left toe\namputation beginning two weeks ago associated with throbbing\npain , soreness , erythema and swelling and exacerbated blood\npressure when walking and only treated by narcotics.\nPAST MEDICAL HISTORY:\nStage IV chronic kidney disease secondary to diabetes with the\nbaseline creatinine of 2.3 , non-insulin-dependent diabetes since\n1998 , peripheral vascular disease , congestive heart failure with\nan EF of 55% on 7/13/06 , aortic stenosis status post AVR ,\ncoronary artery disease status post CABG , anemia and\nhypertension.\nPAST SURGICAL HISTORY:\nAortic valve replacement with a Carpentier-Edwards valve ,\npulmonary hypertension prior to the AVR , status post ablation for\natrioventricular nodal reentry , tachycardia , CABG x4 , and PFO\nclosure 7/13/06 status post left first toe amputation 10/3/06\ncomplicated by delirium and acute renal dysfunction.\nMEDICATIONS:\nAspirin , Lopressor , Norvasc , Zocor , Plavix , PhosLo , Prandin ,\nNephrocaps , Epogen , Calcitriol.\nALLERGIES:\nNo known drug allergies.\nSOCIAL HISTORY:\nLives alone , separated from wife , retired firefighter. Former\nsmoker with a distant history of five-pack years. Seldom alcohol\nuse.\nFAMILY HISTORY:\nDiabetes in the father and the daughter. Father had diabetes ,\nwas a smoker and an alcoholic and died of a myocardial infarction\nat age 65.\nPHYSICAL EXAMINATION ON ADMISSION:\nVITAL SIGNS: Temperature 99.8 , heart rate 79 , blood pressure\n170/90 , respiratory rate 20 , oxygen saturation 100% on room air.\nOn exam , in general , elderly man in no acute distress.\nHEENT: Normocephalic , atraumatic. No scleral icterus.\nNEURO: Alert and oriented x3.\nCARDIAC: Regular rate and rhythm. Split S2 , mild systolic\nmurmur , 2/6 radiating to the carotids bilaterally , heard best at\nthe right second intercostal space. No bruits bilaterally.\nRESPIRATORY: Clear to auscultation bilaterally , no rales ,\nwheezing or rhonchi.\nGI: Soft , nontender , firm , nondistended , positive bowel sounds ,\nno rebound , no guarding , no masses.\nEXTREMITIES: 2+ edema bilaterally. No clubbing , no cyanosis. A\ncold right foot , left lower extremity great toe amputation site\nbandage with bloody drainage. Radial pulses 2+ bilaterally.\nFemoral pulses 2+ bilaterally. PT pulse palpable , DP pulse\npalpable on the right and the left PT pulse 1+ and DP pulse was\nnot palpable.\nEKG: Left axis deviation with left ventricular hypertrophy ,\nquestion of lateral ischemia.\nHOSPITAL COURSE AND PROCEDURES:\nProcedures: 0/9/06 , Irrigation and debridement of the left\ngreat toe with extension of amputation to the transmetatarsal\njoint. 8/14/06 and 6/21/06 , left toe I&amp;D with left popliteal\nbypass graft to the anterior tibial artery with right saphenous\nvein graft and Vac placement. Serial debridements on 4/25/06 ,\n1/30/06 and 8/26/06 . Foot had been debrided so that the\namputation on the first and second toes are down to the level of\nthe tarsometatarsal joint.\nHOSPITAL COURSE:\nThe patient was admitted on 5/22/06 for treatment with IV\nantibiotics and presumed operative intervention.\nNeuro and Psych: The patient has delirium postoperatively for\nwhich he was placed on soft restraints and received Zyprexa.\nThis resolved quickly. Did well for the duration of admission in\nterms of mental status. Alert and oriented x3 at the time of\ndischarge.\nCardiac: Upon admission , potassium was noted to be elevated and\nthe patient had EKG changes associated with hyperkalemia. Both\nthe Renal and Cardiology services were consulted and assisted\nwith his perioperative management in terms of cardioprotection\nand possible need for dialysis. No further events. The\nhyperkalemia resolved. He remained hemodynamically stable. He\nreceived aspirin and Zocor for coronary artery disease related\nevent prophylaxis. Blood pressure was controlled with isosorbide\ndinitrate , Norvasc , lisinopril , and Lopressor.\nPulmonary: No events. Maintained oxygen saturation greater than\n90% on room air.\nRenal: Creatinine was stable in the mid 3s and trended down to\n2.6 at the time of discharge below his baseline of 4-5. Voiding\nwithout difficulty at the time of discharge. Maintained on his\nrenal medications.\nFEN/GI: Tolerated regular diet. Lactulose and Colace to prevent\nconstipation while taking narcotics , also had Dulcolax p.r.n.\nZinc and vitamin C was started per the Nutrition consult.\nHematology: He received heparin for DVT prophylaxis. His\nhematocrit remained stable. He had some oozing from the right\nthigh but this resolved with a pressure dressing.\nID: He was treated throughout his hospitalization with\nvancomycin , levofloxacin and Flagyl for methicillin-resistant\nStaphylococcus aureus that grew from the wound after the first\nand second irrigation and debridement. The levofloxacin and\nFlagyl were discontinued prior to discharge. He will continue\nhis vancomycin at the time of discharge. Please see addendum for\nantibiotic plan.\nEndocrine: Diabetes controlled. He was maintained on his\nPrandin and insulin sliding scale for glycemic control. He also\nreceived vitamin D.\nHis incision remained clean , dry and intact without erythema or\nexudate. He was afebrile with stable signs at the time of\ndischarge.\nACTIVITY INSTRUCTIONS:\nHe is nonweightbearing on the left lower extremity to protect the\nopen toe.\nCOMPLICATIONS:\nNone.\nDISCHARGE LABS:\nLaboratory tests at the time of discharge include sodium 138 ,\npotassium 4.1 , chloride 111 , bicarbonate 21 , BUN 35 , creatinine\n2.6 , calcium 9.0 , magnesium 1.9 , vancomycin 19.5 , white blood\ncell count 7.3 , hemoglobin 9.9 , hematocrit 30.2 , platelets 221.\nDISCHARGE MEDICATIONS:\nHis medications at discharge include aspirin 325 mg p.o. daily ,\nvitamin C 500 mg p.o. b.i.d. , calcitriol 0.5 mcg p.o. daily ,\nColace 100 mg p.o. daily , heparin 5000 units subcutaneous t.i.d. ,\nisosorbide dinitrate 10 mg p.o. t.i.d. , lactulose 30 mL p.o.\nt.i.d. , lisinopril 50 mg p.o. daily , Lopressor 50 mg p.o. q.6h.\nSimethicone 80 mg p.o. q.i.d. , vancomycin 1 g IV every other day ,\nzinc sulfate 220 mg p.o. daily for two weeks , Zocor 80 mg p.o.\ndaily , Norvasc 10 mg p.o. daily , Nephro-Vite one tab p.o. daily ,\nPrandin 0.5 mg p.o. with each meal , Aranesp 40 mcg subcutaneous\nevery week , sliding scale insulin , insulin aspart 4 units\nsubcutaneous with breakfast and dinner , Dulcolax 10 mg PR daily ,\nTylenol p.r.n. , Dilaudid 2-4 mg p.o. q.4h. as needed for pain ,\nmilk of magnesia as needed for constipation , Reglan for nausea ,\noxycodone for pain 5-10 mg p.o. q.4h. hours as needed for pain ,\nZyprexa 5 mg p.o. q.8h. as needed for anxiety or agitation ,\nMaalox p.r.n. upset stomach.\nDISPOSITION:\nTo rehabilitation.\nPHYSICIAN FOLLOWUP:\nThe patient will follow up with Dr. Odo at 030-524-6194. To\ncall Dr. Barkalow to be seen within one to two weeks after\ndischarge.\neScription document: 8-9296036 EMSSten Tel\nDictated By: TEAR , DON\nAttending: BOHRER , DENVER\nDictation ID 3849823\nD: 11/5/06\nT: 11/5/06\n[report_end]\n",
  "annotations": [
    {
      "medication_name": "antibiotics",
      "medication_dosage": "",
      "mode": "",
      "frequency": "",
      "line": "23"
    },
    {
      "medication_name": "narcotics.",
      "medication_dosage": "",
      "mode": "",
      "frequency": "",
      "line": "33"
    },
    {
      "medication_name": "aspirin",
      "medication_dosage": "",
      "mode": "",
      "frequency": "",
      "line": "48"
    },
    {
      "medication_name": "phoslo",
      "medication_dosage": "",
      "mode": "",
      "frequency": "",
      "line": "48"
    },
    {
      "medication_name": "lopressor",
      "medication_dosage": "",
      "mode": "",
      "frequency": "",
      "line": "48"
    },
    {
      "medication_name": "norvasc",
      "medication_dosage": "",
      "mode": "",
      "frequency": "",
      "line": "48"
    },
    {
      "medication_name": "plavix",
      "medication_dosage": "",
      "mode": "",
      "frequency": "",
      "line": "48"
    },
    {
      "medication_name": "prandin",
      "medication_dosage": "",
      "mode": "",
      "frequency": "",
      "line": "48"
    },
    {
      "medication_name": "zocor",
      "medication_dosage": "",
      "mode": "",
      "frequency": "",
      "line": "48"
    },
    {
      "medication_name": "epogen",
      "medication_dosage": "",
      "mode": "",
      "frequency": "",
      "line": "49"
    },
    {
      "medication_name": "calcitriol.",
      "medication_dosage": "",
      "mode": "",
      "frequency": "",
      "line": "49"
    },
    {
      "medication_name": "nephrocaps",
      "medication_dosage": "",
      "mode": "",
      "frequency": "",
      "line": "49"
    },
    {
      "medication_name": "antibiotics",
      "medication_dosage": "",
      "mode": "iv",
      "frequency": "",
      "line": "92"
    },
    {
      "medication_name": "zyprexa.",
      "medication_dosage": "",
      "mode": "",
      "frequency": "",
      "line": "94"
    },
    {
      "medication_name": "aspirin",
      "medication_dosage": "",
      "mode": "",
      "frequency": "",
      "line": "104"
    },
    {
      "medication_name": "zocor",
      "medication_dosage": "",
      "mode": "",
      "frequency": "",
      "line": "104"
    },
    {
      "medication_name": "isosorbide dinitrate",
      "medication_dosage": "",
      "mode": "",
      "frequency": "",
      "line": "105"
    },
    {
      "medication_name": "norvasc",
      "medication_dosage": "",
      "mode": "",
      "frequency": "",
      "line": "106"
    },
    {
      "medication_name": "lisinopril",
      "medication_dosage": "",
      "mode": "",
      "frequency": "",
      "line": "106"
    },
    {
      "medication_name": "lopressor",
      "medication_dosage": "",
      "mode": "",
      "frequency": "",
      "line": "106"
    },
    {
      "medication_name": "renal medications.",
      "medication_dosage": "",
      "mode": "",
      "frequency": "",
      "line": "112"
    },
    {
      "medication_name": "colace",
      "medication_dosage": "",
      "mode": "",
      "frequency": "",
      "line": "113"
    },
    {
      "medication_name": "lactulose",
      "medication_dosage": "",
      "mode": "",
      "frequency": "",
      "line": "113"
    },
    {
      "medication_name": "dulcolax",
      "medication_dosage": "",
      "mode": "",
      "frequency": "p.r.n.",
      "line": "114"
    },
    {
      "medication_name": "narcotics",
      "medication_dosage": "",
      "mode": "",
      "frequency": "",
      "line": "114"
    },
    {
      "medication_name": "vitamin c",
      "medication_dosage": "",
      "mode": "",
      "frequency": "",
      "line": "115"
    },
    {
      "medication_name": "zinc",
      "medication_dosage": "",
      "mode": "",
      "frequency": "p.r.n.",
      "line": "115"
    },
    {
      "medication_name": "heparin",
      "medication_dosage": "",
      "mode": "",
      "frequency": "",
      "line": "116"
    },
    {
      "medication_name": "vancomycin",
      "medication_dosage": "",
      "mode": "",
      "frequency": "",
      "line": "120"
    },
    {
      "medication_name": "flagyl",
      "medication_dosage": "",
      "mode": "",
      "frequency": "",
      "line": "120"
    },
    {
      "medication_name": "levofloxacin",
      "medication_dosage": "",
      "mode": "",
      "frequency": "",
      "line": "120"
    },
    {
      "medication_name": "levofloxacin",
      "medication_dosage": "",
      "mode": "",
      "frequency": "",
      "line": "122"
    },
    {
      "medication_name": "flagyl",
      "medication_dosage": "",
      "mode": "",
      "frequency": "",
      "line": "123"
    },
    {
      "medication_name": "vancomycin",
      "medication_dosage": "",
      "mode": "",
      "frequency": "",
      "line": "124"
    },
    {
      "medication_name": "antibiotic",
      "medication_dosage": "",
      "mode": "",
      "frequency": "",
      "line": "125"
    },
    {
      "medication_name": "prandin",
      "medication_dosage": "",
      "mode": "",
      "frequency": "",
      "line": "127"
    },
    {
      "medication_name": "insulin",
      "medication_dosage": "sliding scale",
      "mode": "",
      "frequency": "",
      "line": "127"
    },
    {
      "medication_name": "vitamin d.",
      "medication_dosage": "",
      "mode": "",
      "frequency": "",
      "line": "128"
    },
    {
      "medication_name": "aspirin",
      "medication_dosage": "325 mg",
      "mode": "p.o.",
      "frequency": "daily",
      "line": "143"
    },
    {
      "medication_name": "calcitriol",
      "medication_dosage": "0.5 mcg",
      "mode": "p.o.",
      "frequency": "daily",
      "line": "144"
    },
    {
      "medication_name": "vitamin c",
      "medication_dosage": "500 mg",
      "mode": "p.o.",
      "frequency": "b.i.d.",
      "line": "144"
    },
    {
      "medication_name": "heparin",
      "medication_dosage": "5000 units",
      "mode": "subcutaneous",
      "frequency": "t.i.d.",
      "line": "145"
    },
    {
      "medication_name": "colace",
      "medication_dosage": "100 mg",
      "mode": "p.o.",
      "frequency": "daily",
      "line": "145"
    },
    {
      "medication_name": "isosorbide dinitrate",
      "medication_dosage": "10 mg",
      "mode": "p.o.",
      "frequency": "t.i.d.",
      "line": "146"
    },
    {
      "medication_name": "lactulose",
      "medication_dosage": "30 ml",
      "mode": "p.o.",
      "frequency": "t.i.d.",
      "line": "146"
    },
    {
      "medication_name": "lopressor",
      "medication_dosage": "50 mg",
      "mode": "p.o.",
      "frequency": "q.6h.",
      "line": "147"
    },
    {
      "medication_name": "lisinopril",
      "medication_dosage": "50 mg",
      "mode": "p.o.",
      "frequency": "daily",
      "line": "147"
    },
    {
      "medication_name": "vancomycin",
      "medication_dosage": "1 g",
      "mode": "iv",
      "frequency": "every other day",
      "line": "148"
    },
    {
      "medication_name": "simethicone",
      "medication_dosage": "80 mg",
      "mode": "p.o.",
      "frequency": "q.i.d.",
      "line": "148"
    },
    {
      "medication_name": "zocor",
      "medication_dosage": "80 mg",
      "mode": "p.o.",
      "frequency": "daily",
      "line": "149"
    },
    {
      "medication_name": "zinc sulfate",
      "medication_dosage": "220 mg",
      "mode": "p.o.",
      "frequency": "daily",
      "line": "149"
    },
    {
      "medication_name": "norvasc",
      "medication_dosage": "10 mg",
      "mode": "p.o.",
      "frequency": "daily",
      "line": "150"
    },
    {
      "medication_name": "nephro-vite",
      "medication_dosage": "one tab",
      "mode": "p.o.",
      "frequency": "daily",
      "line": "150"
    },
    {
      "medication_name": "prandin",
      "medication_dosage": "0.5 mg",
      "mode": "p.o.",
      "frequency": "with each meal",
      "line": "151"
    },
    {
      "medication_name": "aranesp",
      "medication_dosage": "40 mcg",
      "mode": "subcutaneous",
      "frequency": "every week",
      "line": "151"
    },
    {
      "medication_name": "insulin",
      "medication_dosage": "sliding scale",
      "mode": "",
      "frequency": "",
      "line": "152"
    },
    {
      "medication_name": "insulin aspart",
      "medication_dosage": "4 units",
      "mode": "subcutaneous",
      "frequency": "with breakfast and dinner",
      "line": "152"
    },
    {
      "medication_name": "dulcolax",
      "medication_dosage": "10 mg",
      "mode": "pr",
      "frequency": "daily",
      "line": "153"
    },
    {
      "medication_name": "tylenol",
      "medication_dosage": "",
      "mode": "",
      "frequency": "p.r.n.",
      "line": "154"
    },
    {
      "medication_name": "dilaudid",
      "medication_dosage": "2-4 mg",
      "mode": "p.o.",
      "frequency": "q.4h. as needed",
      "line": "154"
    },
    {
      "medication_name": "reglan",
      "medication_dosage": "",
      "mode": "",
      "frequency": "",
      "line": "155"
    },
    {
      "medication_name": "milk of magnesia",
      "medication_dosage": "",
      "mode": "",
      "frequency": "as needed",
      "line": "155"
    },
    {
      "medication_name": "oxycodone",
      "medication_dosage": "5-10 mg",
      "mode": "p.o.",
      "frequency": "q.4h. hours as needed",
      "line": "156"
    },
    {
      "medication_name": "zyprexa",
      "medication_dosage": "5 mg",
      "mode": "p.o.",
      "frequency": "q.8h. as needed",
      "line": "157"
    },
    {
      "medication_name": "maalox",
      "medication_dosage": "",
      "mode": "",
      "frequency": "p.r.n.",
      "line": "158"
    }
  ]
}