{"text": "RECORD #661928\n\n\n457962568 | OMC | 15325194 | | 7149373 | 5/5/2006 12:00:00 AM | chf exacerbation | | DIS | Admission Date: 7/8/2006 Report Status:\n\nDischarge Date: 5/1/2006\n****** FINAL DISCHARGE ORDERS ******\nEVANKO , BENEDICT 205-94-27-9\nDalemilci Lake\nService: MED\nDISCHARGE PATIENT ON: 8/4/06 AT 11:00 AM\nCONTINGENT UPON Not Applicable\nWILL D/C ORDER BE USED AS THE D/C SUMMARY: YES\nAttending: RHATIGAN , WENDELL E. E. M.\nCODE STATUS:\nFull code\nDISPOSITION: Home w/ services\nDISCHARGE MEDICATIONS:\nACETYLSALICYLIC ACID 81 MG PO DAILY\nATORVASTATIN 80 MG PO DAILY\nCOREG ( CARVEDILOL ) 3.125 MG PO BID\nHOLD IF: SBP&lt;90 or P&lt;55\nInstructions: if held , please call HO\nFood/Drug Interaction Instruction\nTake consistently with meals or on empty stomach.\nNumber of Doses Required ( approximate ): 6\nPLAVIX ( CLOPIDOGREL ) 75 MG PO DAILY\nLASIX ( FUROSEMIDE ) 80 MG PO DAILY Starting IN AM March\nINSULIN 70/30 HUMAN 50 UNITS QAM; 35 UNITS QPM SC\n50 UNITS QAM 35 UNITS QPM\nIMDUR ER ( ISOSORBIDE MONONITRATE ( SR ) ) 30 MG PO DAILY\nStarting IN AM March Food/Drug Interaction Instruction\nGive on an empty stomach ( give 1hr before or 2hr after\nfood )\nLISINOPRIL 10 MG PO DAILY HOLD IF: SBP &lt; 90 and call HO\nAlert overridden: Override added on 4/15/06 by\nREICKS , JACQUES M , M.D. , M.P.H.\nPOTENTIALLY SERIOUS INTERACTION: SPIRONOLACTONE &amp;\nLISINOPRIL\nPOTENTIALLY SERIOUS INTERACTION: POTASSIUM CHLORIDE &amp;\nLISINOPRIL\nPOTENTIALLY SERIOUS INTERACTION: POTASSIUM CHLORIDE &amp;\nLISINOPRIL Reason for override: monitor\nMETAMUCIL SUGAR FREE ( PSYLLIUM ( METAMUCIL ) SU... )\n1 PACKET PO DAILY\nSPIRONOLACTONE 50 MG PO DAILY HOLD IF: SBP&lt;90\nFood/Drug Interaction Instruction Give with meals\nOverride Notice: Override added on 4/15/06 by\nVAZZANA , JAN M , M.D. , M.P.H.\non order for LISINOPRIL PO ( ref # 166373866 )\nPOTENTIALLY SERIOUS INTERACTION: SPIRONOLACTONE &amp;\nLISINOPRIL Reason for override: monitor\nPrevious override information:\nOverride added on 4/15/06 by SOLARSKI , ERICH S. , M.D. , M.P.H.\non order for KCL IMMEDIATE RELEASE PO ( ref #\n040984307 )\nSERIOUS INTERACTION: SPIRONOLACTONE &amp; POTASSIUM CHLORIDE\nReason for override: monitored\nPrevious override information:\nOverride added on 10/16/06 by SCHWISOW , CHUNG P , M.D. , M.P.H.\non order for POTASSIUM CHLORIDE IMMED. REL. PO ( ref #\n573534645 )\nSERIOUS INTERACTION: SPIRONOLACTONE &amp; POTASSIUM CHLORIDE\nReason for override: monitor Previous override information:\nOverride added on 10/16/06 by TROTZ , HEATH D. , M.D. , PH.D.\non order for CAPTOPRIL PO ( ref # 244774599 )\nPOTENTIALLY SERIOUS INTERACTION: SPIRONOLACTONE &amp; CAPTOPRIL\nReason for override: aware\nINSULIN ASPART Sliding Scale ( subcutaneously ) SC AC\nIf BS is less than 125 , then give 0 units subcutaneously\nIf BS is 125-150 , then give 2 units subcutaneously\nIf BS is 151-200 , then give 3 units subcutaneously\nIf BS is 201-250 , then give 4 units subcutaneously\nIf BS is 251-300 , then give 6 units subcutaneously\nIf BS is 301-350 , then give 8 units subcutaneously\nIf BS is 351-400 , then give 10 units subcutaneously and\ncall HO Call HO if BS is greater than 400\nDIET: Fluid restriction\nDIET: House / Low chol/low sat. fat\nDIET: 2 gram Sodium\nACTIVITY: Walking as tolerated\nFOLLOW UP APPOINTMENT( S ):\ncardiology dr lelonek 714.815.2497 1-4 weeks ,\npcp dr hoyt shimek 556-913-5202 2 weeks ,\nALLERGY: NKA\nADMIT DIAGNOSIS:\nchf , unstable angina\nPRINCIPAL DISCHARGE DIAGNOSIS ;Responsible After Study for Causing Admission )\nchf exacerbation\nOTHER DIAGNOSIS;Conditions , Infections , Complications , affecting Treatment/Stay\nchf exacerbation\nOPERATIONS AND PROCEDURES:\nnone\nOTHER TREATMENTS/PROCEDURES ( NOT IN O.R. )\necho 10/7 -with EF 20-25% , wall motion abnl , dil ivc , tr , mr. evidence of\natrial septal defect noted.\nMibi/PET-CT 6/1 test results are abnormal and c/w the following:\n1. A medium sized region of myocardial scar without residual\nischemia or viability in the distribution of the mid-LAD coronary\nartery.\n2. A small region of myocardial scar without residual ischemia\nor viability in the distribution of the PDA coronary artery.\n3. Moderate global LV systolic dysfunction.\nBRIEF RESUME OF HOSPITAL COURSE:\nCC- sent in by pcp for chest pressure\nHPI-66yo M spanish speaking from O Ankament Ta 1/10 had labs drawn at\nfrelawn dinghung ant hospital .  11/17 saw pcp , reported sig.cardiac hx. and over the past\nfew months has had an increase in chest pressure , nonradiating , initially\nsx on exertion , most recently at rest. On sunday ,\nhe was lying on couch when the sx started , took two nitro with good\nresolution. no sob , no n/v/diaphoresis/fevers. he has also noted\nworsening LE edema and weight gain of 30lbs over this time period. He\nadmits to missing his meds and to eating a lot of salt.\nHe was worked up at A in Tonusni for several months to\ntry and determine how to best treat his cardiac disease. Per the pt , they\nsaid they couldn't do anything for him.\nIn ED , afebrile hr 60s , BP 110s sat 100%RA. . Tx with lasix 80iiv , asa\n325 , coreg\n6.25 , inuslin 8u. OU 1500. CXR c/w pulm edema\nExam\nGen- resting comfortably in bed , no c/o\nHEENT- jvp to jaw\nPulm- b/l crackles at bases\nAbd- soft , NT , ND\nExt- c/o rt foot pain , no signs of trauma. slight edema , b/l , c/o ttp\nalong top of left. DPs not palpable\nHome meds\nplavix75\nasa81\ncarnitidine ( ? ) 150 bid\nimdur 30\ndigitek 0.125\nlasix 80\ncoreg 6.25\nspironolactone 50\ninsulin 70/30 50qam , 35 qpm\nNKDA\nPMH\nmi x3 ( 1993 ) - ? cath , ?inoperable , knows he has 3v\ndz\nhtn\nchf\ngerd\ndm\nShx\nfrom U Salosra Scot\nexsmoker quit 5y pta\nno etoh , no ivdu\nFHx\nbrother died of MI 10/22 in 50s\nparents died of CAD in 70s/80s\nhtn , dm\nstudies\ncxr 6/10 cardiomegaly , increased interstitial marking c/w pulm edema\nekg- nsr 1 degree avblock , nl axis , q in v1-v3 , poor r waves in v4-v5 , T\ninversion 3 , avf , biphasic Ts and mild depression ( &lt;0.5mm ) in v5\necho 10/7 -with EF 20-25% , wall motion abnl , dil ivc , tr , mr. evidence of\nASD seen.\nMibi 6/1 no evidence of reversible ischemia\nassessment and plan\n66yo with cad/mi , dm , chf , admitted for chf exacerbation and r/o MI\n1.\tCV-\na.\t ischemia- sig cad with hx of chest presure at rest , ce -x2. ekg\nabnl w/o priors , concerning for unstable angina. given asa , carvedilol\n( changed to lisinopril 5/26 ) , lipitor , plavix and started on lovenox 100\nsq. Lovenox was stopped when ce neg x3 on 10/7 .  Lipid panel ok , continue\non lipitor 80. Has been CP free since Sunday. Stressed on 5/26 , results\nshow no evidence of reversible ischemia and pt has had no CP while in the\nhospital.\nb.\tpump - chf exacerbation , likely 2/2 not taking meds and poor diet\ncontrol. will txc with lasix 40iv bid , goals -1liter/day. pt already\nimproving- good diuresis with lasix 40iv. continue home spironolactone ,\nrestarted on home imdur. ACEi started and increased to 10mg qd. fluid\nrestricted to 2L.\necho 10/7 with EF 20-25% , wall motion abnl , dil ivc , tr , mr. Patient has\ndiuresed well during his time in house with a weight on dc of 82\nkg.Continue on lasix 80po daily.\nc.\t rhythm- sinus , on tele. long Pr interval noted , dig stopped to\navoid any additional PR prolongation. may need EP workup in the future.\n2.\tpulm- cardiogenic pulm edema , imprving. sat stable on RA.\ncontinue diuresis. On room air throughout his time in house , appears very\ncomfortable.\n3.\t GI- mild transaminitis- decreased over the course of his time\nhere and normal AST/ALT/Tbili on day of discharge. Alk phos contiues to\nbe elevated at 175. Will need pcp follow up evaluation , but no abdominal\ncomplaints.\n4.\tHeme- on lovenox for UA , transitioned to SC DVT ppx dosing on\n10/7 , on plavix for ? stent. Will continue on plavix and asa as outpt.\n5.\tendo- nph 18 bid for now ( inc from home 10 ) , 6u ac and ss. hgb\na1c 10.4- indicating need for tighter glucose control. He will go home on\nan increased dose on NPH and advised to keep tight control over his blood\nsugar.\n6.\tmsk- c/o left foot pain , unclear source. xray final read shows\ndegenerative changes. able to doppler DPs. ? claudication? Patient is\npain free now.\n7.\tfen- ada , cardiac diet. Lytes repleted while in house , all normal\non discharge.\n8.\tPatient is staible for discharge home. He will need to followup\nwith cardiology as an outpt.\nADDITIONAL COMMENTS: 1. take all your medications as directed.\n2. Weigh yourself daily , if you start to gain weight ( even 5 pounds ) , you\nneed to contact your doctor about increasing your lasix dose.\n3. Follow up with cardiology as directed.\n4. check you blood sugars in the morning and with meals. adjust your\ninsulin as needed. dr erick bedaw at carlekadl rine calccal memorial hospital of county will be following his\nblood sugars.\n5. get a recheck of your lfts as an outpt , your Alk Phos and GGT were\nelevated.\nDISCHARGE CONDITION: Stable\nTO DO/PLAN:\n1. take all your medications as directed.\n2. Weigh yourself daily , if you start to gain weight ( even 5 pounds ) , you\nneed to contact your doctor about increasing your lasix dose.\n3. Follow up with cardiology as directed.\nNo dictated summary\nENTERED BY: DONNA , EMMANUEL E , M.D. , M.P.H. ( YH225 ) 8/4/06 @ 12:54 PM\n****** END OF DISCHARGE ORDERS ******\n[report_end]\n", "annotations": [{"medication_name": "acetylsalicylic acid", "medication_dosage": "81 mg", "mode": "po ", "frequency": "daily ", "line": "19"}, {"medication_name": "atorvastatin", "medication_dosage": "80 mg", "mode": "po", "frequency": "daily", "line": "20"}, {"medication_name": "coreg ( carvedilol )", "medication_dosage": "3.125 mg", "mode": "po ", "frequency": "bid ", "line": "21"}, {"medication_name": "plavix ( clopidogrel )", "medication_dosage": "75 mg", "mode": "po", "frequency": "daily", "line": "27"}, {"medication_name": "lasix ( furosemide )", "medication_dosage": "80 mg", "mode": "po", "frequency": "daily", "line": "28"}, {"medication_name": "insulin 70/30 human", "medication_dosage": "50 units", "mode": "", "frequency": "qam 35", "line": "29"}, {"medication_name": "insulin 70/30 human", "medication_dosage": "35 units", "mode": "sc", "frequency": "qpm", "line": "29"}, {"medication_name": "insulin 70/30 human", "medication_dosage": "50 units", "mode": "", "frequency": "qam;", "line": "29"}, {"medication_name": "insulin 70/30 human", "medication_dosage": "35 units", "mode": "", "frequency": "qpm", "line": "29"}, {"medication_name": "imdur er ( isosorbide mononitrate ( sr ) )", "medication_dosage": "30 mg", "mode": "po", "frequency": "daily", "line": "31"}, {"medication_name": "lisinopril", "medication_dosage": "10 mg", "mode": "po", "frequency": "daily", "line": "35"}, {"medication_name": "spironolactone", "medication_dosage": "", "mode": "", "frequency": "", "line": "38"}, {"medication_name": "lisinopril", "medication_dosage": "", "mode": "", "frequency": "", "line": "39"}, {"medication_name": "potassium chloride", "medication_dosage": "", "mode": "", "frequency": "", "line": "40"}, {"medication_name": "lisinopril", "medication_dosage": "", "mode": "", "frequency": "", "line": "41"}, {"medication_name": "potassium chloride", "medication_dosage": "", "mode": "", "frequency": "", "line": "42"}, {"medication_name": "lisinopril", "medication_dosage": "", "mode": "", "frequency": "", "line": "43"}, {"medication_name": "metamucil sugar free ( psyllium ( metamucil ) su... )", "medication_dosage": "1 packet", "mode": "po", "frequency": "daily", "line": "44"}, {"medication_name": "spironolactone", "medication_dosage": "50 mg", "mode": "po", "frequency": "daily", "line": "46"}, {"medication_name": "lisinopril", "medication_dosage": "", "mode": "po", "frequency": "", "line": "50"}, {"medication_name": "spironolactone", "medication_dosage": "", "mode": "", "frequency": "", "line": "51"}, {"medication_name": "lisinopril", "medication_dosage": "", "mode": "", "frequency": "", "line": "52"}, {"medication_name": "kcl immediate release", "medication_dosage": "", "mode": "po", "frequency": "", "line": "55"}, {"medication_name": "spironolactone", "medication_dosage": "", "mode": "", "frequency": "", "line": "57"}, {"medication_name": "potassium chloride", "medication_dosage": "", "mode": "", "frequency": "", "line": "57"}, {"medication_name": "potassium chloride immed. rel.", "medication_dosage": "", "mode": "po", "frequency": "", "line": "61"}, {"medication_name": "spironolactone", "medication_dosage": "", "mode": "", "frequency": "", "line": "63"}, {"medication_name": "potassium chloride", "medication_dosage": "", "mode": "", "frequency": "", "line": "63"}, {"medication_name": "captopril", "medication_dosage": "", "mode": "po", "frequency": "", "line": "66"}, {"medication_name": "spironolactone", "medication_dosage": "", "mode": "", "frequency": "", "line": "67"}, {"medication_name": "captopril", "medication_dosage": "", "mode": "", "frequency": "", "line": "67"}, {"medication_name": "insulin aspart", "medication_dosage": "4 units", "mode": "subcutaneously", "frequency": "", "line": "69"}, {"medication_name": "insulin aspart", "medication_dosage": "0 units", "mode": "subcutaneously", "frequency": "", "line": "69"}, {"medication_name": "insulin aspart", "medication_dosage": "6 units", "mode": "subcutaneously", "frequency": "", "line": "69"}, {"medication_name": "insulin aspart", "medication_dosage": "sliding scale", "mode": "( subcutaneously ) sc", "frequency": "ac", "line": "69"}, {"medication_name": "insulin aspart", "medication_dosage": "8 units", "mode": "subcutaneously", "frequency": "", "line": "69"}, {"medication_name": "insulin aspart", "medication_dosage": "2 units", "mode": "subcutaneously", "frequency": "", "line": "69"}, {"medication_name": "insulin aspart", "medication_dosage": "3 units", "mode": "subcutaneously", "frequency": "", "line": "69"}, {"medication_name": "insulin aspart", "medication_dosage": "10 units", "mode": "subcutaneously", "frequency": "", "line": "69"}, {"medication_name": "nitro", "medication_dosage": "two", "mode": "", "frequency": "", "line": "110"}, {"medication_name": "meds", "medication_dosage": "", "mode": "", "frequency": "", "line": "113"}, {"medication_name": "lasix", "medication_dosage": "80iiv", "mode": "", "frequency": "", "line": "117"}, {"medication_name": "asa", "medication_dosage": "325", "mode": "", "frequency": "", "line": "117"}, {"medication_name": "coreg", "medication_dosage": "6.25", "mode": "", "frequency": "", "line": "118"}, {"medication_name": "inuslin", "medication_dosage": "8u.", "mode": "", "frequency": "", "line": "119"}, {"medication_name": "plavix75", "medication_dosage": "", "mode": "", "frequency": "", "line": "128"}, {"medication_name": "asa81", "medication_dosage": "", "mode": "", "frequency": "", "line": "129"}, {"medication_name": "carnitidine", "medication_dosage": "150", "mode": "", "frequency": "bid", "line": "130"}, {"medication_name": "imdur", "medication_dosage": "30", "mode": "", "frequency": "", "line": "131"}, {"medication_name": "digitek", "medication_dosage": "0.125", "mode": "", "frequency": "", "line": "132"}, {"medication_name": "lasix", "medication_dosage": "80", "mode": "", "frequency": "", "line": "133"}, {"medication_name": "coreg", "medication_dosage": "6.25", "mode": "", "frequency": "", "line": "134"}, {"medication_name": "spironolactone", "medication_dosage": "50", "mode": "", "frequency": "", "line": "135"}, {"medication_name": "insulin 70/30", "medication_dosage": "35", "mode": "", "frequency": "qpm", "line": "136"}, {"medication_name": "insulin 70/30", "medication_dosage": "50qam", "mode": "", "frequency": "", "line": "136"}, {"medication_name": "asa", "medication_dosage": "", "mode": "", "frequency": "", "line": "164"}, {"medication_name": "carvedilol", "medication_dosage": "", "mode": "", "frequency": "", "line": "164"}, {"medication_name": "plavix", "medication_dosage": "", "mode": "", "frequency": "", "line": "165"}, {"medication_name": "lisinopril", "medication_dosage": "", "mode": "", "frequency": "", "line": "165"}, {"medication_name": "lipitor", "medication_dosage": "", "mode": "", "frequency": "", "line": "165"}, {"medication_name": "lovenox", "medication_dosage": "100", "mode": "sq.", "frequency": "", "line": "165"}, {"medication_name": "lovenox", "medication_dosage": "", "mode": "", "frequency": "", "line": "166"}, {"medication_name": "lipitor", "medication_dosage": "80", "mode": "", "frequency": "", "line": "167"}, {"medication_name": "lasix", "medication_dosage": "40iv", "mode": "", "frequency": "bid", "line": "171"}, {"medication_name": "spironolactone", "medication_dosage": "", "mode": "", "frequency": "", "line": "172"}, {"medication_name": "lasix", "medication_dosage": "40iv", "mode": "", "frequency": "", "line": "172"}, {"medication_name": "imdur.", "medication_dosage": "", "mode": "", "frequency": "", "line": "173"}, {"medication_name": "acei", "medication_dosage": "10mg", "mode": "", "frequency": "qd.", "line": "173"}, {"medication_name": "acei", "medication_dosage": "", "mode": "", "frequency": "", "line": "173"}, {"medication_name": "lasix", "medication_dosage": "80po", "mode": "", "frequency": "daily.", "line": "177"}, {"medication_name": "lovenox", "medication_dosage": "", "mode": "", "frequency": "", "line": "187"}, {"medication_name": "plavix", "medication_dosage": "", "mode": "", "frequency": "", "line": "188"}, {"medication_name": "asa", "medication_dosage": "", "mode": "", "frequency": "", "line": "188"}, {"medication_name": "nph", "medication_dosage": "10", "mode": "", "frequency": "", "line": "189"}, {"medication_name": "nph", "medication_dosage": "18", "mode": "", "frequency": "bid", "line": "189"}, {"medication_name": "nph", "medication_dosage": "6u", "mode": "ac", "frequency": "", "line": "189"}, {"medication_name": "nph", "medication_dosage": "an increased dose", "mode": "", "frequency": "", "line": "191"}, {"medication_name": "your medications", "medication_dosage": "", "mode": "", "frequency": "", "line": "200"}, {"medication_name": "medications", "medication_dosage": "", "mode": "", "frequency": "", "line": "200"}, {"medication_name": "lasix", "medication_dosage": "", "mode": "", "frequency": "", "line": "202"}, {"medication_name": "insulin", "medication_dosage": "", "mode": "", "frequency": "as needed.", "line": "205"}, {"medication_name": "medications", "medication_dosage": "", "mode": "", "frequency": "", "line": "211"}, {"medication_name": "your medications", "medication_dosage": "", "mode": "", "frequency": "", "line": "211"}, {"medication_name": "lasix", "medication_dosage": "dose.", "mode": "", "frequency": "", "line": "213"}]}