{"text": "RECORD #731937\n\n\n601682374 | S | 45082046 | | 7656711 | 1/19/2005 12:00:00 AM | Discharge Summary | Unsigned | DIS | Admission Date: 1/19/2005 Report Status: Unsigned\n\nDischarge Date:\nATTENDING: CRUMBLE , MODESTO LEIF MD\nINTERIM DICTATION\nDATE OF SURGERY: 9/22/2005\nPREOPERATIVE DIAGNOSES: Infective endocarditis , coronary artery\ndisease.\nPOSTOPERATIVE DIAGNOSES: Infective endocarditis , coronary artery\ndisease.\nPROCEDURE: Mitral valve replacement , #28Other annuloplasty\nring , ring annuloplasty , leaflet resection , post leaflet\nchordoplasty with Gore-Tex suture , Vegetectomy , SBE , CABG x1.\nHISTORY OF PRESENT ILLNESS: The patient is a 64-year-old male\nwith signs of past medical history of diet-controlled diabetes\nmellitus , type 2; HTN , status post MI with RCA stent in 1999 who\npresents to ICU from emergency department after being found down\nat home with change in mental status. The patient was in USOH\nuntil approximately six to seven days PTA when he noticed sudden\nonset of sharp left shoulder pain without substernal chest pain\nor pressure. The patient notes that the pain in his body all\nover and his shoulder continued to be excruciating and without\nrelent. He also noted onset of upper and lower extremity\nweakness and that his legs felt heavy. After he did not show up\nto work for several days , the patient was found down in his house\nincontinent of urine. He was found to have profound metabolic\nacidosis , hypertensive , hypovolemic , febrile , covered all over\nthe skin with hemorrhagic rash and required fluid resuscitation\nand Levophed infusion. Lumbar puncture showed over 100 white\nblood cells. Urine was dirty and the patient found to have rash\non back and extremities , which were biopsied by dermatologist on\n1/30/2005 . The patient has since had four of four blood\ncultures positive for gram-positive cocci in clusters(\npreliminary Staphylococcus aureus , MSSA. ) Two of four bottles of\ngram-negative rods enteric and pink , status post stenting and had\nmore than 1100 Staphylococcus aureus from 1/19/2005 urine\nculture. TTE on 1/30/2005 showing vegetation on mitral valve.\nPREOPERATIVE CARDIAC STATUS: Urgent: The patient presented with\ninfection of myocardial infarction in March 1999 requiring\nhospitalization associated with prolonged chest pain. The\npatient does not have symptoms of heart failure. Recent signs\nand symptoms of congestive heart failure include pedal edema.\nThe patient is in normal sinus rhythm.\nPREVIOUS CARDIOVASCULAR INTERVENTIONS: Stent in March 1999.\nPAST MEDICAL HISTORY: Stroke , extremity weakness , history of\npermanent muscle weakness of all four extremities , loss of\nconsciousness. The patient was found at home unconscious within\ntwo weeks of surgery , diabetes mellitus , insulin therapy ,\ninfective endocarditis:active , receiving vancomycin ,\nlevofloxacin , Flagyl , ceftazidime , gentamicin , Nafcillin ,\nhypercholesterolemia , heparin-induced thrombocytopenia , HAT\nduring hospitalization in 1999 , creatinine clearance 158.18.\nPAST SURGICAL HISTORY: None.\nFAMILY HISTORY: No family history of coronary artery disease.\nSOCIAL HISTORY: No history of tobacco use.\nALLERGIES: Heparin , HIT .\nADMISSION MEDICATIONS: Heparin low molecular weight last dose\nless than 24 hours , enoxaparin , Lovenox 40 mg subcu daily ,\nnorepinephrine 3 mcg per kg per minute continuous , simvastatin 40\nmg p.o. daily , Nexium 40 mg p.o. daily , ceftazidime 2000 mg IV\nq8h , gentamicin 560 mg IV q.24h. , penicillin G , potassium 3\nmillion units IV.\nPHYSICAL EXAMINATION: Height and Weight: 5 feet 9 inches , 92.7\nkg. Vital Signs: Temperature 99 , heart rate 120 , blood pressure\nright arm 107/65 , extubated on 9/0/2005 6 p.m. , FiO2 4 L nasal\ncannula , ambulating , oxygen saturation 99%. HEENT: PERRLA.\nDentition without evidence of infection. No carotid bruits.\nChest: No incisions. Cardiovascular: No murmurs. Respiratory:\nRales present bilaterally. Abdomen: No incisions , soft. No\nmasses. Rectal: Deferred. Extremities: Leg edematous 1+ 2+ ,\ndiminished muscle strength 4/5. Neuro: Alert and oriented. No\nfocal deficits.\nPREOP LABS: On 7/9/2005 , sodium 143 , potassium 4.1 , chloride\n114 , CO2 21 , BUN 11 , creatinine 0.7 , glucose 110 , magnesium 2.1.\nHematology on 9/0/2005 , white blood cells 423 , hematocrit 32.2 ,\nhemoglobin 10.9 , platelets 73 , PT 14.9 , INR 1.2 , PTT 28.4. ABGs;\nPO2 72 , pH 7.52 , PCO2 28 , total CO2 23 , base excess 0.\nUrinalysis consisted with infection.\nCARDIAC CATHETERIZATION DATA: On 9/0/2005 performed at N . \nCoronary anatomy 50% LAD , 45% mid Ramus , dominant circulation ,\nLVEDP 15 mmHg. Echo on 1/30/2005 , 55% ejection fraction , mild\nmitral insufficiency , trivial pulmonic insufficiency , the mitral\nvalve is myxomatous. There is a 2-cm focal leaflet mass on the\nmitral leaflet that could represent a vegetation. EKG on\n1/30/2005 , normal sinus rhythm at 117. Chest x-ray on\n9/0/2005 consistent with congestive heart failure and left base\nopacity , probably atelectasis has worsened. There is minimal new\nright basilar atelectasis. Upper lung zones remain clear. The\nheart is enlarged with vascular engorgement , but no frank\npulmonary edema. Central line remains in the CVC. There is no\npneumothorax seen.\nPROCEDURE: MVP #28 Other annuloplasty ring , ring annuloplasty ,\nleaflet resection , post leaflet chordoplasty with Gore-Tex\nsuture , Vegetectomy , SBE , CABG x1.\nBYPASS: 350 minutes.\nCROSS CLAMP: 288 minutes.\nOpen chest one ventricular wire , one pericardial tube , one\nretrosternal tube , two pleural tubes. Open chest/semarch with\nbridge fashioned from 60 mL syringe and single lap pad left in\nplace.\nICU PROGRESS EVENT SUMMARY: POD 1 on 7/6/2005 ; admitted to ICU\npostop with open chest after 6 hour pump run.Overnight\nvasodilated , requiring pressors , inotrops and methylene blue. POD\n2 , Weaned of onoptrops successfully; Cultured from OR- Staff ,\nantibiotics changed. Previous allergy ceftriaxone , gentamicin ,\nlevofloxacin discontinued , one unit of packed red blood cells\ngiven , SVO2 improved; hematocrit stable. Chest open on fentanyl\nand Versed/semarch. On 3/28/2005 POD 3 difficult to wean\ninotrops Culture from OR staff. Antibiotics changed. Previous\nallergy ceftriaxone , gentamicin , levofloxacin discontinued.\nChest washout yesterday , hematocrit stable. Chest remains; open\non fentanyl and Versed ;for 2ND washout+/- closure later this\nweek. POD 4 stable , remains on epi and vaso , diuresing.Plan to\nclose chest tomorrow.POD 5Pressors continued , continued\ndiuresis. Abx adjustments made per ID recommendations ,\ndiscontinue vancomycin and gentamicin. POD 6 , chest closed\nyesterday , ongoing pressor requirement. POD 7 , ventilation weaned\nto pressure support ventilation , sedation weaned , epinephrine\nweaned to off/ , vasopressin weaned. Coffee-ground output via\nnasogastric tube today. POD 8 , developed fluctuant collection ,\nleft supraclavicular fossa . CT confirmed probable collection in\nclavicular scapular region , no bony involvement. Aspiration\nrevealed gram-positive cocci. Orthopedics aware , will review\ntoday , remains vasodilated on vasopressin. Diuresed well. POD\n9 , had I&amp;D of collection yesterday , hypertensive 0f pressors ,\nrequiring increasing Lopressor doses , now on minimal ventilator\nsupport. POD 10 , extubated , hypertensive , requiring Lopressor ,\nTNG , Hydralazine. Temperature 102 , failed speech evaluation. POD\n11 , remains on nicardipine drip for hypertension , febrile 102.\nPOD 12 , off nicardipine drip. Abscess in right thigh discharged\nspontaneously. PICC line now in. Small amount of fresh blood\nper rectum. No drop in hematocrit. Afebrile , taking p.o. diet ,\ndiuresing. MRSA. POD 14 , MRSA in sputum , started on vancomycin.\nArterial line discontinued. POD 15 , started on tube feeds ,\nhypertensive , Lopressor dose reduced to 50. POD 16 ,\nsputum-growing MRSA. Right-sided effusion seen on chest x-ray\nwith elevation of right diaphragm.Pulled out dop-hof overnight.\nPOD 17 , VRE isolated from right side abscess. Now oriented x3.\nICU TRANSFER NOTE: Date of transfer , 7/9/2005 .\nSUMMARY BY SYSTEM:\n1. Neurologic: Mental status intact , alert , and oriented.\nNeurological exam , no focal deficits. Now oriented to place ,\nmonth and year. Marked improvement.\n2. Cardiovascular: Cardiac medications: Aspirin , Lopressor , .\nHeart rate , normal sinus rhythm at 95 , blood pressure 120/60 .\nECG , preop ejection fraction 65% EF. Echo on 1/30/2005 .\nCardiac meds , Lopressor 37.5 p.o. q.6h. Exam , RRR. S1 , S2 , WNL.\n3. Respiratory: Ventilated more than 24 hours postoperatively.\nExtubated on 10/26/2005 , FiO2 3 L nasal cannula , out of bed.\nChest x-ray findings: Extubated on 10/26/2005 , POD 9.\n4. GI: Diet. Mechanical soft , liquid consistency , nectar , tube\nfeeds , Jevity 1.2 tube feeds , rate 100 mL /hr , 0 scoops/day\ncalories.\n5. Renal: Fluid in 1700 mL 24 hours , urine output 3200 mL ,\nbalance -1500.\nWeight: Previous day weight 84.5 kg.\n6. Endocrine: Diabetes. Meds , insulin 10 units subcutaneously\nat 10 p.m. , Lantus 22 units SC q.p.m.\n7. Heme: Anticoagulation. Aspirin.\n8. ID: Septicemia. Organism , Staphylococcus aureus.\nAntibiotics , vancomycin started on 9/22/2005 , penicillin G ,\npotassium 3 million units IV. Skin lesion infection. Organism ,\nVRE. Antibiotics , ceftriaxone 2000 mg IV daily , penicillin G ,\npotassium 4 million units started on 9/14/2005 . Current\nantibiotics , vancomycin day 18 for Staph aureus septicemia ,\npenicillin G 3 million units IV , ceftriaxone 2000 mg IV daily ,\npenicillin G , potassium 4 million units day 13 for Staph aureus\nsepticemia , VRE skin lesion infection. T-max 99.2 Fahrenheit.\nID consult declined , needs inLineziline for right side abscess.\n9. Neurologic plan: Continue to monitor neurologic progress.\n10. Cardiovascular plan: Watch blood pressure , titrate\nLopressor as tolerated while diuresing.\n11. Respiratory plan:OOB with PT , wean oxygen.\n12. Gastrointestinal plan: Did well with oral diet yesterday.\nContinue to encourage oral diet and monitor calorie intake.\n13. Renal plan: Continue gentle diuresis.\n14. Endocrine: Controlled.\n15. Hematologic plan: Monitor hematocrit. Ensue his wearing\npneumatic boots. Minor procedures: Bronchoscopy , therapeutic\nrespiration.\nMOST RECENT MEDICATIONS: Lopressor 37.5 mg p.o. q.6h. , Lasix 20\nmg p.o. t.i.d. , acetylsalicylic acid 325 mg p.o. , Naturale Tears\none drop O.U. , Colace 100 mg p.o. t.i.d. , insulin regular Humulin\n4 units subcu , lactinex granules 2 tabs p.o. , magnesium sulfate ,\nsliding scale intravenously , penicillin G , potassium 4 million\nunits IV , vancomycin 1000 mg IV , Nexium 20 mg p.o. daily , Lantus\n22 units subcu q.p.m. , NovoLog sliding scale SC.\neScription document: 1-4775276 HFFocus\nDictated By: GAIN , LENNY\nAttending: DITUCCI , KIETH CLAUD\nDictation ID 7748550\nD: 7/4/05\nT: 3/15/05\n[report_end]\n", "annotations": [{"medication_name": "levophed", "medication_dosage": "", "mode": "infusion.", "frequency": "", "line": "32"}, {"medication_name": "insulin", "medication_dosage": "", "mode": "", "frequency": "", "line": "51"}, {"medication_name": "vancomycin", "medication_dosage": "", "mode": "", "frequency": "", "line": "52"}, {"medication_name": "flagyl", "medication_dosage": "", "mode": "", "frequency": "", "line": "53"}, {"medication_name": "ceftazidime", "medication_dosage": "", "mode": "", "frequency": "", "line": "53"}, {"medication_name": "nafcillin", "medication_dosage": "", "mode": "", "frequency": "", "line": "53"}, {"medication_name": "gentamicin", "medication_dosage": "", "mode": "", "frequency": "", "line": "53"}, {"medication_name": "levofloxacin", "medication_dosage": "", "mode": "", "frequency": "", "line": "53"}, {"medication_name": "heparin low molecular weight", "medication_dosage": "", "mode": "", "frequency": "", "line": "60"}, {"medication_name": "enoxaparin", "medication_dosage": "", "mode": "", "frequency": "", "line": "61"}, {"medication_name": "lovenox", "medication_dosage": "40 mg", "mode": "subcu", "frequency": "daily", "line": "61"}, {"medication_name": "norepinephrine", "medication_dosage": "3 mcg per kg per minute continuous", "mode": "", "frequency": "", "line": "62"}, {"medication_name": "simvastatin", "medication_dosage": "40 mg", "mode": "p.o.", "frequency": "daily", "line": "62"}, {"medication_name": "nexium", "medication_dosage": "40 mg", "mode": "p.o.", "frequency": "daily", "line": "63"}, {"medication_name": "ceftazidime", "medication_dosage": "2000 mg", "mode": "iv", "frequency": "q8h", "line": "63"}, {"medication_name": "penicillin g", "medication_dosage": "", "mode": "", "frequency": "", "line": "64"}, {"medication_name": "gentamicin", "medication_dosage": "560 mg", "mode": "iv", "frequency": "q.24h.", "line": "64"}, {"medication_name": "potassium", "medication_dosage": "3 million units", "mode": "iv", "frequency": "", "line": "64"}, {"medication_name": "pressors", "medication_dosage": "", "mode": "", "frequency": "", "line": "106"}, {"medication_name": "inotrops", "medication_dosage": "", "mode": "", "frequency": "", "line": "106"}, {"medication_name": "methylene blue.", "medication_dosage": "", "mode": "", "frequency": "", "line": "106"}, {"medication_name": "onoptrops", "medication_dosage": "", "mode": "", "frequency": "", "line": "107"}, {"medication_name": "antibiotics", "medication_dosage": "", "mode": "", "frequency": "", "line": "108"}, {"medication_name": "packed red blood cells", "medication_dosage": "one unit", "mode": "", "frequency": "", "line": "109"}, {"medication_name": "fentanyl", "medication_dosage": "", "mode": "", "frequency": "", "line": "110"}, {"medication_name": "versed/semarch.", "medication_dosage": "", "mode": "", "frequency": "", "line": "111"}, {"medication_name": "inotrops", "medication_dosage": "", "mode": "", "frequency": "", "line": "112"}, {"medication_name": "antibiotics", "medication_dosage": "", "mode": "", "frequency": "", "line": "112"}, {"medication_name": "fentanyl", "medication_dosage": "", "mode": "", "frequency": "", "line": "115"}, {"medication_name": "versed", "medication_dosage": "", "mode": "", "frequency": "", "line": "115"}, {"medication_name": "vaso", "medication_dosage": "", "mode": "", "frequency": "", "line": "116"}, {"medication_name": "epi", "medication_dosage": "", "mode": "", "frequency": "", "line": "116"}, {"medication_name": "vancomycin", "medication_dosage": "", "mode": "", "frequency": "", "line": "119"}, {"medication_name": "gentamicin.", "medication_dosage": "", "mode": "", "frequency": "", "line": "119"}, {"medication_name": "pressor", "medication_dosage": "", "mode": "", "frequency": "", "line": "120"}, {"medication_name": "epinephrine", "medication_dosage": "", "mode": "", "frequency": "", "line": "121"}, {"medication_name": "sedation", "medication_dosage": "", "mode": "", "frequency": "", "line": "121"}, {"medication_name": "vasopressin", "medication_dosage": "", "mode": "", "frequency": "", "line": "122"}, {"medication_name": "vasopressin.", "medication_dosage": "", "mode": "", "frequency": "", "line": "127"}, {"medication_name": "pressors", "medication_dosage": "", "mode": "", "frequency": "", "line": "128"}, {"medication_name": "lopressor", "medication_dosage": "", "mode": "", "frequency": "", "line": "129"}, {"medication_name": "lopressor", "medication_dosage": "", "mode": "", "frequency": "", "line": "130"}, {"medication_name": "tng", "medication_dosage": "", "mode": "", "frequency": "", "line": "131"}, {"medication_name": "hydralazine.", "medication_dosage": "", "mode": "", "frequency": "", "line": "131"}, {"medication_name": "nicardipine", "medication_dosage": "", "mode": "drip", "frequency": "", "line": "132"}, {"medication_name": "nicardipine", "medication_dosage": "", "mode": "drip", "frequency": "", "line": "133"}, {"medication_name": "vancomycin.", "medication_dosage": "", "mode": "", "frequency": "", "line": "136"}, {"medication_name": "lopressor", "medication_dosage": "50", "mode": "", "frequency": "", "line": "138"}, {"medication_name": "aspirin", "medication_dosage": "", "mode": "", "frequency": "", "line": "147"}, {"medication_name": "lopressor", "medication_dosage": "", "mode": "", "frequency": "", "line": "147"}, {"medication_name": "cardiac meds", "medication_dosage": "", "mode": "", "frequency": "", "line": "150"}, {"medication_name": "lopressor", "medication_dosage": "37.5", "mode": "p.o.", "frequency": "q.6h.", "line": "150"}, {"medication_name": "insulin", "medication_dosage": "10 units", "mode": "subcutaneously", "frequency": "10 p.m.", "line": "160"}, {"medication_name": "lantus", "medication_dosage": "22 units", "mode": "sc", "frequency": "q.p.m.", "line": "161"}, {"medication_name": "aspirin.", "medication_dosage": "", "mode": "", "frequency": "", "line": "162"}, {"medication_name": "antibiotics", "medication_dosage": "", "mode": "", "frequency": "", "line": "164"}, {"medication_name": "vancomycin", "medication_dosage": "", "mode": "", "frequency": "", "line": "164"}, {"medication_name": "penicillin g", "medication_dosage": "", "mode": "", "frequency": "", "line": "164"}, {"medication_name": "potassium", "medication_dosage": "3 million units", "mode": "iv.", "frequency": "", "line": "165"}, {"medication_name": "antibiotics", "medication_dosage": "", "mode": "", "frequency": "", "line": "166"}, {"medication_name": "penicillin g", "medication_dosage": "", "mode": "", "frequency": "", "line": "166"}, {"medication_name": "ceftriaxone", "medication_dosage": "2000 mg", "mode": "iv", "frequency": "daily", "line": "166"}, {"medication_name": "potassium", "medication_dosage": "4 million units", "mode": "", "frequency": "", "line": "167"}, {"medication_name": "antibiotics", "medication_dosage": "", "mode": "", "frequency": "", "line": "168"}, {"medication_name": "vancomycin", "medication_dosage": "", "mode": "", "frequency": "", "line": "168"}, {"medication_name": "penicillin g", "medication_dosage": "3 million units", "mode": "iv", "frequency": "", "line": "169"}, {"medication_name": "ceftriaxone", "medication_dosage": "2000 mg", "mode": "iv", "frequency": "daily", "line": "169"}, {"medication_name": "penicillin g", "medication_dosage": "", "mode": "", "frequency": "", "line": "170"}, {"medication_name": "potassium", "medication_dosage": "4 million units", "mode": "", "frequency": "", "line": "170"}, {"medication_name": "lopressor", "medication_dosage": "titrate", "mode": "", "frequency": "", "line": "175"}, {"medication_name": "oxygen", "medication_dosage": "", "mode": "", "frequency": "", "line": "176"}, {"medication_name": "lopressor", "medication_dosage": "37.5 mg", "mode": "p.o.", "frequency": "q.6h.", "line": "184"}, {"medication_name": "lasix", "medication_dosage": "20 mg", "mode": "p.o.", "frequency": "t.i.d.", "line": "184"}, {"medication_name": "naturale tears", "medication_dosage": "one drop", "mode": "o.u.", "frequency": "", "line": "185"}, {"medication_name": "acetylsalicylic acid", "medication_dosage": "325 mg", "mode": "p.o.", "frequency": "", "line": "185"}, {"medication_name": "colace", "medication_dosage": "100 mg", "mode": "p.o.", "frequency": "t.i.d.", "line": "186"}, {"medication_name": "insulin regular humulin", "medication_dosage": "4 units", "mode": "subcu", "frequency": "", "line": "186"}, {"medication_name": "magnesium sulfate", "medication_dosage": "sliding scale", "mode": "intravenously", "frequency": "", "line": "187"}, {"medication_name": "lactinex granules", "medication_dosage": "2 tabs", "mode": "p.o.", "frequency": "", "line": "187"}, {"medication_name": "potassium", "medication_dosage": "4 million units", "mode": "iv", "frequency": "", "line": "188"}, {"medication_name": "penicillin g", "medication_dosage": "", "mode": "", "frequency": "", "line": "188"}, {"medication_name": "nexium", "medication_dosage": "20 mg", "mode": "p.o.", "frequency": "daily", "line": "189"}, {"medication_name": "vancomycin", "medication_dosage": "1000 mg", "mode": "iv", "frequency": "", "line": "189"}, {"medication_name": "lantus", "medication_dosage": "22 units", "mode": "subcu", "frequency": "q.p.m.", "line": "189"}, {"medication_name": "novolog", "medication_dosage": "sliding scale", "mode": "sc.", "frequency": "", "line": "190"}]}