{"text": "RECORD #497131\n089633078 | SMC | 47778883 | | 4598548 | 1/12/2005 12:00:00 AM | back pain , UTI | | DIS | Admission Date: 7/9/2005 Report Status:\nDischarge Date: 5/12/2005\n****** FINAL DISCHARGE ORDERS ******\nEADDY , DEAN 708-09-45-0\nTl I\nService: MED\nDISCHARGE PATIENT ON: 3/15/05 AT 12:30 PM\nCONTINGENT UPON ekg\nWILL D/C ORDER BE USED AS THE D/C SUMMARY: YES\nAttending: RULLMAN , JARRETT Q. , M.D. , J.D.\nCODE STATUS:\nFull code\nDISPOSITION: Home w/ services\nDISCHARGE MEDICATIONS:\nACETYLSALICYLIC ACID 325 MG PO QD Starting Today ( 5/28 )\nInstructions: FOR YOUR HEART\nAlert overridden: Override added on 7/4/05 by DAGDAG , DION EMMETT , M.D. , PH.D.\non order for ACETYLSALICYLIC ACID PO ( ref # 262695316 )\nPt. has a POSSIBLE allergy to IBUPROFEN; reaction is Hives.\nReason for override: md aware\nCIPROFLOXACIN 250 MG PO Q12H X 5 Days\nStarting Today ( 5/28 )\nInstructions: FINISH ANTIBIOTICS TO TREAT YOUR URINARY\nTRACT INFECTION Food/Drug Interaction Instruction\nAdminister iron products a minimum of 2 hours before or\nafter a levofloxacin or ciprofloxacin dose dose\nIf on tube feeds , please cycle ( hold 1 hr before to 2 hr\nafter ) Take 2 hours before or 2 hours after dairy products.\nCOLACE ( DOCUSATE SODIUM ) 100 MG PO BID\nStarting Today ( 5/28 ) Instructions: STOOL SOFTNER\nFOLATE ( FOLIC ACID ) 1 MG PO QD\nGLIPIZIDE 5 MG PO Q12H\nStarting AT 9:00 PM ON 0/16 ( 5/28 )\nInstructions: for your diabetes\nLISINOPRIL 20 MG PO Q12H\nOverride Notice: Override added on 7/4/05 by\nBOWERY , TOM J. , M.D.\non order for KCL IMMEDIATE RELEASE PO ( ref #\n876350117 )\nPOTENTIALLY SERIOUS INTERACTION: LISINOPRIL &amp; POTASSIUM\nCHLORIDE Reason for override: monitoring\nPrevious override information:\nOverride added on 7/4/05 by FULBRIGHT , JEWELL R. , M.D.\non order for KCL IV ( ref # 739034101 )\nPOTENTIALLY SERIOUS INTERACTION: LISINOPRIL &amp; POTASSIUM\nCHLORIDE Reason for override: monitoring\nPrevious override information:\nOverride added on 7/4/05 by ANADIO , SHAWN E. , M.D.\non order for KCL SLOW RELEASE PO ( ref # 898030992 )\nPOTENTIALLY SERIOUS INTERACTION: LISINOPRIL &amp; POTASSIUM\nCHLORIDE Reason for override: aware\nPrevious override information:\nOverride added on 7/4/05 by RANDLES , COLEMAN KELLEY , M.D. , PH.D.\non order for K-LOR PO ( ref # 887251597 )\nPOTENTIALLY SERIOUS INTERACTION: LISINOPRIL &amp; POTASSIUM\nCHLORIDE Reason for override: md aware\nPrevious override information:\nOverride added on 7/4/05 by KLINGLESMITH , EFREN O. , M.D.\nPOTENTIALLY SERIOUS INTERACTION: POTASSIUM CHLORIDE &amp;\nLISINOPRIL Reason for override: md aware\nNIFEREX-150 150 MG PO BID\nMVI THERAPEUTIC ( THERAPEUTIC MULTIVITAMINS ) 1 TAB PO QD\nAlert overridden: Override added on 7/4/05 by CAPPAERT , BASIL R. , M.D.\nPOTENTIALLY SERIOUS INTERACTION: ATORVASTATIN CALCIUM &amp;\nNIACIN , VIT. B-3 Reason for override: requires\nTOPROL XL ( METOPROLOL SUCCINATE EXTENDED RELEASE )\n100 MG PO Q24H Food/Drug Interaction Instruction\nTake consistently with meals or on empty stomach.\nNumber of Doses Required ( approximate ): 3\nAMBIEN ( ZOLPIDEM TARTRATE ) 10 MG PO QHS PRN Insomnia\nFood/Drug Interaction Instruction\nGive on an empty stomach ( give 1hr before or 2hr after\nfood )\nKCL SLOW RELEASE 20 MEQ PO QD\nAs per WRH Potassium Chloride Policy:\neach 20 mEq dose to be given with 4 oz of fluid\nOverride Notice: Override added on 7/4/05 by WAYT , FERDINAND W. , M.D. on order for LISINOPRIL PO ( ref # 700978620 )\nPOTENTIALLY SERIOUS INTERACTION: POTASSIUM CHLORIDE &amp;\nLISINOPRIL Reason for override: md aware\nLIPITOR ( ATORVASTATIN ) 40 MG PO QHS\nStarting Today ( 5/28 ) Instructions: for your cholesterol\nOverride Notice: Override added on 7/4/05 by HALSELL , FIDEL J. , M.D.\non order for MVI THERAPEUTIC PO ( ref # 537040946 )\nPOTENTIALLY SERIOUS INTERACTION: ATORVASTATIN CALCIUM &amp;\nNIACIN , VIT. B-3 Reason for override: requires\nPLAVIX ( CLOPIDOGREL ) 75 MG PO QD Starting IN AM ( 3/28 )\nInstructions: to prevent blood clots\nCANDESARTAN 16 MG PO QD Starting Today ( 5/28 )\nInstructions: for your blood pressure\nADVAIR DISKUS 250/50 ( FLUTICASONE PROPIONATE/... )\n1 PUFF INH BID Starting Today ( 5/28 )\nInstructions: for your breathing\nLASIX ( FUROSEMIDE ) 40 MG PO BID\nInstructions: FOR LEG SWELLING\nOXYCONTIN ( OXYCODONE CONTROLLED RELEASE ) 45 MG PO Q12H\nStarting AT 5:00 PM ON 10/9/05 ( 5/28 )\nInstructions: for pain\nPERCOCET 1 TAB PO Q4-6 hours PRN Pain\nInstructions: for breakthrough pain not managed by\noxycontin\nALBUTEROL INHALER 2 PUFF INH QID PRN Wheezing\nInstructions: for your breathing\nALBUTEROL NEBULIZER 2.5 MG NEB Q4H PRN Wheezing\nInstructions: for your breathing\nMETAMUCIL SUGAR FREE ( PSYLLIUM ( METAMUCIL ) SU... )\n1-2 PACKET PO QD PRN Constipation\nNITROGLYCERIN 1/150 ( 0.4 MG ) 1 TAB SL Q5MIN X 3 doses\nPRN Chest Pain\nInstructions: if pain is not relieved by nitro , call 911.\nDIET: Patient should measure weight daily\nDIET: House / Low chol/low sat. fat\nDIET: House / ADA 1800 cals/dy\nDIET: 2 gram Sodium\nACTIVITY: Resume regular exercise\nFOLLOW UP APPOINTMENT( S ):\nBrentkii Hospital office will call you. If you do not hear from the office , call: 701-815-0965 ,\nDr. Kleinke , Renal 10/16 at 3PM scheduled ,\nDr. Romine , Cardiology 2/7 at 12:30 PM scheduled ,\nALLERGY: Erythromycins , Penicillins , CLINDAMYCIN , IBUPROFEN\nADMIT DIAGNOSIS:\nnephrolithiasis\nPRINCIPAL DISCHARGE DIAGNOSIS ;Responsible After Study for Causing Admission )\nback pain , UTI\nOTHER DIAGNOSIS;Conditions , Infections , Complications , affecting Treatment/Stay\nh/o IMI Non-cardiac chest pain , Lumbosacral disc dz Chronic pain syndrome\nMigraines , HTN , Anxiety Depression ALLERG:PCN , Erythro , Tetracy\nS/P PTCA 3/18 FOR OCC RCA POSITIVE ETT/MIBI 93: ANT/LAT WALL ISCHEMIA\nOPERATIONS AND PROCEDURES:\nOTHER TREATMENTS/PROCEDURES ( NOT IN O.R. )\nCT abd\nBRIEF RESUME OF HOSPITAL COURSE:\nCC: 59F w/ CAD recently RCA/OM1 stent admitted with\nnephrolithiasis for pain control. HPI: hx chronic pain syndrome on\npercocet and morphine ( also for OA ) , who recently had R heart\ncath and PCI 1 wks ago. During that admission , was noted to have\nhematuria --&gt; renal f/u. C/O L flank pain x 2 days , planned for CT.\nIn Cards clinic on DOA , noted poor pain control. admitted by ED for\npain control. Got ASA , no IVF. morphine. PMH: chronic pain syndrome ,\nFM on mscontin tid. CHF , diastolic dysfunction. OSA , CPAP. HTN , CAD ,\nchol , mult MI , stent x 3 1 wk ----------\nEVENTS: in ED OBS appeared comfortable on dilaudid and\nmorphine. ----------\nSTATUS: resumed on home pain regimen , required additional 25 mg oxycodone\novernight.\n--------- STUDIES:\nI- CT showed: kidney stones on R , by CT ureter in ED , no hydro.\nstones are old , not clear that this is causing her current pain.\n-------- IMP: 59F with CAD and recent PCI now with\nnephrolithiasis and pain control problems. PLAN:\n1. CV: gave lasix to increase filtration and UOP , while\nincreasing IVF to keep up w/ euvolemic state.\n- cont outpt regimen - asa , statin , bb , acei. 2. GU/RENAL: increase\nUOP w/ IVF and Lasix. 3. ID: does not appear to have systemic\ninfection. Inflammation of ureter. tx UTI ( UA+ ) with cipro 250 mg PO x 7\ndays. Started 1/16 , ending 2/12\n4. FEN: Diabetic , low salt , low fat/cholesterol diet 5. Pain control with\nhome regimen of MScontin and\noxycodone. Switched to 45 mg oxycontin PO q12h instead of MS contin upon\ndischarge as patient requiring frequent PRN for breakthrough. Of note ,\nback pain crosses lumbosacrum , radiates down legs bilaterally , and to\ngroin bilaterally. This distribution is consistent with a\nmore mucskuloskeletal etiology of pain , rather than R-sided\nnephrolithiasis.\nADDITIONAL COMMENTS: You must continue your medications , especially aspirin and plavix to\nprotect your stent. Continue the Ciprrfloxacin for your UTI. Follow up\nwith your doctors or call to reschedule the appointments. Call your\ndoctor or return to the ER if you have fever , chills , sweats , worsening\nshortness of breath , chest pain , or any other problems.\nDISCHARGE CONDITION: Stable\nTO DO/PLAN:\n1. Follow-up U/A.\n2. Consider CT scan to R/O renal CA given hx of microscopic hematuria\n3. Consider cystoscopy to R/O bladder CA given above.\n4. Med check\nNo dictated summary\nENTERED BY: HEMBRE , MARCELINO J. , M.D. , PH.D. ( PS482 ) 3/15/05 @ 01\n****** END OF DISCHARGE ORDERS ******\n[report_end]\n", "annotations": [{"medication_name": "acetylsalicylic acid", "medication_dosage": "325 mg", "mode": "po", "frequency": "qd", "line": "16"}, {"medication_name": "acetylsalicylic acid", "medication_dosage": "", "mode": "po", "frequency": "", "line": "19"}, {"medication_name": "ciprofloxacin", "medication_dosage": "250 mg", "mode": "po", "frequency": "q12h", "line": "22"}, {"medication_name": "antibiotics", "medication_dosage": "", "mode": "", "frequency": "", "line": "24"}, {"medication_name": "iron products", "medication_dosage": "", "mode": "", "frequency": "a minimum of 2 hours before or after a levofloxacin or ciprofloxacin dose dose if on tube feeds , please cycle ( hold 1 hr before to 2 hr after ) take 2 hours before or 2 hours after dairy products", "line": "26"}, {"medication_name": "ciprofloxacin", "medication_dosage": "", "mode": "", "frequency": "", "line": "27"}, {"medication_name": "levofloxacin", "medication_dosage": "", "mode": "", "frequency": "", "line": "27"}, {"medication_name": "colace ( docusate sodium )", "medication_dosage": "100 mg", "mode": "po", "frequency": "bid", "line": "30"}, {"medication_name": "folate ( folic acid )", "medication_dosage": "1 mg", "mode": "po", "frequency": "qd", "line": "32"}, {"medication_name": "glipizide", "medication_dosage": "5 mg", "mode": "po", "frequency": "q12h", "line": "33"}, {"medication_name": "lisinopril", "medication_dosage": "20 mg", "mode": "po", "frequency": "q12h", "line": "36"}, {"medication_name": "kcl immediate release", "medication_dosage": "", "mode": "po", "frequency": "", "line": "39"}, {"medication_name": "potassium chloride", "medication_dosage": "", "mode": "", "frequency": "", "line": "41"}, {"medication_name": "lisinopril", "medication_dosage": "", "mode": "", "frequency": "", "line": "41"}, {"medication_name": "kcl", "medication_dosage": "", "mode": "iv", "frequency": "", "line": "45"}, {"medication_name": "lisinopril", "medication_dosage": "", "mode": "", "frequency": "", "line": "46"}, {"medication_name": "potassium chloride", "medication_dosage": "", "mode": "", "frequency": "", "line": "46"}, {"medication_name": "kcl slow release", "medication_dosage": "", "mode": "po", "frequency": "", "line": "50"}, {"medication_name": "potassium chloride", "medication_dosage": "", "mode": "", "frequency": "", "line": "51"}, {"medication_name": "lisinopril", "medication_dosage": "", "mode": "", "frequency": "", "line": "51"}, {"medication_name": "k-lor", "medication_dosage": "", "mode": "po", "frequency": "", "line": "55"}, {"medication_name": "lisinopril", "medication_dosage": "", "mode": "", "frequency": "", "line": "56"}, {"medication_name": "potassium chloride", "medication_dosage": "", "mode": "", "frequency": "", "line": "56"}, {"medication_name": "potassium chloride", "medication_dosage": "", "mode": "", "frequency": "", "line": "60"}, {"medication_name": "lisinopril", "medication_dosage": "", "mode": "", "frequency": "", "line": "61"}, {"medication_name": "niferex-150", "medication_dosage": "150 mg", "mode": "po", "frequency": "bid", "line": "62"}, {"medication_name": "mvi therapeutic ( therapeutic multivitamins )", "medication_dosage": "1 tab", "mode": "po", "frequency": "qd", "line": "63"}, {"medication_name": "atorvastatin calcium", "medication_dosage": "", "mode": "", "frequency": "", "line": "65"}, {"medication_name": "vit. b-3", "medication_dosage": "", "mode": "", "frequency": "", "line": "66"}, {"medication_name": "niacin", "medication_dosage": "", "mode": "", "frequency": "", "line": "66"}, {"medication_name": "toprol xl ( metoprolol succinate extended release )", "medication_dosage": "100 mg", "mode": "po", "frequency": "q24h", "line": "67"}, {"medication_name": "ambien ( zolpidem tartrate )", "medication_dosage": "10 mg", "mode": "po", "frequency": "qhs prn", "line": "71"}, {"medication_name": "kcl slow release", "medication_dosage": "20 meq", "mode": "po", "frequency": "qd", "line": "75"}, {"medication_name": "potassium chloride", "medication_dosage": "20 meq", "mode": "", "frequency": "", "line": "76"}, {"medication_name": "lisinopril", "medication_dosage": "", "mode": "po", "frequency": "", "line": "78"}, {"medication_name": "potassium chloride", "medication_dosage": "", "mode": "", "frequency": "", "line": "79"}, {"medication_name": "lisinopril", "medication_dosage": "", "mode": "", "frequency": "", "line": "80"}, {"medication_name": "lipitor ( atorvastatin )", "medication_dosage": "40 mg", "mode": "po", "frequency": "qhs", "line": "81"}, {"medication_name": "mvi therapeutic", "medication_dosage": "", "mode": "po", "frequency": "", "line": "84"}, {"medication_name": "atorvastatin calcium", "medication_dosage": "", "mode": "", "frequency": "", "line": "85"}, {"medication_name": "vit. b-3", "medication_dosage": "", "mode": "", "frequency": "", "line": "86"}, {"medication_name": "niacin", "medication_dosage": "", "mode": "", "frequency": "", "line": "86"}, {"medication_name": "plavix ( clopidogrel )", "medication_dosage": "75 mg", "mode": "po", "frequency": "qd", "line": "87"}, {"medication_name": "candesartan", "medication_dosage": "16 mg", "mode": "po", "frequency": "qd", "line": "89"}, {"medication_name": "advair diskus 250/50 ( fluticasone propionate/... )", "medication_dosage": "1 puff", "mode": "inh", "frequency": "bid", "line": "91"}, {"medication_name": "lasix ( furosemide )", "medication_dosage": "40 mg", "mode": "po", "frequency": "bid", "line": "94"}, {"medication_name": "oxycontin ( oxycodone controlled release )", "medication_dosage": "45 mg", "mode": "po", "frequency": "q12h", "line": "96"}, {"medication_name": "percocet", "medication_dosage": "1 tab", "mode": "po", "frequency": "q4-6 hours prn", "line": "99"}, {"medication_name": "oxycontin", "medication_dosage": "", "mode": "", "frequency": "", "line": "101"}, {"medication_name": "albuterol inhaler", "medication_dosage": "2 puff", "mode": "inh", "frequency": "qid prn", "line": "102"}, {"medication_name": "albuterol nebulizer", "medication_dosage": "2.5 mg", "mode": "neb", "frequency": "q4h prn", "line": "104"}, {"medication_name": "metamucil sugar free ( psyllium ( metamucil ) su... )", "medication_dosage": "1-2 packet", "mode": "po", "frequency": "qd prn", "line": "106"}, {"medication_name": "nitroglycerin 1/150 ( 0.4 mg )", "medication_dosage": "1 tab", "mode": "sl", "frequency": "q5min x 3 doses prn", "line": "108"}, {"medication_name": "nitro", "medication_dosage": "", "mode": "", "frequency": "", "line": "110"}, {"medication_name": "percocet", "medication_dosage": "", "mode": "", "frequency": "", "line": "135"}, {"medication_name": "morphine", "medication_dosage": "", "mode": "", "frequency": "", "line": "135"}, {"medication_name": "asa", "medication_dosage": "", "mode": "", "frequency": "", "line": "139"}, {"medication_name": "mscontin", "medication_dosage": "", "mode": "", "frequency": "tid.", "line": "140"}, {"medication_name": "dilaudid", "medication_dosage": "", "mode": "", "frequency": "", "line": "142"}, {"medication_name": "morphine.", "medication_dosage": "", "mode": "", "frequency": "", "line": "143"}, {"medication_name": "oxycodone", "medication_dosage": "25 mg", "mode": "", "frequency": "", "line": "144"}, {"medication_name": "lasix", "medication_dosage": "", "mode": "", "frequency": "", "line": "151"}, {"medication_name": "ivf", "medication_dosage": "", "mode": "", "frequency": "", "line": "152"}, {"medication_name": "statin", "medication_dosage": "", "mode": "", "frequency": "", "line": "153"}, {"medication_name": "bb", "medication_dosage": "", "mode": "", "frequency": "", "line": "153"}, {"medication_name": "acei.", "medication_dosage": "", "mode": "", "frequency": "", "line": "153"}, {"medication_name": "asa", "medication_dosage": "", "mode": "", "frequency": "", "line": "153"}, {"medication_name": "ivf", "medication_dosage": "", "mode": "", "frequency": "", "line": "154"}, {"medication_name": "lasix.", "medication_dosage": "", "mode": "", "frequency": "", "line": "154"}, {"medication_name": "cipro", "medication_dosage": "250 mg", "mode": "po", "frequency": "", "line": "155"}, {"medication_name": "mscontin", "medication_dosage": "", "mode": "", "frequency": "", "line": "158"}, {"medication_name": "ms contin", "medication_dosage": "", "mode": "", "frequency": "", "line": "159"}, {"medication_name": "oxycontin", "medication_dosage": "45 mg", "mode": "po", "frequency": "q12h", "line": "159"}, {"medication_name": "oxycodone.", "medication_dosage": "", "mode": "", "frequency": "", "line": "159"}, {"medication_name": "plavix", "medication_dosage": "", "mode": "", "frequency": "", "line": "165"}, {"medication_name": "your medications", "medication_dosage": "", "mode": "", "frequency": "", "line": "165"}, {"medication_name": "aspirin", "medication_dosage": "", "mode": "", "frequency": "", "line": "165"}, {"medication_name": "ciprrfloxacin", "medication_dosage": "", "mode": "", "frequency": "", "line": "166"}]}