{"text": "RECORD #701307\n\n\n214970012 | MH | 93476909 | | 8756858 | 6/21/2006 12:00:00 AM | chest pain | | DIS | Admission Date: 6/19/2006 Report Status:\n\nDischarge Date: 3/13/2006\n****** FINAL DISCHARGE ORDERS ******\nDESIATO , LLOYD 443-91-88-7\nCharljer Ster Po\nService: CAR\nDISCHARGE PATIENT ON: 10/22/06 AT 02:00 PM\nCONTINGENT UPON HO evaluation\nWILL D/C ORDER BE USED AS THE D/C SUMMARY: YES\nAttending: STEINHART , JR , FEDERICO J. , M.D.\nDISPOSITION: Home\nDISCHARGE MEDICATIONS:\nAMIODARONE 200 MG PO BID\nECASA 325 MG PO QD\nISOSORBIDE DINITRATE 30 MG PO TID HOLD IF: sbp&lt;100\nLOPRESSOR ( METOPROLOL TARTRATE ) 50 MG PO BID\nHOLD IF: hr&lt;60 , SBP&lt;100 Food/Drug Interaction Instruction\nTake consistently with meals or on empty stomach.\nNITROGLYCERIN 1/150 ( 0.4 MG ) 1 TAB SL q5min x 3\nPRN chest pain HOLD IF: SBP &lt; 100\nKEFLEX ( CEPHALEXIN ) 500 MG PO QID\nInstructions: for chronic osteomyelitis right foot\nALTACE ( RAMIPRIL ) 1.25 MG PO QD\nAlert overridden: Override added on 0/9/06 by INGARGIOLA , CARMINE J D. , M.D.\nPOTENTIALLY SERIOUS INTERACTION: POTASSIUM CHLORIDE &amp;\nRAMIPRIL\nPOTENTIALLY SERIOUS INTERACTION: POTASSIUM CHLORIDE &amp;\nRAMIPRIL Reason for override: pt takes\nPLAVIX ( CLOPIDOGREL ) 75 MG PO QD\nNEXIUM ( ESOMEPRAZOLE ) 20 MG PO QD\nDIET: House / Low chol/low sat. fat\nACTIVITY: Resume regular exercise\nFOLLOW UP APPOINTMENT( S ):\nPlease see your PCP in Own within 2 weeks. ,\nALLERGY: statins\nADMIT DIAGNOSIS:\nchest pain\nPRINCIPAL DISCHARGE DIAGNOSIS ;Responsible After Study for Causing Admission )\nchest pain\nOTHER DIAGNOSIS;Conditions , Infections , Complications , affecting Treatment/Stay\nHTN CAD dyslipidemia\nOPERATIONS AND PROCEDURES:\nOTHER TREATMENTS/PROCEDURES ( NOT IN O.R. )\nETT\nBRIEF RESUME OF HOSPITAL COURSE:\n66 yo man w/ CAD s/p MI's ( 76 , 98 ) , and 2v CABG\n5/13 and stenting to grafts 5/12 and multiple admits at multiple\nhospitals in multiple states for CP evals presents with 10/10 CP.\nJust discharged same day for identical presentation at SGH where\nenzymes and ekg showed no ischemia despite ongoing CP , and adenosine\nmibi was poor study but could not rule out small area of ischemia in\nlat wall. He was not re-cath'd. Today at bus stop , developed\nrecurrence of CP and has not been responsive to NTG , and his enzyme on\npresentation was negative and ekg w/ only nonspecific Tw flat in\nII , III and V2-V3 previously noted.\nIn ED: 86 118/60 99%. Got sl Nitro x 2-&gt;BP 87/59 P86 118/60. Got sl\nntg x2-&gt; BP 87/59. cp 10/10-&gt;4/10. Pt sitting up laughing. c/o 6-7/10\ncp radiating to neck and jaw. sl ntg given w/out\nrelief. PMH: CAD MI '76 , '98 ( HMC ) , PCI 6/4 Poll Hospital\nSabeth Otte Den , s/p 2V CABG 5/13 Ocitor's Tianneyvass Gentburke Hospital , sternal surgery for Staph\ninfection 3/24 , PCI to grafts 6/7 Stillpen Hospital , + ETT w ?PCI\nCC 6/25 , PM placement 4/10 Di Pendsti adenosine-MIBI RCH\n9/11/06 -&gt;LVEF 68% , mild-mod lateral wall ischemia vs artifact 9/9 ,\nobsesity , GERD , chronic osteomyelitis rt foot on keflex , DM2 ( '92 ).\nCHF , pAF ( no t on coumadin ) , hyperlipidemia , HTN , CVA w left\nsided wkns meds:ASA 325 , amiodarone 200 bid , lopressor 50 bid ,\nimdur 60 bid , plavix 75 , protonix , keflex 500 q4 , lasix 60 bid , kcl\n40 qd , metformin 500 bid , micronase 10 bid , tylenol c codeine , ativan\n5 mg prn\nall: ?statins SH: divorced x2 , son died from HL age 10; son living\nin Pla Odownde Lake , quit tob 20 y ago , no etoh. antique dealer. FH:\nCAD; PE T 97 102/62 68 18\n98% Gen: obese in good spirit.\nNAD HEENT: JVP\nflat Cor: RRR , 3/6 SM\nUSB Pulm:\nCTA Abd:\nbenign Ext: no edema , 1 cm red spot rt ankle nontender;\nWWP neuro: slight dec strenth left\nside labs: Cr 1.8 ( bs 1.5 ) , CK 69 , 1.5 TnI&lt;ass , HCT 39 ,\nWBC 9 , PLT 354 INR 1.0 PTT 29 EKG: NSR 68 Twave flat II , III , V2-V3.\nno new changes.\nImpression: 66 yo M w h/o CAD s/p MI , CABG + PCI w recent admits for\nsame and ?+ MIBI 1/8 admitted with chest pain. high prob low-int\nrisk. CP in patient with known CAD and\nongoing RF's. While story and his behavior and presentation and lack\nof response to antianginal therapy , argue against ischemic , we will\nneed to monitor carefully\n1. CV ( I )tele. r/o w/ enzymes , ekg heparininze until ruled out , given\nongoing pain no further sL nitro given no relief and BP\ndrops continue asa , plavix , oral\nnitrate -ETT 1/5 2 min stopped 2/2 chest pain. no\nischemic EKG changes. ( P ) EF 68 %. euvolemic. cont\nnitrate. ( R ) tele. cont bblocker. NSR. monitor for pAF. cont\namiodarone. 2. Endo: check A1c. hold oral agents. SS.\n3. Renal: elevated BUN/Cr. gentle hydration. IVF 100 cc/h.\ntrend. 4. ID- chronic osteomyletis. cont keflex. normal\nWBC , afebrile. no sign of acute infection. 5. FEN: NPO. cont PPI for\nGERD. 5. ppx: PPI , sc hep.\n6. dispo: FC.\nADDITIONAL COMMENTS: please f/u with your PCP in Ton Ronatlleighing Rill You will need to discuss the issue\nstarting coumadin therapy given your history of atrial fibrillation.\nDISCHARGE CONDITION: Stable\nTO DO/PLAN:\nNo dictated summary\nENTERED BY: FAUPEL , LAWERENCE K. , M.D. , PH.D. ( LP51 ) 10/22/06 @ 11:08 AM\n****** END OF DISCHARGE ORDERS ******\n[report_end]\n", "annotations": [{"medication_name": "amiodarone", "medication_dosage": "200 mg", "mode": "po", "frequency": "bid", "line": "17"}, {"medication_name": "ecasa", "medication_dosage": "325 mg", "mode": "po", "frequency": "qd", "line": "18"}, {"medication_name": "isosorbide dinitrate", "medication_dosage": "30 mg", "mode": "po", "frequency": "tid", "line": "19"}, {"medication_name": "lopressor ( metoprolol tartrate )", "medication_dosage": "50 mg", "mode": "po", "frequency": "bid", "line": "20"}, {"medication_name": "nitroglycerin 1/150 ( 0.4 mg )", "medication_dosage": "1 tab", "mode": "sl", "frequency": "q5min", "line": "23"}, {"medication_name": "nitroglycerin 1/150 ( 0.4 mg )", "medication_dosage": "1 tab", "mode": "sl", "frequency": "q5min...prn", "line": "23"}, {"medication_name": "keflex ( cephalexin )", "medication_dosage": "500 mg", "mode": "po", "frequency": "qid", "line": "25"}, {"medication_name": "altace ( ramipril )", "medication_dosage": "1.25 mg", "mode": "po", "frequency": "qd", "line": "27"}, {"medication_name": "potassium chloride", "medication_dosage": "", "mode": "", "frequency": "", "line": "29"}, {"medication_name": "ramipril", "medication_dosage": "", "mode": "", "frequency": "", "line": "30"}, {"medication_name": "potassium chloride", "medication_dosage": "", "mode": "", "frequency": "", "line": "31"}, {"medication_name": "ramipril", "medication_dosage": "", "mode": "", "frequency": "", "line": "32"}, {"medication_name": "plavix ( clopidogrel )", "medication_dosage": "75 mg", "mode": "po", "frequency": "qd", "line": "33"}, {"medication_name": "nexium ( esomeprazole )", "medication_dosage": "20 mg", "mode": "po", "frequency": "qd", "line": "34"}, {"medication_name": "ntg", "medication_dosage": "", "mode": "", "frequency": "", "line": "57"}, {"medication_name": "nitro", "medication_dosage": "", "mode": "sl", "frequency": "", "line": "60"}, {"medication_name": "ntg", "medication_dosage": "", "mode": "sl", "frequency": "", "line": "61"}, {"medication_name": "ntg", "medication_dosage": "", "mode": "sl", "frequency": "", "line": "62"}, {"medication_name": "keflex", "medication_dosage": "", "mode": "", "frequency": "", "line": "68"}, {"medication_name": "meds:asa", "medication_dosage": "325", "mode": "", "frequency": "", "line": "70"}, {"medication_name": "lopressor", "medication_dosage": "50", "mode": "", "frequency": "bid", "line": "70"}, {"medication_name": "amiodarone", "medication_dosage": "200", "mode": "", "frequency": "bid", "line": "70"}, {"medication_name": "protonix", "medication_dosage": "", "mode": "", "frequency": "", "line": "71"}, {"medication_name": "plavix", "medication_dosage": "75", "mode": "", "frequency": "", "line": "71"}, {"medication_name": "imdur", "medication_dosage": "60", "mode": "", "frequency": "bid", "line": "71"}, {"medication_name": "lasix", "medication_dosage": "60", "mode": "", "frequency": "bid", "line": "71"}, {"medication_name": "kcl", "medication_dosage": "40", "mode": "", "frequency": "qd", "line": "71"}, {"medication_name": "keflex", "medication_dosage": "500", "mode": "", "frequency": "q4", "line": "71"}, {"medication_name": "tylenol c codeine", "medication_dosage": "", "mode": "", "frequency": "", "line": "72"}, {"medication_name": "metformin", "medication_dosage": "500", "mode": "", "frequency": "bid", "line": "72"}, {"medication_name": "ativan", "medication_dosage": "5 mg", "mode": "", "frequency": "prn", "line": "72"}, {"medication_name": "micronase", "medication_dosage": "10", "mode": "", "frequency": "bid", "line": "72"}, {"medication_name": "antianginal therapy", "medication_dosage": "", "mode": "", "frequency": "", "line": "91"}, {"medication_name": "nitro", "medication_dosage": "", "mode": "sl", "frequency": "", "line": "94"}, {"medication_name": "asa", "medication_dosage": "", "mode": "", "frequency": "", "line": "95"}, {"medication_name": "plavix", "medication_dosage": "", "mode": "", "frequency": "", "line": "95"}, {"medication_name": "nitrate", "medication_dosage": "", "mode": "oral", "frequency": "", "line": "96"}, {"medication_name": "nitrate.", "medication_dosage": "", "mode": "", "frequency": "", "line": "98"}, {"medication_name": "bblocker.", "medication_dosage": "", "mode": "", "frequency": "", "line": "98"}, {"medication_name": "amiodarone.", "medication_dosage": "", "mode": "", "frequency": "", "line": "99"}, {"medication_name": "agents.", "medication_dosage": "", "mode": "oral", "frequency": "", "line": "99"}, {"medication_name": "ivf", "medication_dosage": "100 cc/h.", "mode": "", "frequency": "", "line": "100"}, {"medication_name": "keflex.", "medication_dosage": "", "mode": "", "frequency": "", "line": "101"}, {"medication_name": "ppi", "medication_dosage": "", "mode": "", "frequency": "", "line": "102"}, {"medication_name": "ppi", "medication_dosage": "", "mode": "", "frequency": "", "line": "103"}, {"medication_name": "hep.", "medication_dosage": "", "mode": "sc", "frequency": "", "line": "103"}, {"medication_name": "coumadin", "medication_dosage": "", "mode": "", "frequency": "", "line": "106"}]}