{"text": "RECORD #941312\n955804700 | KPMMCO | 96181967 | | 1176706 | 5/8/2005 12:00:00 AM | CHF , pneumonia | | DIS | Admission Date: 0/28/2005 Report Status:\nDischarge Date: 10/15/2005\n****** FINAL DISCHARGE ORDERS ******\nSAMU , CURTIS 759-74-53-9\nBeth Ba Ri\nService: MED\nDISCHARGE PATIENT ON: 1/29/05 AT 04:00 PM\nCONTINGENT UPON Attending evaluation\nWILL D/C ORDER BE USED AS THE D/C SUMMARY: YES\nAttending: TIMBERLAKE , MEL WYATT , M.D.\nCODE STATUS:\nFull code\nDISPOSITION: Assisted Living\nDISCHARGE MEDICATIONS:\nACETYLSALICYLIC ACID 81 MG PO QD\nOverride Notice: Override added on 6/17/05 by\nTHEUNISSEN , LYNWOOD D.\non order for COUMADIN PO ( ref # 29937145 )\nPOTENTIALLY SERIOUS INTERACTION: ASPIRIN &amp; WARFARIN\nReason for override: aware Previous override information:\nOverride added on 8/0/05 by BOURNS , WALTON JERALD , M.D.\non order for COUMADIN PO ( ref # 50397676 )\nPOTENTIALLY SERIOUS INTERACTION: ASPIRIN &amp; WARFARIN\nReason for override: aware\nDIGOXIN 0.125 MG PO QD\nOverride Notice: Override added on 8/0/05 by CHRISTOFFERSE , KRIS MARCELLUS , M.D.\non order for LEVOTHYROXINE SODIUM PO ( ref # 13700176 )\nPOTENTIALLY SERIOUS INTERACTION: DIGOXIN &amp; LEVOTHYROXINE\nSODIUM Reason for override: aware\nCOLACE ( DOCUSATE SODIUM ) 100 MG PO BID\nFERROUS SULFATE 325 MG PO BID\nFood/Drug Interaction Instruction Avoid milk and antacid\nMOTRIN ( IBUPROFEN ) 600 MG PO Q8H Starting Today ( 10/7 )\nPRN Pain Food/Drug Interaction Instruction Take with food\nLEVOTHYROXINE SODIUM 75 MCG PO QD\nOverride Notice: Override added on 6/17/05 by\nCONNELLY , ELIAS E.\non order for COUMADIN PO ( ref # 29937145 )\nSERIOUS INTERACTION: LEVOTHYROXINE SODIUM &amp; WARFARIN\nReason for override: aware Previous override information:\nOverride added on 8/0/05 by ORMONDE , GUY NICHOLAS , M.D.\nPOTENTIALLY SERIOUS INTERACTION: DIGOXIN &amp; LEVOTHYROXINE\nSODIUM SERIOUS INTERACTION: WARFARIN &amp; LEVOTHYROXINE SODIUM\nReason for override: aware\nREGLAN ( METOCLOPRAMIDE HCL ) 5 MG PO AC\nSIMETHICONE 80 MG PO QID\nVITAMIN B1 ( THIAMINE HCL ) 100 MG PO QD\nTRAZODONE 50 MG PO HS\nCOUMADIN ( WARFARIN SODIUM ) 5 MG PO QPM\nStarting ROUTINE , 20:00 ( Standard Admin Time )\nFood/Drug Interaction Instruction\nNo high Vitamin-K containing foods\nAlert overridden: Override added on 6/17/05 by\nMORKVE , OLLIE J.\nPOTENTIALLY SERIOUS INTERACTION: ASPIRIN &amp; WARFARIN\nSERIOUS INTERACTION: LEVOTHYROXINE SODIUM &amp; WARFARIN\nPOTENTIALLY SERIOUS INTERACTION: SIMVASTATIN &amp; WARFARIN\nPOTENTIALLY SERIOUS INTERACTION: LEVOFLOXACIN &amp; WARFARIN\nPOTENTIALLY SERIOUS INTERACTION: LEVOFLOXACIN &amp; WARFARIN\nReason for override: aware\nMVI THERAPEUTIC ( THERAPEUTIC MULTIVITAMINS ) 1 TAB PO QD\nAlert overridden: Override added on 8/0/05 by\nMUNGO , KOREY DEON , M.D.\nPOTENTIALLY SERIOUS INTERACTION: SIMVASTATIN &amp; NIACIN ,\nVIT. B-3 Reason for override: aware\nTOPROL XL ( METOPROLOL SUCCINATE EXTENDED RELEASE )\n75 MG PO QD Food/Drug Interaction Instruction\nTake consistently with meals or on empty stomach.\nNumber of Doses Required ( approximate ): 10\nGABAPENTIN 200 MG PO QD\nTORSEMIDE 100 MG PO BID\nCOZAAR ( LOSARTAN ) 50 MG PO QD\nNumber of Doses Required ( approximate ): 10\nLEVOCARNITINE 1 GM PO QD Starting Today ( 8/21 )\nInstructions: on 15 ml at home\nNumber of Doses Required ( approximate ): 10\nCITALOPRAM 20 MG PO QD\nADVAIR DISKUS 250/50 ( FLUTICASONE PROPIONATE/... )\n1 PUFF INH BID\nOverride Notice: Override added on 8/0/05 by WHITESELL , OTIS DARRICK , M.D.\non order for LEVOFLOXACIN PO ( ref # 24 of June )\nPOTENTIALLY SERIOUS INTERACTION: SALMETEROL XINAFOATE &amp;\nLEVOFLOXACIN Reason for override: aware\nNEXIUM ( ESOMEPRAZOLE ) 20 MG PO QD\nLANTUS ( INSULIN GLARGINE ) 60 UNITS SC QHS\nNOVOLOG ( INSULIN ASPART )\nSliding Scale ( subcutaneously ) SC AC\nIf BS is less than 125 , then give 0 units subcutaneously\nIf BS is 125-150 , then give 2 units subcutaneously\nIf BS is 151-200 , then give 3 units subcutaneously\nIf BS is 201-250 , then give 4 units subcutaneously\nIf BS is 251-300 , then give 6 units subcutaneously\nIf BS is 301-350 , then give 8 units subcutaneously\nIf BS is 351-400 , then give 10 units subcutaneously and\ncall HO Call HO if BS is greater than 400\nLIPITOR ( ATORVASTATIN ) 10 MG PO QPM\nAlert overridden: Override added on 6/17/05 by :\nPOTENTIALLY SERIOUS INTERACTION: NIACIN , VIT. B-3 &amp;\nATORVASTATIN CALCIUM\nPOTENTIALLY SERIOUS INTERACTION: WARFARIN &amp; ATORVASTATIN\nCALCIUM Reason for override: aware\nCOMBIVENT ( IPRATROPIUM AND ALBUTEROL SULFATE )\n2 PUFF INH QID\nDIET: House / Low chol/low sat. fat\nDIET: House / ADA 1800 cals/dy\nDIET: 2 gram Sodium\nACTIVITY: Resume regular exercise\nFOLLOW UP APPOINTMENT( S ):\nFollow up with you Primary Care Provider within the next two weeks ,\nArrange INR to be drawn on 8/17/05 with f/u INR's to be drawn every\n2 days. INR's will be followed by Dr. Hechinger AH\nALLERGY: SHRIMP\nADMIT DIAGNOSIS:\nCHF , pneumonia\nPRINCIPAL DISCHARGE DIAGNOSIS ;Responsible After Study for Causing Admission )\nCHF , pneumonia\nOTHER DIAGNOSIS;Conditions , Infections , Complications , affecting Treatment/Stay\nAdriamycin induced CMP HTN IDDM Sarcoid\nLeft Breast CA- s/p lumpect and XRT/Adria-'84 hypercholesterolemia\n? GI origin of epigastric pain dvt ( deep venous thrombosis )\nosteoarthritis ( unspecified or generalized OA ) hypothyroid\n( hypothyroidism ) cad ( )\nOPERATIONS AND PROCEDURES:\nnone\nOTHER TREATMENTS/PROCEDURES ( NOT IN O.R. )\nMidline placed on 8/10 for blood draws but did not work. Midline taken\nout before discharge.\nBRIEF RESUME OF HOSPITAL COURSE:\nCC: SOB\nHPI: 61 yo F with multiple medical problems , including dilated CMP ,\ns/p chemo and XRT for Breast CA , CAD , s/p MI , COPD , on occasional O2 ,\npresents with dry cough associated with some SOB x 2 days\nand increased DOE as well. At baseline pt is able to walk 1 block\n( with walker ) before DOE , now DOE after 1/2 block. Pt denies CP. Pt\nreports orthopnea and PND. Pt has chronic abd pain at baseline that\nhas been evaluated in the past with Abd CT , U/S showing sludge. Pt\nhas a Hx of increased Alk Phos. She reports no change in abd pain at\nthis time , except increased bloating. No increased leg edema ,\nbut reports increased in size of L arm. Pt also reports wheezing\nwithout increased O2 need at night. No sick contacts , no diarrhea , no\nconstipation.\n****\nPE on admission: VS: T97.8 HR73 BP113/71 RR18 O2Sat 92%\nGen: NAD\nHEENT: oropharynx clear , no JVD\nCV: distant heart sounds , 1/6 SEM\nPulm:ant. endexp wheezes , no crackles\nAbd: mild tenderness in epigastrium , RUQ , distended\nExt:Venous stasis , 1+ edema , L arm larger than R arm\n*****\nTests: ALK Phos: 627\nALT: 71\nAST: 65\nCard Enzymes: neg\nWBC: 6.4\nUA: 1.011 , 1+prot , 5-10WBC , 2+bact\nCXR: LLL opacity , seen best on lateral view\nEKG: prolonged PR , q in AVL , flat Ts laterally , unchanged from 9/5\nRUQ US: sludge , gall bladder wall thickened 8mm , neg sonographic\nMurphy's sign , B/L small pleural effusions\n2/4 Echo: EF 25% , LV mild to mod dilated at 4.2cm , some RWMA ,\nmod-severe MR\n6/7 Abd U/S: sludge in gallbladder\n2/4 Abd CT: Ascites\n2/4 PE protocol CT: mild edema , bilat. effusions , anasarca\n**********************************************************************\nHOSPITAL COURSE:\n61F with LLL PNA and CHF\n1. ) ID: Pt placed on po levofloxacin for LLL pneumonia. She received a 7\ndays course and symptoms resolved. Stable vitals and O2 sats.\n2. ) Pulm: HX of CHF. Pt's weight 227lbs 7/6/05 ( dry weight ~ 200 ). Pt\non torsemide 100mg bid at baseline. Pt given po lasix ( in place of\ntorsemide on admit ) and was increased to 200bid x 2 doses. Then , pt\nplaced back on torsemide and zaroxyln 5mg po BID x 6 doses was added.\nLytes closely monitored , however , pt was difficult to draw\nblood from secondary to poor access. Followed daily weights. On D/C , pt's\nbreathing was improved and she was ambulating with walker @ her baseline..\nLungs were clear and pt still had BLE edema on d/c.\n3. ) GI: Hx of gallbladder sludge , with chronic RUQ pain , w/u with CT and\nUS in the past , but pt not surgical candidate. RUQ US showed just sludge ,\ngallbladder wall thickened 8mm , neg sonographic murphy's sign.\n4. ) Rheum- 6/26 pt c/o right thumb pain- thumb was\nred , warm , and painful to touch at joint. Pt has h/o gout-\nwas started on motrin TID.\n6. ) Endo- BS were high during hospitalization and insulin was adjusted\nappropriately. Lantus increased to 60mg QHS and novolog 8u QAC and\nsliding scale. Pt will be d/c'd home on lantus 60u QHS with novolog\nsliding scale.\n7. ) Heme- Pt was restarted on coumadin 5mg po QD for DVT on\n5/16 Follow up INR to be drawn on 11/2 INR on 6/26 was 1.2.\nFULL CODE.\nADDITIONAL COMMENTS: 1. ) Primary care follow up to check lytes on torsemide.\n2. ) INR checks to be arranged by RMC and coumadin dosing to be called\ninto Ak Heim pharmacy.\n3. ) Monitor weight 2x/week\n4. ) VNA arranged\nDISCHARGE CONDITION: Stable\nTO DO/PLAN:\n1. INR to be checked on 0/29 ( goal 2-3 ). Pt sent home on coumadin 5mg po\nQHS. INR results interepreted by NH and coumadin dose should be calle\ninto A Larepitbrown Lyoco pharmacy 862-435-6102.\n2. Continue diuresis with torsemide 100mg twice a day and monitor\nweights 2x/week. Keep legs elevated while in bed to help reduce swelling.\n3. Please make follow up appointment with Dr. Danahy within the\nnext two weeks. You will need follow up blood work.\n4. Take motrin 600mg as needed for your thumb pain. Once pain resolves ,\nresume taking your allopurinol 100mg daily for gout prophylaxis.\n5. Your lantus insulin dose was increased to 60units at night. Please\ncontinue your sliding scale as usual.\n6. You no longer need procrit , as your blood levels were within normal\nrange. Follow up with your PCP for bloodwork monitoring.\n7. Contact your primary care provider or come to the emergency room if\nyou experience difficulty breathing , chest pain , or fever.\nNo dictated summary\nENTERED BY: FLY , RENATO T. ( GN51 ) 1/29/05 @ 01:29 PM\n****** END OF DISCHARGE ORDERS ******\n[report_end]\n", "annotations": [{"medication_name": "acetylsalicylic acid", "medication_dosage": "81 mg", "mode": "po", "frequency": "qd", "line": "16"}, {"medication_name": "coumadin", "medication_dosage": "", "mode": "po", "frequency": "", "line": "19"}, {"medication_name": "warfarin", "medication_dosage": "", "mode": "", "frequency": "", "line": "20"}, {"medication_name": "aspirin", "medication_dosage": "", "mode": "", "frequency": "", "line": "20"}, {"medication_name": "coumadin", "medication_dosage": "", "mode": "po", "frequency": "", "line": "23"}, {"medication_name": "warfarin", "medication_dosage": "", "mode": "", "frequency": "", "line": "24"}, {"medication_name": "aspirin", "medication_dosage": "", "mode": "", "frequency": "", "line": "24"}, {"medication_name": "digoxin", "medication_dosage": "0.125 mg", "mode": "po", "frequency": "qd", "line": "26"}, {"medication_name": "levothyroxine sodium", "medication_dosage": "", "mode": "po", "frequency": "", "line": "28"}, {"medication_name": "levothyroxine sodium", "medication_dosage": "", "mode": "", "frequency": "", "line": "29"}, {"medication_name": "digoxin", "medication_dosage": "", "mode": "", "frequency": "", "line": "29"}, {"medication_name": "colace ( docusate sodium )", "medication_dosage": "100 mg", "mode": "po", "frequency": "bid", "line": "31"}, {"medication_name": "ferrous sulfate", "medication_dosage": "325 mg", "mode": "po", "frequency": "bid", "line": "32"}, {"medication_name": "motrin ( ibuprofen )", "medication_dosage": "600 mg", "mode": "po", "frequency": "q8h...prn", "line": "34"}, {"medication_name": "levothyroxine sodium", "medication_dosage": "75 mcg", "mode": "po", "frequency": "qd", "line": "36"}, {"medication_name": "coumadin", "medication_dosage": "", "mode": "po", "frequency": "", "line": "39"}, {"medication_name": "levothyroxine sodium", "medication_dosage": "", "mode": "", "frequency": "", "line": "40"}, {"medication_name": "warfarin", "medication_dosage": "", "mode": "", "frequency": "", "line": "40"}, {"medication_name": "levothyroxine sodium", "medication_dosage": "", "mode": "", "frequency": "", "line": "43"}, {"medication_name": "digoxin", "medication_dosage": "", "mode": "", "frequency": "", "line": "43"}, {"medication_name": "warfarin", "medication_dosage": "", "mode": "", "frequency": "", "line": "44"}, {"medication_name": "levothyroxine sodium", "medication_dosage": "", "mode": "", "frequency": "", "line": "44"}, {"medication_name": "reglan ( metoclopramide hcl )", "medication_dosage": "5 mg", "mode": "po", "frequency": "ac", "line": "46"}, {"medication_name": "simethicone", "medication_dosage": "80 mg", "mode": "po", "frequency": "qid", "line": "47"}, {"medication_name": "vitamin b1 ( thiamine hcl )", "medication_dosage": "100 mg", "mode": "po", "frequency": "qd", "line": "48"}, {"medication_name": "trazodone", "medication_dosage": "50 mg", "mode": "po", "frequency": "hs", "line": "49"}, {"medication_name": "coumadin ( warfarin sodium )", "medication_dosage": "5 mg", "mode": "po", "frequency": "qpm", "line": "50"}, {"medication_name": "aspirin", "medication_dosage": "", "mode": "", "frequency": "", "line": "56"}, {"medication_name": "warfarin", "medication_dosage": "", "mode": "", "frequency": "", "line": "56"}, {"medication_name": "levothyroxine sodium", "medication_dosage": "", "mode": "", "frequency": "", "line": "57"}, {"medication_name": "warfarin", "medication_dosage": "", "mode": "", "frequency": "", "line": "57"}, {"medication_name": "warfarin", "medication_dosage": "", "mode": "", "frequency": "", "line": "58"}, {"medication_name": "simvastatin", "medication_dosage": "", "mode": "", "frequency": "", "line": "58"}, {"medication_name": "warfarin", "medication_dosage": "", "mode": "", "frequency": "", "line": "59"}, {"medication_name": "levofloxacin", "medication_dosage": "", "mode": "", "frequency": "", "line": "59"}, {"medication_name": "levofloxacin", "medication_dosage": "", "mode": "", "frequency": "", "line": "60"}, {"medication_name": "warfarin", "medication_dosage": "", "mode": "", "frequency": "", "line": "60"}, {"medication_name": "mvi therapeutic ( therapeutic multivitamins )", "medication_dosage": "1 tab", "mode": "po", "frequency": "qd", "line": "62"}, {"medication_name": "niacin", "medication_dosage": "", "mode": "", "frequency": "", "line": "65"}, {"medication_name": "simvastatin", "medication_dosage": "", "mode": "", "frequency": "", "line": "65"}, {"medication_name": "vit. b-3", "medication_dosage": "", "mode": "", "frequency": "", "line": "66"}, {"medication_name": "toprol xl ( metoprolol succinate extended release )", "medication_dosage": "75 mg", "mode": "po", "frequency": "qd", "line": "67"}, {"medication_name": "gabapentin", "medication_dosage": "200 mg", "mode": "po", "frequency": "qd", "line": "71"}, {"medication_name": "torsemide", "medication_dosage": "100 mg", "mode": "po", "frequency": "bid", "line": "72"}, {"medication_name": "cozaar ( losartan )", "medication_dosage": "50 mg", "mode": "po", "frequency": "qd", "line": "73"}, {"medication_name": "levocarnitine", "medication_dosage": "1 gm", "mode": "po", "frequency": "qd", "line": "75"}, {"medication_name": "citalopram", "medication_dosage": "20 mg", "mode": "po", "frequency": "qd", "line": "78"}, {"medication_name": "advair diskus 250/50 ( fluticasone propionate/... )", "medication_dosage": "1 puff", "mode": "inh", "frequency": "bid", "line": "79"}, {"medication_name": "levofloxacin", "medication_dosage": "", "mode": "po", "frequency": "", "line": "82"}, {"medication_name": "salmeterol xinafoate", "medication_dosage": "", "mode": "", "frequency": "", "line": "83"}, {"medication_name": "levofloxacin", "medication_dosage": "", "mode": "", "frequency": "", "line": "84"}, {"medication_name": "nexium ( esomeprazole )", "medication_dosage": "20 mg", "mode": "po", "frequency": "qd", "line": "85"}, {"medication_name": "lantus ( insulin glargine )", "medication_dosage": "60 units", "mode": "sc", "frequency": "qhs", "line": "86"}, {"medication_name": "novolog ( insulin aspart )", "medication_dosage": "4 units", "mode": "subcutaneously", "frequency": "", "line": "87"}, {"medication_name": "novolog ( insulin aspart )", "medication_dosage": "6 units", "mode": "subcutaneously", "frequency": "", "line": "87"}, {"medication_name": "novolog ( insulin aspart )", "medication_dosage": "2 units", "mode": "subcutaneously", "frequency": "", "line": "87"}, {"medication_name": "novolog ( insulin aspart )", "medication_dosage": "10 units", "mode": "subcutaneously", "frequency": "", "line": "87"}, {"medication_name": "novolog ( insulin aspart )", "medication_dosage": "sliding scale", "mode": "( subcutaneously ) sc", "frequency": "ac", "line": "87"}, {"medication_name": "novolog ( insulin aspart )", "medication_dosage": "8 units", "mode": "subcutaneously", "frequency": "", "line": "87"}, {"medication_name": "novolog ( insulin aspart )", "medication_dosage": "3 units", "mode": "subcutaneously", "frequency": "", "line": "87"}, {"medication_name": "novolog ( insulin aspart )", "medication_dosage": "0 units", "mode": "subcutaneously", "frequency": "", "line": "87"}, {"medication_name": "lipitor ( atorvastatin )", "medication_dosage": "10 mg", "mode": "po", "frequency": "qpm", "line": "97"}, {"medication_name": "vit. b-3", "medication_dosage": "", "mode": "", "frequency": "", "line": "99"}, {"medication_name": "niacin", "medication_dosage": "", "mode": "", "frequency": "", "line": "99"}, {"medication_name": "atorvastatin calcium", "medication_dosage": "", "mode": "", "frequency": "", "line": "100"}, {"medication_name": "atorvastatin calcium", "medication_dosage": "", "mode": "", "frequency": "", "line": "101"}, {"medication_name": "warfarin", "medication_dosage": "", "mode": "", "frequency": "", "line": "101"}, {"medication_name": "combivent ( ipratropium and albuterol sulfate )", "medication_dosage": "2 puff", "mode": "inh", "frequency": "qid", "line": "103"}, {"medication_name": "adriamycin", "medication_dosage": "", "mode": "", "frequency": "", "line": "119"}, {"medication_name": "levofloxacin", "medication_dosage": "", "mode": "po", "frequency": "", "line": "170"}, {"medication_name": "torsemide", "medication_dosage": "100mg", "mode": "", "frequency": "bid", "line": "173"}, {"medication_name": "lasix", "medication_dosage": "", "mode": "po", "frequency": "", "line": "173"}, {"medication_name": "lasix", "medication_dosage": "200bid", "mode": "", "frequency": "", "line": "173"}, {"medication_name": "torsemide", "medication_dosage": "", "mode": "", "frequency": "", "line": "174"}, {"medication_name": "torsemide", "medication_dosage": "", "mode": "", "frequency": "", "line": "175"}, {"medication_name": "zaroxyln", "medication_dosage": "5mg", "mode": "po", "frequency": "bid", "line": "175"}, {"medication_name": "motrin", "medication_dosage": "", "mode": "", "frequency": "tid.", "line": "185"}, {"medication_name": "insulin", "medication_dosage": "", "mode": "", "frequency": "", "line": "186"}, {"medication_name": "novolog", "medication_dosage": "8u", "mode": "", "frequency": "qac", "line": "187"}, {"medication_name": "lantus", "medication_dosage": "60mg", "mode": "", "frequency": "qhs", "line": "187"}, {"medication_name": "novolog", "medication_dosage": "sliding scale", "mode": "", "frequency": "qac", "line": "187"}, {"medication_name": "lantus", "medication_dosage": "", "mode": "", "frequency": "", "line": "187"}, {"medication_name": "lantus", "medication_dosage": "60u", "mode": "", "frequency": "qhs", "line": "188"}, {"medication_name": "novolog", "medication_dosage": "sliding scale.", "mode": "", "frequency": "", "line": "188"}, {"medication_name": "coumadin", "medication_dosage": "5mg", "mode": "po", "frequency": "qd", "line": "190"}, {"medication_name": "torsemide.", "medication_dosage": "", "mode": "", "frequency": "", "line": "193"}, {"medication_name": "coumadin", "medication_dosage": "", "mode": "", "frequency": "", "line": "194"}, {"medication_name": "coumadin", "medication_dosage": "5mg", "mode": "po", "frequency": "qhs.", "line": "200"}, {"medication_name": "coumadin", "medication_dosage": "", "mode": "", "frequency": "", "line": "201"}, {"medication_name": "torsemide", "medication_dosage": "100mg", "mode": "", "frequency": "twice a day", "line": "203"}, {"medication_name": "motrin", "medication_dosage": "600mg", "mode": "", "frequency": "as needed", "line": "207"}, {"medication_name": "allopurinol", "medication_dosage": "100mg", "mode": "", "frequency": "daily", "line": "208"}, {"medication_name": "lantus insulin", "medication_dosage": "60units", "mode": "", "frequency": "at night.", "line": "209"}]}